PM/iqdemap_bpsk/iqdemap_bpsk.v
`timescale 1ns / 1ps
//////////////////////////////////////////////////////////////////////////////////
// Company: 
// Engineer: 
// 
// Create Date:    15:18:14 12/09/2013 
// Design Name: 
// Module Name:    iqdemap_bpsk 
// Project Name: 
// Target Devices: 
// Tool versions: 
// Description: 
//
// Dependencies: 
//
// Revision: 
// Revision 0.01 - File Created
// Additional Comments: 
//
//////////////////////////////////////////////////////////////////////////////////
module iqdemap_bpsk(
                    input               CLK,
                    input               RST,
                    input               ce,
                    input               valid_i,
                    input signed [10:0] ar,
                    input signed [10:0] ai,
                    output reg          valid_o,
                    output reg [127:0]  writer_data,
                    output              valid_raw,
                    output reg [3:0]    raw
                    );

   reg [8:0]                            cnt;
   reg                                  write_data_output_flg;

   assign valid_raw = valid_o;
   
   
   always@(posedge CLK)
     begin
        if(!RST)
          begin
             cnt <= 0;
             
             valid_o <= 0;
             raw <= 0;
          end
        else
          begin
             if(write_data_output_flg)  
               begin
                  cnt <= 0;
                  write_data_output_flg <= 0;
                  valid_o <= 0;              
               end
             else
               begin
                  if(valid_i)
                    begin
                       raw <= ar;
                       writer_data[cnt] <= ((1 - ar) >> 1);
                       cnt <= cnt + 1;
                       if(cnt >= 128)
                         begin
                            write_data_output_flg <= 1;
                            valid_o <= 1;
                         end
                    end
                  else
                    begin
                       cnt <= 0;
                    end 
               end 
          end
        
     end
   

   
endmodule

PM/iqdemap_bpsk/test_iqdemap_bpsk.v

module test_iqdemap_bpsk;
   reg [127:0] reader_data;
   reg         reader_en;
   reg         clk,rst,start_update, busy;
   reg         valid,raw;
   reg [6:0]   cnt;
   reg signed [10:0]  ar;
   reg signed [10:0]  ai;
   
   
   initial begin rst=1;
      #1 rst=0;
      #2 rst=1;
      #3000 $finish;

   end
   initial
     begin
        $dumpvars;
        $dumpfile("stm.vcd");
        #0
          clk <= 0;
	    reader_data <= 128'habcdefabcdefabcdefabcdefabcdef;
        ai <= 0;
        cnt <= 0;
        
     end

   always #5         clk <= ~clk;

   always #10
     begin
        ar <= 1 - (reader_data[cnt] << 1);
        valid <= 1;
          cnt <= cnt + 1;
     end
   
   
   
   initial begin
      
      
   end // initial begin
   
   iqdemap_bpsk bpsk(.CLK(clk), .RST(rst), .valid_i(valid), .ce(ce), .ar(ar), .ai(ai));
   
   
endmodule

PM/iqdemap_bpsk/dump.vcd
$date
	Tue Dec 10 14:31:11 2013
$end
$version
	Icarus Verilog
$end
$timescale
	1ps
$end
$scope module test_iqdemap_bpsk $end
$var wire 1 ! ce $end
$var reg 11 " ai [10:0] $end
$var reg 11 # ar [10:0] $end
$var reg 1 $ clk $end
$var reg 7 % cnt [6:0] $end
$var reg 128 & reader_data [127:0] $end
$var reg 1 ' rst $end
$var reg 1 ( valid $end
$scope module bpsk $end
$var wire 1 ) CLK $end
$var wire 1 * RST $end
$var wire 11 + ai [10:0] $end
$var wire 11 , ar [10:0] $end
$var wire 1 ! ce $end
$var wire 1 - valid_i $end
$var wire 1 . valid_raw $end
$var reg 9 / cnt [8:0] $end
$var reg 4 0 raw [3:0] $end
$var reg 1 1 valid_o $end
$var reg 1 2 write_data_output_flg $end
$var reg 128 3 writer_data [127:0] $end
$upscope $end
$upscope $end
$enddefinitions $end
#0
$dumpvars
bx 3
x2
x1
bx 0
bx /
x.
x-
bx ,
b0 +
1*
0)
x(
1'
b101010111100110111101111101010111100110111101111101010111100110111101111101010111100110111101111101010111100110111101111 &
b0 %
0$
bx #
b0 "
z!
$end
#1000
0'
0*
#3000
1'
1*
#5000
b0 /
1$
1)
#10000
0$
0)
b1 %
1(
1-
b11111111111 #
b11111111111 ,
#15000
b1 /
bx1 3
b1111 0
1$
1)
#20000
0$
0)
b10 %
#25000
b10 /
bx11 3
1$
1)
#30000
0$
0)
b11 %
#35000
b11 /
bx111 3
1$
1)
#40000
0$
0)
b100 %
#45000
b100 /
bx1111 3
1$
1)
#50000
0$
0)
b101 %
b1 #
b1 ,
#55000
b101 /
bx01111 3
b1 0
1$
1)
#60000
0$
0)
b110 %
b11111111111 #
b11111111111 ,
#65000
b110 /
bx101111 3
b1111 0
1$
1)
#70000
0$
0)
b111 %
#75000
b111 /
bx1101111 3
1$
1)
#80000
0$
0)
b1000 %
#85000
b1000 /
bx11101111 3
1$
1)
#90000
0$
0)
b1001 %
#95000
b1001 /
bx111101111 3
1$
1)
#100000
0$
0)
b1010 %
b1 #
b1 ,
#105000
b1010 /
bx0111101111 3
b1 0
1$
1)
#110000
0$
0)
b1011 %
b11111111111 #
b11111111111 ,
#115000
b1011 /
bx10111101111 3
b1111 0
1$
1)
#120000
0$
0)
b1100 %
#125000
b1100 /
bx110111101111 3
1$
1)
#130000
0$
0)
b1101 %
b1 #
b1 ,
#135000
b1101 /
bx0110111101111 3
b1 0
1$
1)
#140000
0$
0)
b1110 %
#145000
b1110 /
bx00110111101111 3
1$
1)
#150000
0$
0)
b1111 %
b11111111111 #
b11111111111 ,
#155000
b1111 /
bx100110111101111 3
b1111 0
1$
1)
#160000
0$
0)
b10000 %
#165000
b10000 /
bx1100110111101111 3
1$
1)
#170000
0$
0)
b10001 %
#175000
b10001 /
bx11100110111101111 3
1$
1)
#180000
0$
0)
b10010 %
#185000
b10010 /
bx111100110111101111 3
1$
1)
#190000
0$
0)
b10011 %
b1 #
b1 ,
#195000
b10011 /
bx0111100110111101111 3
b1 0
1$
1)
#200000
0$
0)
b10100 %
b11111111111 #
b11111111111 ,
#205000
b10100 /
bx10111100110111101111 3
b1111 0
1$
1)
#210000
0$
0)
b10101 %
b1 #
b1 ,
#215000
b10101 /
bx010111100110111101111 3
b1 0
1$
1)
#220000
0$
0)
b10110 %
b11111111111 #
b11111111111 ,
#225000
b10110 /
bx1010111100110111101111 3
b1111 0
1$
1)
#230000
0$
0)
b10111 %
b1 #
b1 ,
#235000
b10111 /
bx01010111100110111101111 3
b1 0
1$
1)
#240000
0$
0)
b11000 %
b11111111111 #
b11111111111 ,
#245000
b11000 /
bx101010111100110111101111 3
b1111 0
1$
1)
#250000
0$
0)
b11001 %
#255000
b11001 /
bx1101010111100110111101111 3
1$
1)
#260000
0$
0)
b11010 %
#265000
b11010 /
bx11101010111100110111101111 3
1$
1)
#270000
0$
0)
b11011 %
#275000
b11011 /
bx111101010111100110111101111 3
1$
1)
#280000
0$
0)
b11100 %
#285000
b11100 /
bx1111101010111100110111101111 3
1$
1)
#290000
0$
0)
b11101 %
b1 #
b1 ,
#295000
b11101 /
bx01111101010111100110111101111 3
b1 0
1$
1)
#300000
0$
0)
b11110 %
b11111111111 #
b11111111111 ,
#305000
b11110 /
bx101111101010111100110111101111 3
b1111 0
1$
1)
#310000
0$
0)
b11111 %
#315000
b11111 /
bx1101111101010111100110111101111 3
1$
1)
#320000
0$
0)
b100000 %
#325000
b100000 /
bx11101111101010111100110111101111 3
1$
1)
#330000
0$
0)
b100001 %
#335000
b100001 /
bx111101111101010111100110111101111 3
1$
1)
#340000
0$
0)
b100010 %
b1 #
b1 ,
#345000
b100010 /
bx0111101111101010111100110111101111 3
b1 0
1$
1)
#350000
0$
0)
b100011 %
b11111111111 #
b11111111111 ,
#355000
b100011 /
bx10111101111101010111100110111101111 3
b1111 0
1$
1)
#360000
0$
0)
b100100 %
#365000
b100100 /
bx110111101111101010111100110111101111 3
1$
1)
#370000
0$
0)
b100101 %
b1 #
b1 ,
#375000
b100101 /
bx0110111101111101010111100110111101111 3
b1 0
1$
1)
#380000
0$
0)
b100110 %
#385000
b100110 /
bx00110111101111101010111100110111101111 3
1$
1)
#390000
0$
0)
b100111 %
b11111111111 #
b11111111111 ,
#395000
b100111 /
bx100110111101111101010111100110111101111 3
b1111 0
1$
1)
#400000
0$
0)
b101000 %
#405000
b101000 /
bx1100110111101111101010111100110111101111 3
1$
1)
#410000
0$
0)
b101001 %
#415000
b101001 /
bx11100110111101111101010111100110111101111 3
1$
1)
#420000
0$
0)
b101010 %
#425000
b101010 /
bx111100110111101111101010111100110111101111 3
1$
1)
#430000
0$
0)
b101011 %
b1 #
b1 ,
#435000
b101011 /
bx0111100110111101111101010111100110111101111 3
b1 0
1$
1)
#440000
0$
0)
b101100 %
b11111111111 #
b11111111111 ,
#445000
b101100 /
bx10111100110111101111101010111100110111101111 3
b1111 0
1$
1)
#450000
0$
0)
b101101 %
b1 #
b1 ,
#455000
b101101 /
bx010111100110111101111101010111100110111101111 3
b1 0
1$
1)
#460000
0$
0)
b101110 %
b11111111111 #
b11111111111 ,
#465000
b101110 /
bx1010111100110111101111101010111100110111101111 3
b1111 0
1$
1)
#470000
0$
0)
b101111 %
b1 #
b1 ,
#475000
b101111 /
bx01010111100110111101111101010111100110111101111 3
b1 0
1$
1)
#480000
0$
0)
b110000 %
b11111111111 #
b11111111111 ,
#485000
b110000 /
bx101010111100110111101111101010111100110111101111 3
b1111 0
1$
1)
#490000
0$
0)
b110001 %
#495000
b110001 /
bx1101010111100110111101111101010111100110111101111 3
1$
1)
#500000
0$
0)
b110010 %
#505000
b110010 /
bx11101010111100110111101111101010111100110111101111 3
1$
1)
#510000
0$
0)
b110011 %
#515000
b110011 /
bx111101010111100110111101111101010111100110111101111 3
1$
1)
#520000
0$
0)
b110100 %
#525000
b110100 /
bx1111101010111100110111101111101010111100110111101111 3
1$
1)
#530000
0$
0)
b110101 %
b1 #
b1 ,
#535000
b110101 /
bx01111101010111100110111101111101010111100110111101111 3
b1 0
1$
1)
#540000
0$
0)
b110110 %
b11111111111 #
b11111111111 ,
#545000
b110110 /
bx101111101010111100110111101111101010111100110111101111 3
b1111 0
1$
1)
#550000
0$
0)
b110111 %
#555000
b110111 /
bx1101111101010111100110111101111101010111100110111101111 3
1$
1)
#560000
0$
0)
b111000 %
#565000
b111000 /
bx11101111101010111100110111101111101010111100110111101111 3
1$
1)
#570000
0$
0)
b111001 %
#575000
b111001 /
bx111101111101010111100110111101111101010111100110111101111 3
1$
1)
#580000
0$
0)
b111010 %
b1 #
b1 ,
#585000
b111010 /
bx0111101111101010111100110111101111101010111100110111101111 3
b1 0
1$
1)
#590000
0$
0)
b111011 %
b11111111111 #
b11111111111 ,
#595000
b111011 /
bx10111101111101010111100110111101111101010111100110111101111 3
b1111 0
1$
1)
#600000
0$
0)
b111100 %
#605000
b111100 /
bx110111101111101010111100110111101111101010111100110111101111 3
1$
1)
#610000
0$
0)
b111101 %
b1 #
b1 ,
#615000
b111101 /
bx0110111101111101010111100110111101111101010111100110111101111 3
b1 0
1$
1)
#620000
0$
0)
b111110 %
#625000
b111110 /
bx00110111101111101010111100110111101111101010111100110111101111 3
1$
1)
#630000
0$
0)
b111111 %
b11111111111 #
b11111111111 ,
#635000
b111111 /
bx100110111101111101010111100110111101111101010111100110111101111 3
b1111 0
1$
1)
#640000
0$
0)
b1000000 %
#645000
b1000000 /
bx1100110111101111101010111100110111101111101010111100110111101111 3
1$
1)
#650000
0$
0)
b1000001 %
#655000
b1000001 /
bx11100110111101111101010111100110111101111101010111100110111101111 3
1$
1)
#660000
0$
0)
b1000010 %
#665000
b1000010 /
bx111100110111101111101010111100110111101111101010111100110111101111 3
1$
1)
#670000
0$
0)
b1000011 %
b1 #
b1 ,
#675000
b1000011 /
bx0111100110111101111101010111100110111101111101010111100110111101111 3
b1 0
1$
1)
#680000
0$
0)
b1000100 %
b11111111111 #
b11111111111 ,
#685000
b1000100 /
bx10111100110111101111101010111100110111101111101010111100110111101111 3
b1111 0
1$
1)
#690000
0$
0)
b1000101 %
b1 #
b1 ,
#695000
b1000101 /
bx010111100110111101111101010111100110111101111101010111100110111101111 3
b1 0
1$
1)
#700000
0$
0)
b1000110 %
b11111111111 #
b11111111111 ,
#705000
b1000110 /
bx1010111100110111101111101010111100110111101111101010111100110111101111 3
b1111 0
1$
1)
#710000
0$
0)
b1000111 %
b1 #
b1 ,
#715000
b1000111 /
bx01010111100110111101111101010111100110111101111101010111100110111101111 3
b1 0
1$
1)
#720000
0$
0)
b1001000 %
b11111111111 #
b11111111111 ,
#725000
b1001000 /
bx101010111100110111101111101010111100110111101111101010111100110111101111 3
b1111 0
1$
1)
#730000
0$
0)
b1001001 %
#735000
b1001001 /
bx1101010111100110111101111101010111100110111101111101010111100110111101111 3
1$
1)
#740000
0$
0)
b1001010 %
#745000
b1001010 /
bx11101010111100110111101111101010111100110111101111101010111100110111101111 3
1$
1)
#750000
0$
0)
b1001011 %
#755000
b1001011 /
bx111101010111100110111101111101010111100110111101111101010111100110111101111 3
1$
1)
#760000
0$
0)
b1001100 %
#765000
b1001100 /
bx1111101010111100110111101111101010111100110111101111101010111100110111101111 3
1$
1)
#770000
0$
0)
b1001101 %
b1 #
b1 ,
#775000
b1001101 /
bx01111101010111100110111101111101010111100110111101111101010111100110111101111 3
b1 0
1$
1)
#780000
0$
0)
b1001110 %
b11111111111 #
b11111111111 ,
#785000
b1001110 /
bx101111101010111100110111101111101010111100110111101111101010111100110111101111 3
b1111 0
1$
1)
#790000
0$
0)
b1001111 %
#795000
b1001111 /
bx1101111101010111100110111101111101010111100110111101111101010111100110111101111 3
1$
1)
#800000
0$
0)
b1010000 %
#805000
b1010000 /
bx11101111101010111100110111101111101010111100110111101111101010111100110111101111 3
1$
1)
#810000
0$
0)
b1010001 %
#815000
b1010001 /
bx111101111101010111100110111101111101010111100110111101111101010111100110111101111 3
1$
1)
#820000
0$
0)
b1010010 %
b1 #
b1 ,
#825000
b1010010 /
bx0111101111101010111100110111101111101010111100110111101111101010111100110111101111 3
b1 0
1$
1)
#830000
0$
0)
b1010011 %
b11111111111 #
b11111111111 ,
#835000
b1010011 /
bx10111101111101010111100110111101111101010111100110111101111101010111100110111101111 3
b1111 0
1$
1)
#840000
0$
0)
b1010100 %
#845000
b1010100 /
bx110111101111101010111100110111101111101010111100110111101111101010111100110111101111 3
1$
1)
#850000
0$
0)
b1010101 %
b1 #
b1 ,
#855000
b1010101 /
bx0110111101111101010111100110111101111101010111100110111101111101010111100110111101111 3
b1 0
1$
1)
#860000
0$
0)
b1010110 %
#865000
b1010110 /
bx00110111101111101010111100110111101111101010111100110111101111101010111100110111101111 3
1$
1)
#870000
0$
0)
b1010111 %
b11111111111 #
b11111111111 ,
#875000
b1010111 /
bx100110111101111101010111100110111101111101010111100110111101111101010111100110111101111 3
b1111 0
1$
1)
#880000
0$
0)
b1011000 %
#885000
b1011000 /
bx1100110111101111101010111100110111101111101010111100110111101111101010111100110111101111 3
1$
1)
#890000
0$
0)
b1011001 %
#895000
b1011001 /
bx11100110111101111101010111100110111101111101010111100110111101111101010111100110111101111 3
1$
1)
#900000
0$
0)
b1011010 %
#905000
b1011010 /
bx111100110111101111101010111100110111101111101010111100110111101111101010111100110111101111 3
1$
1)
#910000
0$
0)
b1011011 %
b1 #
b1 ,
#915000
b1011011 /
bx0111100110111101111101010111100110111101111101010111100110111101111101010111100110111101111 3
b1 0
1$
1)
#920000
0$
0)
b1011100 %
b11111111111 #
b11111111111 ,
#925000
b1011100 /
bx10111100110111101111101010111100110111101111101010111100110111101111101010111100110111101111 3
b1111 0
1$
1)
#930000
0$
0)
b1011101 %
b1 #
b1 ,
#935000
b1011101 /
bx010111100110111101111101010111100110111101111101010111100110111101111101010111100110111101111 3
b1 0
1$
1)
#940000
0$
0)
b1011110 %
b11111111111 #
b11111111111 ,
#945000
b1011110 /
bx1010111100110111101111101010111100110111101111101010111100110111101111101010111100110111101111 3
b1111 0
1$
1)
#950000
0$
0)
b1011111 %
b1 #
b1 ,
#955000
b1011111 /
bx01010111100110111101111101010111100110111101111101010111100110111101111101010111100110111101111 3
b1 0
1$
1)
#960000
0$
0)
b1100000 %
b11111111111 #
b11111111111 ,
#965000
b1100000 /
bx101010111100110111101111101010111100110111101111101010111100110111101111101010111100110111101111 3
b1111 0
1$
1)
#970000
0$
0)
b1100001 %
#975000
b1100001 /
bx1101010111100110111101111101010111100110111101111101010111100110111101111101010111100110111101111 3
1$
1)
#980000
0$
0)
b1100010 %
#985000
b1100010 /
bx11101010111100110111101111101010111100110111101111101010111100110111101111101010111100110111101111 3
1$
1)
#990000
0$
0)
b1100011 %
#995000
b1100011 /
bx111101010111100110111101111101010111100110111101111101010111100110111101111101010111100110111101111 3
1$
1)
#1000000
0$
0)
b1100100 %
#1005000
b1100100 /
bx1111101010111100110111101111101010111100110111101111101010111100110111101111101010111100110111101111 3
1$
1)
#1010000
0$
0)
b1100101 %
b1 #
b1 ,
#1015000
b1100101 /
bx01111101010111100110111101111101010111100110111101111101010111100110111101111101010111100110111101111 3
b1 0
1$
1)
#1020000
0$
0)
b1100110 %
b11111111111 #
b11111111111 ,
#1025000
b1100110 /
bx101111101010111100110111101111101010111100110111101111101010111100110111101111101010111100110111101111 3
b1111 0
1$
1)
#1030000
0$
0)
b1100111 %
#1035000
b1100111 /
bx1101111101010111100110111101111101010111100110111101111101010111100110111101111101010111100110111101111 3
1$
1)
#1040000
0$
0)
b1101000 %
#1045000
b1101000 /
bx11101111101010111100110111101111101010111100110111101111101010111100110111101111101010111100110111101111 3
1$
1)
#1050000
0$
0)
b1101001 %
#1055000
b1101001 /
bx111101111101010111100110111101111101010111100110111101111101010111100110111101111101010111100110111101111 3
1$
1)
#1060000
0$
0)
b1101010 %
b1 #
b1 ,
#1065000
b1101010 /
bx0111101111101010111100110111101111101010111100110111101111101010111100110111101111101010111100110111101111 3
b1 0
1$
1)
#1070000
0$
0)
b1101011 %
b11111111111 #
b11111111111 ,
#1075000
b1101011 /
bx10111101111101010111100110111101111101010111100110111101111101010111100110111101111101010111100110111101111 3
b1111 0
1$
1)
#1080000
0$
0)
b1101100 %
#1085000
b1101100 /
bx110111101111101010111100110111101111101010111100110111101111101010111100110111101111101010111100110111101111 3
1$
1)
#1090000
0$
0)
b1101101 %
b1 #
b1 ,
#1095000
b1101101 /
bx0110111101111101010111100110111101111101010111100110111101111101010111100110111101111101010111100110111101111 3
b1 0
1$
1)
#1100000
0$
0)
b1101110 %
#1105000
b1101110 /
bx00110111101111101010111100110111101111101010111100110111101111101010111100110111101111101010111100110111101111 3
1$
1)
#1110000
0$
0)
b1101111 %
b11111111111 #
b11111111111 ,
#1115000
b1101111 /
bx100110111101111101010111100110111101111101010111100110111101111101010111100110111101111101010111100110111101111 3
b1111 0
1$
1)
#1120000
0$
0)
b1110000 %
#1125000
b1110000 /
bx1100110111101111101010111100110111101111101010111100110111101111101010111100110111101111101010111100110111101111 3
1$
1)
#1130000
0$
0)
b1110001 %
#1135000
b1110001 /
bx11100110111101111101010111100110111101111101010111100110111101111101010111100110111101111101010111100110111101111 3
1$
1)
#1140000
0$
0)
b1110010 %
#1145000
b1110010 /
bx111100110111101111101010111100110111101111101010111100110111101111101010111100110111101111101010111100110111101111 3
1$
1)
#1150000
0$
0)
b1110011 %
b1 #
b1 ,
#1155000
b1110011 /
bx0111100110111101111101010111100110111101111101010111100110111101111101010111100110111101111101010111100110111101111 3
b1 0
1$
1)
#1160000
0$
0)
b1110100 %
b11111111111 #
b11111111111 ,
#1165000
b1110100 /
bx10111100110111101111101010111100110111101111101010111100110111101111101010111100110111101111101010111100110111101111 3
b1111 0
1$
1)
#1170000
0$
0)
b1110101 %
b1 #
b1 ,
#1175000
b1110101 /
bx010111100110111101111101010111100110111101111101010111100110111101111101010111100110111101111101010111100110111101111 3
b1 0
1$
1)
#1180000
0$
0)
b1110110 %
b11111111111 #
b11111111111 ,
#1185000
b1110110 /
bx1010111100110111101111101010111100110111101111101010111100110111101111101010111100110111101111101010111100110111101111 3
b1111 0
1$
1)
#1190000
0$
0)
b1110111 %
b1 #
b1 ,
#1195000
b1110111 /
bx01010111100110111101111101010111100110111101111101010111100110111101111101010111100110111101111101010111100110111101111 3
b1 0
1$
1)
#1200000
0$
0)
b1111000 %
b11111111111 #
b11111111111 ,
#1205000
b1111000 /
bx101010111100110111101111101010111100110111101111101010111100110111101111101010111100110111101111101010111100110111101111 3
b1111 0
1$
1)
#1210000
0$
0)
b1111001 %
b1 #
b1 ,
#1215000
b1111001 /
bx0101010111100110111101111101010111100110111101111101010111100110111101111101010111100110111101111101010111100110111101111 3
b1 0
1$
1)
#1220000
0$
0)
b1111010 %
#1225000
b1111010 /
bx00101010111100110111101111101010111100110111101111101010111100110111101111101010111100110111101111101010111100110111101111 3
1$
1)
#1230000
0$
0)
b1111011 %
#1235000
b1111011 /
bx000101010111100110111101111101010111100110111101111101010111100110111101111101010111100110111101111101010111100110111101111 3
1$
1)
#1240000
0$
0)
b1111100 %
#1245000
b1111100 /
bx0000101010111100110111101111101010111100110111101111101010111100110111101111101010111100110111101111101010111100110111101111 3
1$
1)
#1250000
0$
0)
b1111101 %
#1255000
b1111101 /
bx00000101010111100110111101111101010111100110111101111101010111100110111101111101010111100110111101111101010111100110111101111 3
1$
1)
#1260000
0$
0)
b1111110 %
#1265000
b1111110 /
bx000000101010111100110111101111101010111100110111101111101010111100110111101111101010111100110111101111101010111100110111101111 3
1$
1)
#1270000
0$
0)
b1111111 %
#1275000
b1111111 /
bx0000000101010111100110111101111101010111100110111101111101010111100110111101111101010111100110111101111101010111100110111101111 3
1$
1)
#1280000
0$
0)
b0 %
#1285000
b10000000 /
b101010111100110111101111101010111100110111101111101010111100110111101111101010111100110111101111101010111100110111101111 3
1$
1)
#1290000
0$
0)
b1 %
b11111111111 #
b11111111111 ,
#1295000
11
1.
12
b10000001 /
b1111 0
1$
1)
#1300000
0$
0)
b10 %
#1305000
01
0.
02
b0 /
1$
1)
#1310000
0$
0)
b11 %
#1315000
b1 /
b101010111100110111101111101010111100110111101111101010111100110111101111101010111100110111101111101010111100110111101111 3
1$
1)
#1320000
0$
0)
b100 %
#1325000
b10 /
b101010111100110111101111101010111100110111101111101010111100110111101111101010111100110111101111101010111100110111101111 3
1$
1)
#1330000
0$
0)
b101 %
b1 #
b1 ,
#1335000
b11 /
b101010111100110111101111101010111100110111101111101010111100110111101111101010111100110111101111101010111100110111101011 3
b1 0
1$
1)
#1340000
0$
0)
b110 %
b11111111111 #
b11111111111 ,
#1345000
b100 /
b101010111100110111101111101010111100110111101111101010111100110111101111101010111100110111101111101010111100110111101011 3
b1111 0
1$
1)
#1350000
0$
0)
b111 %
#1355000
b101 /
b101010111100110111101111101010111100110111101111101010111100110111101111101010111100110111101111101010111100110111111011 3
1$
1)
#1360000
0$
0)
b1000 %
#1365000
b110 /
b101010111100110111101111101010111100110111101111101010111100110111101111101010111100110111101111101010111100110111111011 3
1$
1)
#1370000
0$
0)
b1001 %
#1375000
b111 /
b101010111100110111101111101010111100110111101111101010111100110111101111101010111100110111101111101010111100110111111011 3
1$
1)
#1380000
0$
0)
b1010 %
b1 #
b1 ,
#1385000
b1000 /
b101010111100110111101111101010111100110111101111101010111100110111101111101010111100110111101111101010111100110101111011 3
b1 0
1$
1)
#1390000
0$
0)
b1011 %
b11111111111 #
b11111111111 ,
#1395000
b1001 /
b101010111100110111101111101010111100110111101111101010111100110111101111101010111100110111101111101010111100110101111011 3
b1111 0
1$
1)
#1400000
0$
0)
b1100 %
#1405000
b1010 /
b101010111100110111101111101010111100110111101111101010111100110111101111101010111100110111101111101010111100111101111011 3
1$
1)
#1410000
0$
0)
b1101 %
b1 #
b1 ,
#1415000
b1011 /
b101010111100110111101111101010111100110111101111101010111100110111101111101010111100110111101111101010111100101101111011 3
b1 0
1$
1)
#1420000
0$
0)
b1110 %
#1425000
b1100 /
b101010111100110111101111101010111100110111101111101010111100110111101111101010111100110111101111101010111100001101111011 3
1$
1)
#1430000
0$
0)
b1111 %
b11111111111 #
b11111111111 ,
#1435000
b1101 /
b101010111100110111101111101010111100110111101111101010111100110111101111101010111100110111101111101010111101001101111011 3
b1111 0
1$
1)
#1440000
0$
0)
b10000 %
#1445000
b1110 /
b101010111100110111101111101010111100110111101111101010111100110111101111101010111100110111101111101010111111001101111011 3
1$
1)
#1450000
0$
0)
b10001 %
#1455000
b1111 /
b101010111100110111101111101010111100110111101111101010111100110111101111101010111100110111101111101010111111001101111011 3
1$
1)
#1460000
0$
0)
b10010 %
#1465000
b10000 /
b101010111100110111101111101010111100110111101111101010111100110111101111101010111100110111101111101010111111001101111011 3
1$
1)
#1470000
0$
0)
b10011 %
b1 #
b1 ,
#1475000
b10001 /
b101010111100110111101111101010111100110111101111101010111100110111101111101010111100110111101111101010101111001101111011 3
b1 0
1$
1)
#1480000
0$
0)
b10100 %
b11111111111 #
b11111111111 ,
#1485000
b10010 /
b101010111100110111101111101010111100110111101111101010111100110111101111101010111100110111101111101010101111001101111011 3
b1111 0
1$
1)
#1490000
0$
0)
b10101 %
b1 #
b1 ,
#1495000
b10011 /
b101010111100110111101111101010111100110111101111101010111100110111101111101010111100110111101111101010101111001101111011 3
b1 0
1$
1)
#1500000
0$
0)
b10110 %
b11111111111 #
b11111111111 ,
#1505000
b10100 /
b101010111100110111101111101010111100110111101111101010111100110111101111101010111100110111101111101010101111001101111011 3
b1111 0
1$
1)
#1510000
0$
0)
b10111 %
b1 #
b1 ,
#1515000
b10101 /
b101010111100110111101111101010111100110111101111101010111100110111101111101010111100110111101111101010101111001101111011 3
b1 0
1$
1)
#1520000
0$
0)
b11000 %
b11111111111 #
b11111111111 ,
#1525000
b10110 /
b101010111100110111101111101010111100110111101111101010111100110111101111101010111100110111101111101010101111001101111011 3
b1111 0
1$
1)
#1530000
0$
0)
b11001 %
#1535000
b10111 /
b101010111100110111101111101010111100110111101111101010111100110111101111101010111100110111101111111010101111001101111011 3
1$
1)
#1540000
0$
0)
b11010 %
#1545000
b11000 /
b101010111100110111101111101010111100110111101111101010111100110111101111101010111100110111101111111010101111001101111011 3
1$
1)
#1550000
0$
0)
b11011 %
#1555000
b11001 /
b101010111100110111101111101010111100110111101111101010111100110111101111101010111100110111101111111010101111001101111011 3
1$
1)
#1560000
0$
0)
b11100 %
#1565000
b11010 /
b101010111100110111101111101010111100110111101111101010111100110111101111101010111100110111101111111010101111001101111011 3
1$
1)
#1570000
0$
0)
b11101 %
b1 #
b1 ,
#1575000
b11011 /
b101010111100110111101111101010111100110111101111101010111100110111101111101010111100110111101011111010101111001101111011 3
b1 0
1$
1)
#1580000
0$
0)
b11110 %
b11111111111 #
b11111111111 ,
#1585000
b11100 /
b101010111100110111101111101010111100110111101111101010111100110111101111101010111100110111101011111010101111001101111011 3
b1111 0
1$
1)
#1590000
0$
0)
b11111 %
#1595000
b11101 /
b101010111100110111101111101010111100110111101111101010111100110111101111101010111100110111111011111010101111001101111011 3
1$
1)
#1600000
0$
0)
b100000 %
#1605000
b11110 /
b101010111100110111101111101010111100110111101111101010111100110111101111101010111100110111111011111010101111001101111011 3
1$
1)
#1610000
0$
0)
b100001 %
#1615000
b11111 /
b101010111100110111101111101010111100110111101111101010111100110111101111101010111100110111111011111010101111001101111011 3
1$
1)
#1620000
0$
0)
b100010 %
b1 #
b1 ,
#1625000
b100000 /
b101010111100110111101111101010111100110111101111101010111100110111101111101010111100110101111011111010101111001101111011 3
b1 0
1$
1)
#1630000
0$
0)
b100011 %
b11111111111 #
b11111111111 ,
#1635000
b100001 /
b101010111100110111101111101010111100110111101111101010111100110111101111101010111100110101111011111010101111001101111011 3
b1111 0
1$
1)
#1640000
0$
0)
b100100 %
#1645000
b100010 /
b101010111100110111101111101010111100110111101111101010111100110111101111101010111100111101111011111010101111001101111011 3
1$
1)
#1650000
0$
0)
b100101 %
b1 #
b1 ,
#1655000
b100011 /
b101010111100110111101111101010111100110111101111101010111100110111101111101010111100101101111011111010101111001101111011 3
b1 0
1$
1)
#1660000
0$
0)
b100110 %
#1665000
b100100 /
b101010111100110111101111101010111100110111101111101010111100110111101111101010111100001101111011111010101111001101111011 3
1$
1)
#1670000
0$
0)
b100111 %
b11111111111 #
b11111111111 ,
#1675000
b100101 /
b101010111100110111101111101010111100110111101111101010111100110111101111101010111101001101111011111010101111001101111011 3
b1111 0
1$
1)
#1680000
0$
0)
b101000 %
#1685000
b100110 /
b101010111100110111101111101010111100110111101111101010111100110111101111101010111111001101111011111010101111001101111011 3
1$
1)
#1690000
0$
0)
b101001 %
#1695000
b100111 /
b101010111100110111101111101010111100110111101111101010111100110111101111101010111111001101111011111010101111001101111011 3
1$
1)
#1700000
0$
0)
b101010 %
#1705000
b101000 /
b101010111100110111101111101010111100110111101111101010111100110111101111101010111111001101111011111010101111001101111011 3
1$
1)
#1710000
0$
0)
b101011 %
b1 #
b1 ,
#1715000
b101001 /
b101010111100110111101111101010111100110111101111101010111100110111101111101010101111001101111011111010101111001101111011 3
b1 0
1$
1)
#1720000
0$
0)
b101100 %
b11111111111 #
b11111111111 ,
#1725000
b101010 /
b101010111100110111101111101010111100110111101111101010111100110111101111101010101111001101111011111010101111001101111011 3
b1111 0
1$
1)
#1730000
0$
0)
b101101 %
b1 #
b1 ,
#1735000
b101011 /
b101010111100110111101111101010111100110111101111101010111100110111101111101010101111001101111011111010101111001101111011 3
b1 0
1$
1)
#1740000
0$
0)
b101110 %
b11111111111 #
b11111111111 ,
#1745000
b101100 /
b101010111100110111101111101010111100110111101111101010111100110111101111101010101111001101111011111010101111001101111011 3
b1111 0
1$
1)
#1750000
0$
0)
b101111 %
b1 #
b1 ,
#1755000
b101101 /
b101010111100110111101111101010111100110111101111101010111100110111101111101010101111001101111011111010101111001101111011 3
b1 0
1$
1)
#1760000
0$
0)
b110000 %
b11111111111 #
b11111111111 ,
#1765000
b101110 /
b101010111100110111101111101010111100110111101111101010111100110111101111101010101111001101111011111010101111001101111011 3
b1111 0
1$
1)
#1770000
0$
0)
b110001 %
#1775000
b101111 /
b101010111100110111101111101010111100110111101111101010111100110111101111111010101111001101111011111010101111001101111011 3
1$
1)
#1780000
0$
0)
b110010 %
