PM/iqdemap_16qam/iqdemap_16qam.v
`timescale 1ns / 1ps

module iqdemap_qpsk(
                    input               CLK,
                    input               RST,
                    input               ce,
                    input               valid_i,
                    input signed [10:0] ar,
                    input signed [10:0] ai,
                    output reg          valid_o,
                    output reg [127:0]  writer_data,
                    output              valid_raw,
                    output reg [3:0]    raw
                    );

   reg [8:0]                            cnt;
   reg                                  write_data_output_flg;

   assign valid_raw = valid_o;
   
   
   always@(posedge CLK)
     begin
        if(!RST)
          begin
             valid_o <= 0;
             raw <= 0;
          end
        else
          begin
             if(write_data_output_flg)  
               begin
                  cnt <= 3;
                  write_data_output_flg <= 0;
                  valid_o <= 0;              
               end
             else
               begin
                  if(valid_i)
                    begin
                       raw <= ar;
                       case(ar)
                         3:
                           begin
                              writer_data[cnt-3] = 0;
                              writer_data[cnt-1] = 0;
                           end
                         1:
                           begin
                              writer_data[cnt-3] = 0;
                              writer_data[cnt-1] = 1;
                           end
                        -1:
                          begin
                             writer_data[cnt-3] = 1;
                             writer_data[cnt-1] = 1;
                          end
                        -3:
                          begin
                             writer_data[cnt-3] = 1;
                             writer_data[cnt-1] = 0;
                          end                            
                       endcase // case (ar)
                       case(ai)
                         3:
                           begin
                              writer_data[cnt-2] = 0;
                              writer_data[cnt] = 0;
                           end
                         1:
                           begin
                              writer_data[cnt-2] = 0;
                              writer_data[cnt] = 1;
                           end
                         -1:
                           begin
                              writer_data[cnt-2] = 1;
                              writer_data[cnt] = 1;
                           end
                        -3:
                          begin
                             writer_data[cnt-2] = 1;
                             writer_data[cnt] = 0;
                          end
                       endcase // case (ar)

                       cnt <= cnt + 4;
                       if(cnt >= 128)
                         begin
                            write_data_output_flg <= 1;
                            valid_o <= 1;
                         end
                    end
                  else
                    begin
                       cnt <= 3;
                       
                    end 
               end 
          end
        
     end
   

   
endmodule

PM/iqdemap_qpsk/test_iqdemap_qpsk.v

module test_iqdemap_qpsk;
   reg [127:0] reader_data;
   reg         reader_en;
   reg         clk,rst,start_update, busy;
   reg         valid,raw;
   reg [6:0]   cnt;
   reg signed [10:0]  ar;
   reg signed [10:0]  ai;
   
   
   initial begin rst=1;
      #1 rst=0;
      #2 rst=1;
      #3000 $finish;

   end
   initial
     begin
        $dumpvars;
        $dumpfile("stm.vcd");
        #0
          clk <= 0;
	    reader_data <= 128'habcdefabcdefabcdefabcdefabcdef;
        valid <= 0;
        ai <= 0;
        cnt <= 1;
        
     end

   always #5         clk <= ~clk;


   always #10
     begin
        ar <= 1 - (reader_data[cnt-1] << 1);
        ai <= 1 - (reader_data[cnt] << 1);
        valid <= 1;        
        cnt <= cnt + 2;
     end
   
   
   
   initial begin
      
      #50
        valid <= 1;
   end // initial begin
   
   iqdemap_qpsk qpsk(.CLK(clk), .RST(rst), .valid_i(valid), .ce(ce), .ar(ar), .ai(ai));
   
   
endmodule

PM/iqdemap_qpsk/dump.vcd
$date
	Tue Dec 10 14:36:57 2013
$end
$version
	Icarus Verilog
$end
$timescale
	1ps
$end
$scope module test_iqdemap_qpsk $end
$var wire 1 ! ce $end
$var reg 11 " ai [10:0] $end
$var reg 11 # ar [10:0] $end
$var reg 1 $ clk $end
$var reg 7 % cnt [6:0] $end
$var reg 128 & reader_data [127:0] $end
$var reg 1 ' rst $end
$var reg 1 ( valid $end
$scope module qpsk $end
$var wire 1 ) CLK $end
$var wire 1 * RST $end
$var wire 11 + ai [10:0] $end
$var wire 11 , ar [10:0] $end
$var wire 1 ! ce $end
$var wire 1 - valid_i $end
$var wire 1 . valid_raw $end
$var reg 9 / cnt [8:0] $end
$var reg 4 0 raw [3:0] $end
$var reg 1 1 valid_o $end
$var reg 1 2 write_data_output_flg $end
$var reg 128 3 writer_data [127:0] $end
$upscope $end
$upscope $end
$enddefinitions $end
#0
$dumpvars
bx 3
x2
x1
bx 0
bx /
x.
0-
bx ,
b0 +
1*
0)
0(
1'
b101010111100110111101111101010111100110111101111101010111100110111101111101010111100110111101111101010111100110111101111 &
b1 %
0$
bx #
b0 "
z!
$end
#1000
0'
0*
#3000
1'
1*
#5000
b1 /
1$
1)
#10000
0$
0)
b11 %
1(
1-
b11111111111 "
b11111111111 +
b11111111111 #
b11111111111 ,
#15000
b11 /
bx11 3
b1111 0
1$
1)
#20000
0$
0)
b101 %
#25000
b101 /
bx1111 3
1$
1)
#30000
0$
0)
b111 %
b1 #
b1 ,
#35000
b111 /
bx101111 3
b1 0
1$
1)
#40000
0$
0)
b1001 %
b11111111111 #
b11111111111 ,
#45000
b1001 /
bx11101111 3
b1111 0
1$
1)
#50000
0$
0)
b1011 %
b1 "
b1 +
#55000
b1011 /
bx0111101111 3
1$
1)
#60000
0$
0)
b1101 %
b11111111111 "
b11111111111 +
#65000
b1101 /
bx110111101111 3
1$
1)
#70000
0$
0)
b1111 %
b1 "
b1 +
b1 #
b1 ,
#75000
b1111 /
bx00110111101111 3
b1 0
1$
1)
#80000
0$
0)
b10001 %
b11111111111 "
b11111111111 +
b11111111111 #
b11111111111 ,
#85000
b10001 /
bx1100110111101111 3
b1111 0
1$
1)
#90000
0$
0)
b10011 %
#95000
b10011 /
bx111100110111101111 3
1$
1)
#100000
0$
0)
b10101 %
b1 #
b1 ,
#105000
b10101 /
bx10111100110111101111 3
b1 0
1$
1)
#110000
0$
0)
b10111 %
#115000
b10111 /
bx1010111100110111101111 3
1$
1)
#120000
0$
0)
b11001 %
#125000
b11001 /
bx101010111100110111101111 3
1$
1)
#130000
0$
0)
b11011 %
b11111111111 #
b11111111111 ,
#135000
b11011 /
bx11101010111100110111101111 3
b1111 0
1$
1)
#140000
0$
0)
b11101 %
#145000
b11101 /
bx1111101010111100110111101111 3
1$
1)
#150000
0$
0)
b11111 %
b1 #
b1 ,
#155000
b11111 /
bx101111101010111100110111101111 3
b1 0
1$
1)
#160000
0$
0)
b100001 %
b11111111111 #
b11111111111 ,
#165000
b100001 /
bx11101111101010111100110111101111 3
b1111 0
1$
1)
#170000
0$
0)
b100011 %
b1 "
b1 +
#175000
b100011 /
bx0111101111101010111100110111101111 3
1$
1)
#180000
0$
0)
b100101 %
b11111111111 "
b11111111111 +
#185000
b100101 /
bx110111101111101010111100110111101111 3
1$
1)
#190000
0$
0)
b100111 %
b1 "
b1 +
b1 #
b1 ,
#195000
b100111 /
bx00110111101111101010111100110111101111 3
b1 0
1$
1)
#200000
0$
0)
b101001 %
b11111111111 "
b11111111111 +
b11111111111 #
b11111111111 ,
#205000
b101001 /
bx1100110111101111101010111100110111101111 3
b1111 0
1$
1)
#210000
0$
0)
b101011 %
#215000
b101011 /
bx111100110111101111101010111100110111101111 3
1$
1)
#220000
0$
0)
b101101 %
b1 #
b1 ,
#225000
b101101 /
bx10111100110111101111101010111100110111101111 3
b1 0
1$
1)
#230000
0$
0)
b101111 %
#235000
b101111 /
bx1010111100110111101111101010111100110111101111 3
1$
1)
#240000
0$
0)
b110001 %
#245000
b110001 /
bx101010111100110111101111101010111100110111101111 3
1$
1)
#250000
0$
0)
b110011 %
b11111111111 #
b11111111111 ,
#255000
b110011 /
bx11101010111100110111101111101010111100110111101111 3
b1111 0
1$
1)
#260000
0$
0)
b110101 %
#265000
b110101 /
bx1111101010111100110111101111101010111100110111101111 3
1$
1)
#270000
0$
0)
b110111 %
b1 #
b1 ,
#275000
b110111 /
bx101111101010111100110111101111101010111100110111101111 3
b1 0
1$
1)
#280000
0$
0)
b111001 %
b11111111111 #
b11111111111 ,
#285000
b111001 /
bx11101111101010111100110111101111101010111100110111101111 3
b1111 0
1$
1)
#290000
0$
0)
b111011 %
b1 "
b1 +
#295000
b111011 /
bx0111101111101010111100110111101111101010111100110111101111 3
1$
1)
#300000
0$
0)
b111101 %
b11111111111 "
b11111111111 +
#305000
b111101 /
bx110111101111101010111100110111101111101010111100110111101111 3
1$
1)
#310000
0$
0)
b111111 %
b1 "
b1 +
b1 #
b1 ,
#315000
b111111 /
bx00110111101111101010111100110111101111101010111100110111101111 3
b1 0
1$
1)
#320000
0$
0)
b1000001 %
b11111111111 "
b11111111111 +
b11111111111 #
b11111111111 ,
#325000
b1000001 /
bx1100110111101111101010111100110111101111101010111100110111101111 3
b1111 0
1$
1)
#330000
0$
0)
b1000011 %
#335000
b1000011 /
bx111100110111101111101010111100110111101111101010111100110111101111 3
1$
1)
#340000
0$
0)
b1000101 %
b1 #
b1 ,
#345000
b1000101 /
bx10111100110111101111101010111100110111101111101010111100110111101111 3
b1 0
1$
1)
#350000
0$
0)
b1000111 %
#355000
b1000111 /
bx1010111100110111101111101010111100110111101111101010111100110111101111 3
1$
1)
#360000
0$
0)
b1001001 %
#365000
b1001001 /
bx101010111100110111101111101010111100110111101111101010111100110111101111 3
1$
1)
#370000
0$
0)
b1001011 %
b11111111111 #
b11111111111 ,
#375000
b1001011 /
bx11101010111100110111101111101010111100110111101111101010111100110111101111 3
b1111 0
1$
1)
#380000
0$
0)
b1001101 %
#385000
b1001101 /
bx1111101010111100110111101111101010111100110111101111101010111100110111101111 3
1$
1)
#390000
0$
0)
b1001111 %
b1 #
b1 ,
#395000
b1001111 /
bx101111101010111100110111101111101010111100110111101111101010111100110111101111 3
b1 0
1$
1)
#400000
0$
0)
b1010001 %
b11111111111 #
b11111111111 ,
#405000
b1010001 /
bx11101111101010111100110111101111101010111100110111101111101010111100110111101111 3
b1111 0
1$
1)
#410000
0$
0)
b1010011 %
b1 "
b1 +
#415000
b1010011 /
bx0111101111101010111100110111101111101010111100110111101111101010111100110111101111 3
1$
1)
#420000
0$
0)
b1010101 %
b11111111111 "
b11111111111 +
#425000
b1010101 /
bx110111101111101010111100110111101111101010111100110111101111101010111100110111101111 3
1$
1)
#430000
0$
0)
b1010111 %
b1 "
b1 +
b1 #
b1 ,
#435000
b1010111 /
bx00110111101111101010111100110111101111101010111100110111101111101010111100110111101111 3
b1 0
1$
1)
#440000
0$
0)
b1011001 %
b11111111111 "
b11111111111 +
b11111111111 #
b11111111111 ,
#445000
b1011001 /
bx1100110111101111101010111100110111101111101010111100110111101111101010111100110111101111 3
b1111 0
1$
1)
#450000
0$
0)
b1011011 %
#455000
b1011011 /
bx111100110111101111101010111100110111101111101010111100110111101111101010111100110111101111 3
1$
1)
#460000
0$
0)
b1011101 %
b1 #
b1 ,
#465000
b1011101 /
bx10111100110111101111101010111100110111101111101010111100110111101111101010111100110111101111 3
b1 0
1$
1)
#470000
0$
0)
b1011111 %
#475000
b1011111 /
bx1010111100110111101111101010111100110111101111101010111100110111101111101010111100110111101111 3
1$
1)
#480000
0$
0)
b1100001 %
#485000
b1100001 /
bx101010111100110111101111101010111100110111101111101010111100110111101111101010111100110111101111 3
1$
1)
#490000
0$
0)
b1100011 %
b11111111111 #
b11111111111 ,
#495000
b1100011 /
bx11101010111100110111101111101010111100110111101111101010111100110111101111101010111100110111101111 3
b1111 0
1$
1)
#500000
0$
0)
b1100101 %
#505000
b1100101 /
bx1111101010111100110111101111101010111100110111101111101010111100110111101111101010111100110111101111 3
1$
1)
#510000
0$
0)
b1100111 %
b1 #
b1 ,
#515000
b1100111 /
bx101111101010111100110111101111101010111100110111101111101010111100110111101111101010111100110111101111 3
b1 0
1$
1)
#520000
0$
0)
b1101001 %
b11111111111 #
b11111111111 ,
#525000
b1101001 /
bx11101111101010111100110111101111101010111100110111101111101010111100110111101111101010111100110111101111 3
b1111 0
1$
1)
#530000
0$
0)
b1101011 %
b1 "
b1 +
#535000
b1101011 /
bx0111101111101010111100110111101111101010111100110111101111101010111100110111101111101010111100110111101111 3
1$
1)
#540000
0$
0)
b1101101 %
b11111111111 "
b11111111111 +
#545000
b1101101 /
bx110111101111101010111100110111101111101010111100110111101111101010111100110111101111101010111100110111101111 3
1$
1)
#550000
0$
0)
b1101111 %
b1 "
b1 +
b1 #
b1 ,
#555000
b1101111 /
bx00110111101111101010111100110111101111101010111100110111101111101010111100110111101111101010111100110111101111 3
b1 0
1$
1)
#560000
0$
0)
b1110001 %
b11111111111 "
b11111111111 +
b11111111111 #
b11111111111 ,
#565000
b1110001 /
bx1100110111101111101010111100110111101111101010111100110111101111101010111100110111101111101010111100110111101111 3
b1111 0
1$
1)
#570000
0$
0)
b1110011 %
#575000
b1110011 /
bx111100110111101111101010111100110111101111101010111100110111101111101010111100110111101111101010111100110111101111 3
1$
1)
#580000
0$
0)
b1110101 %
b1 #
b1 ,
#585000
b1110101 /
bx10111100110111101111101010111100110111101111101010111100110111101111101010111100110111101111101010111100110111101111 3
b1 0
1$
1)
#590000
0$
0)
b1110111 %
#595000
b1110111 /
bx1010111100110111101111101010111100110111101111101010111100110111101111101010111100110111101111101010111100110111101111 3
1$
1)
#600000
0$
0)
b1111001 %
#605000
b1111001 /
bx101010111100110111101111101010111100110111101111101010111100110111101111101010111100110111101111101010111100110111101111 3
1$
1)
#610000
0$
0)
b1111011 %
b1 "
b1 +
#615000
b1111011 /
bx00101010111100110111101111101010111100110111101111101010111100110111101111101010111100110111101111101010111100110111101111 3
1$
1)
#620000
0$
0)
b1111101 %
#625000
b1111101 /
bx0000101010111100110111101111101010111100110111101111101010111100110111101111101010111100110111101111101010111100110111101111 3
1$
1)
#630000
0$
0)
b1111111 %
#635000
b1111111 /
bx000000101010111100110111101111101010111100110111101111101010111100110111101111101010111100110111101111101010111100110111101111 3
1$
1)
#640000
0$
0)
b1 %
#645000
b10000001 /
b101010111100110111101111101010111100110111101111101010111100110111101111101010111100110111101111101010111100110111101111 3
1$
1)
#650000
0$
0)
b11 %
b11111111111 "
b11111111111 +
b11111111111 #
b11111111111 ,
#655000
11
1.
12
b10000011 /
b1111 0
1$
1)
#660000
0$
0)
b101 %
#665000
01
0.
02
b1 /
1$
1)
#670000
0$
0)
b111 %
b1 #
b1 ,
#675000
b11 /
b101010111100110111101111101010111100110111101111101010111100110111101111101010111100110111101111101010111100110111101110 3
b1 0
1$
1)
#680000
0$
0)
b1001 %
b11111111111 #
b11111111111 ,
#685000
b101 /
b101010111100110111101111101010111100110111101111101010111100110111101111101010111100110111101111101010111100110111101110 3
b1111 0
1$
1)
#690000
0$
0)
b1011 %
b1 "
b1 +
#695000
b111 /
b101010111100110111101111101010111100110111101111101010111100110111101111101010111100110111101111101010111100110111011110 3
1$
1)
#700000
0$
0)
b1101 %
b11111111111 "
b11111111111 +
#705000
b1001 /
b101010111100110111101111101010111100110111101111101010111100110111101111101010111100110111101111101010111100110111011110 3
1$
1)
#710000
0$
0)
b1111 %
b1 "
b1 +
b1 #
b1 ,
#715000
b1011 /
b101010111100110111101111101010111100110111101111101010111100110111101111101010111100110111101111101010111100110011011110 3
b1 0
1$
1)
#720000
0$
0)
b10001 %
b11111111111 "
b11111111111 +
b11111111111 #
b11111111111 ,
#725000
b1101 /
b101010111100110111101111101010111100110111101111101010111100110111101111101010111100110111101111101010111100110011011110 3
b1111 0
1$
1)
#730000
0$
0)
b10011 %
#735000
b1111 /
b101010111100110111101111101010111100110111101111101010111100110111101111101010111100110111101111101010111111110011011110 3
1$
1)
#740000
0$
0)
b10101 %
b1 #
b1 ,
#745000
b10001 /
b101010111100110111101111101010111100110111101111101010111100110111101111101010111100110111101111101010111011110011011110 3
b1 0
1$
1)
#750000
0$
0)
b10111 %
#755000
b10011 /
b101010111100110111101111101010111100110111101111101010111100110111101111101010111100110111101111101010101011110011011110 3
1$
1)
#760000
0$
0)
b11001 %
#765000
b10101 /
b101010111100110111101111101010111100110111101111101010111100110111101111101010111100110111101111101010101011110011011110 3
1$
1)
#770000
0$
0)
b11011 %
b11111111111 #
b11111111111 ,
#775000
b10111 /
b101010111100110111101111101010111100110111101111101010111100110111101111101010111100110111101111101110101011110011011110 3
b1111 0
1$
1)
#780000
0$
0)
b11101 %
#785000
b11001 /
b101010111100110111101111101010111100110111101111101010111100110111101111101010111100110111101111111110101011110011011110 3
1$
1)
#790000
0$
0)
b11111 %
b1 #
b1 ,
#795000
b11011 /
b101010111100110111101111101010111100110111101111101010111100110111101111101010111100110111101110111110101011110011011110 3
b1 0
1$
1)
#800000
0$
0)
b100001 %
b11111111111 #
b11111111111 ,
#805000
b11101 /
b101010111100110111101111101010111100110111101111101010111100110111101111101010111100110111101110111110101011110011011110 3
b1111 0
1$
1)
#810000
0$
0)
b100011 %
b1 "
b1 +
#815000
b11111 /
b101010111100110111101111101010111100110111101111101010111100110111101111101010111100110111011110111110101011110011011110 3
1$
1)
#820000
0$
0)
b100101 %
b11111111111 "
b11111111111 +
#825000
b100001 /
b101010111100110111101111101010111100110111101111101010111100110111101111101010111100110111011110111110101011110011011110 3
1$
1)
#830000
0$
0)
b100111 %
b1 "
b1 +
b1 #
b1 ,
#835000
b100011 /
b101010111100110111101111101010111100110111101111101010111100110111101111101010111100110011011110111110101011110011011110 3
b1 0
1$
1)
#840000
0$
0)
b101001 %
b11111111111 "
b11111111111 +
b11111111111 #
b11111111111 ,
#845000
b100101 /
b101010111100110111101111101010111100110111101111101010111100110111101111101010111100110011011110111110101011110011011110 3
b1111 0
1$
1)
#850000
0$
0)
b101011 %
#855000
b100111 /
b101010111100110111101111101010111100110111101111101010111100110111101111101010111111110011011110111110101011110011011110 3
1$
1)
#860000
0$
0)
b101101 %
b1 #
b1 ,
#865000
b101001 /
b101010111100110111101111101010111100110111101111101010111100110111101111101010111011110011011110111110101011110011011110 3
b1 0
1$
1)
#870000
0$
0)
b101111 %
#875000
b101011 /
b101010111100110111101111101010111100110111101111101010111100110111101111101010101011110011011110111110101011110011011110 3
1$
1)
#880000
0$
0)
b110001 %
#885000
b101101 /
b101010111100110111101111101010111100110111101111101010111100110111101111101010101011110011011110111110101011110011011110 3
1$
1)
#890000
0$
0)
b110011 %
b11111111111 #
b11111111111 ,
#895000
b101111 /
b101010111100110111101111101010111100110111101111101010111100110111101111101110101011110011011110111110101011110011011110 3
b1111 0
1$
1)
#900000
0$
0)
b110101 %
#905000
b110001 /
b101010111100110111101111101010111100110111101111101010111100110111101111111110101011110011011110111110101011110011011110 3
1$
1)
#910000
0$
0)
b110111 %
b1 #
b1 ,
#915000
b110011 /
b101010111100110111101111101010111100110111101111101010111100110111101110111110101011110011011110111110101011110011011110 3
b1 0
1$
1)
#920000
0$
0)
b111001 %
b11111111111 #
b11111111111 ,
#925000
b110101 /
b101010111100110111101111101010111100110111101111101010111100110111101110111110101011110011011110111110101011110011011110 3
b1111 0
1$
1)
#930000
0$
0)
b111011 %
b1 "
b1 +
#935000
b110111 /
b101010111100110111101111101010111100110111101111101010111100110111011110111110101011110011011110111110101011110011011110 3
1$
1)
#940000
0$
0)
b111101 %
b11111111111 "
b11111111111 +
#945000
b111001 /
b101010111100110111101111101010111100110111101111101010111100110111011110111110101011110011011110111110101011110011011110 3
1$
1)
#950000
0$
0)
b111111 %
b1 "
b1 +
b1 #
b1 ,
#955000
b111011 /
b101010111100110111101111101010111100110111101111101010111100110011011110111110101011110011011110111110101011110011011110 3
b1 0
1$
1)
#960000
0$
0)
b1000001 %
b11111111111 "
b11111111111 +
b11111111111 #
b11111111111 ,
#965000
b111101 /
b101010111100110111101111101010111100110111101111101010111100110011011110111110101011110011011110111110101011110011011110 3
b1111 0
1$
1)
#970000
0$
0)
b1000011 %
#975000
b111111 /
b101010111100110111101111101010111100110111101111101010111111110011011110111110101011110011011110111110101011110011011110 3
1$
1)
#980000
0$
0)
b1000101 %
b1 #
b1 ,
#985000
b1000001 /
b101010111100110111101111101010111100110111101111101010111011110011011110111110101011110011011110111110101011110011011110 3
b1 0
1$
1)
#990000
0$
0)
b1000111 %
#995000
b1000011 /
b101010111100110111101111101010111100110111101111101010101011110011011110111110101011110011011110111110101011110011011110 3
1$
1)
#1000000
0$
0)
b1001001 %
#1005000
b1000101 /
b101010111100110111101111101010111100110111101111101010101011110011011110111110101011110011011110111110101011110011011110 3
1$
1)
#1010000
0$
0)
b1001011 %
b11111111111 #
b11111111111 ,
#1015000
b1000111 /
b101010111100110111101111101010111100110111101111101110101011110011011110111110101011110011011110111110101011110011011110 3
b1111 0
1$
1)
#1020000
0$
0)
b1001101 %
#1025000
b1001001 /
b101010111100110111101111101010111100110111101111111110101011110011011110111110101011110011011110111110101011110011011110 3
1$
1)
#1030000
0$
0)
b1001111 %
b1 #
b1 ,
#1035000
b1001011 /
b101010111100110111101111101010111100110111101110111110101011110011011110111110101011110011011110111110101011110011011110 3
b1 0
1$
1)
#1040000
0$
0)
b1010001 %
b11111111111 #
b11111111111 ,
#1045000
b1001101 /
b101010111100110111101111101010111100110111101110111110101011110011011110111110101011110011011110111110101011110011011110 3
b1111 0
1$
1)
#1050000
0$
0)
b1010011 %
b1 "
b1 +
#1055000
b1001111 /
b101010111100110111101111101010111100110111011110111110101011110011011110111110101011110011011110111110101011110011011110 3
1$
1)
#1060000
0$
0)
b1010101 %
b11111111111 "
b11111111111 +
#1065000
b1010001 /
b101010111100110111101111101010111100110111011110111110101011110011011110111110101011110011011110111110101011110011011110 3
1$
1)
#1070000
0$
0)
b1010111 %
b1 "
b1 +
b1 #
b1 ,
#1075000
b1010011 /
b101010111100110111101111101010111100110011011110111110101011110011011110111110101011110011011110111110101011110011011110 3
b1 0
1$
1)
#1080000
0$
0)
b1011001 %
b11111111111 "
b11111111111 +
b11111111111 #
b11111111111 ,
#1085000
b1010101 /
b101010111100110111101111101010111100110011011110111110101011110011011110111110101011110011011110111110101011110011011110 3
b1111 0
1$
1)
#1090000
0$
0)
b1011011 %
#1095000
b1010111 /
b101010111100110111101111101010111111110011011110111110101011110011011110111110101011110011011110111110101011110011011110 3
1$
1)
#1100000
0$
0)
b1011101 %
b1 #
b1 ,
#1105000
b1011001 /
b101010111100110111101111101010111011110011011110111110101011110011011110111110101011110011011110111110101011110011011110 3
b1 0
1$
1)
#1110000
0$
0)
b1011111 %
#1115000
b1011011 /
b101010111100110111101111101010101011110011011110111110101011110011011110111110101011110011011110111110101011110011011110 3
1$
1)
#1120000
0$
0)
b1100001 %
#1125000
b1011101 /
b101010111100110111101111101010101011110011011110111110101011110011011110111110101011110011011110111110101011110011011110 3
1$
1)
#1130000
0$
0)
b1100011 %
b11111111111 #
b11111111111 ,
#1135000
b1011111 /
b101010111100110111101111101110101011110011011110111110101011110011011110111110101011110011011110111110101011110011011110 3
b1111 0
1$
1)
#1140000
0$
0)
b1100101 %
#1145000
b1100001 /
b101010111100110111101111111110101011110011011110111110101011110011011110111110101011110011011110111110101011110011011110 3
1$
1)
#1150000
0$
0)
b1100111 %
b1 #
b1 ,
#1155000
b1100011 /
b101010111100110111101110111110101011110011011110111110101011110011011110111110101011110011011110111110101011110011011110 3
b1 0
1$
1)
#1160000
0$
0)
b1101001 %
b11111111111 #
b11111111111 ,
#1165000
b1100101 /
b101010111100110111101110111110101011110011011110111110101011110011011110111110101011110011011110111110101011110011011110 3
b1111 0
1$
1)
#1170000
0$
0)
b1101011 %
b1 "
b1 +
#1175000
b1100111 /
b101010111100110111011110111110101011110011011110111110101011110011011110111110101011110011011110111110101011110011011110 3
1$
1)
#1180000
0$
0)
b1101101 %
b11111111111 "
b11111111111 +
#1185000
b1101001 /
b101010111100110111011110111110101011110011011110111110101011110011011110111110101011110011011110111110101011110011011110 3
1$
1)
#1190000
0$
0)
b1101111 %
b1 "
b1 +
b1 #
b1 ,
#1195000
b1101011 /
b101010111100110011011110111110101011110011011110111110101011110011011110111110101011110011011110111110101011110011011110 3
b1 0
1$
1)
#1200000
0$
0)
b1110001 %
b11111111111 "
b11111111111 +
b11111111111 #
b11111111111 ,
#1205000
b1101101 /
b101010111100110011011110111110101011110011011110111110101011110011011110111110101011110011011110111110101011110011011110 3
b1111 0
1$
1)
#1210000
0$
0)
b1110011 %
#1215000
b1101111 /
b101010111111110011011110111110101011110011011110111110101011110011011110111110101011110011011110111110101011110011011110 3
1$
1)
#1220000
0$
0)
b1110101 %
b1 #
b1 ,
#1225000
b1110001 /
b101010111011110011011110111110101011110011011110111110101011110011011110111110101011110011011110111110101011110011011110 3
b1 0
1$
1)
#1230000
0$
0)
b1110111 %
#1235000
b1110011 /
b101010101011110011011110111110101011110011011110111110101011110011011110111110101011110011011110111110101011110011011110 3
1$
1)
#1240000
0$
0)
b1111001 %
#1245000
b1110101 /
b101010101011110011011110111110101011110011011110111110101011110011011110111110101011110011011110111110101011110011011110 3
1$
1)
#1250000
0$
0)
b1111011 %
b1 "
b1 +
#1255000
b1110111 /
b100010101011110011011110111110101011110011011110111110101011110011011110111110101011110011011110111110101011110011011110 3
1$
1)
#1260000
0$
0)
b1111101 %
#1265000
b1111001 /
b10101011110011011110111110101011110011011110111110101011110011011110111110101011110011011110111110101011110011011110 3
1$
1)
#1270000
0$
0)
b1111111 %
#1275000
b1111011 /
b10101011110011011110111110101011110011011110111110101011110011011110111110101011110011011110111110101011110011011110 3
1$
1)
#1280000
0$
0)
b1 %
#1285000
b1111101 /
b10101011110011011110111110101011110011011110111110101011110011011110111110101011110011011110111110101011110011011110 3
1$
1)
#1290000
0$
0)
b11 %
b11111111111 "
b11111111111 +
b11111111111 #
b11111111111 ,
#1295000
b1111111 /
b110000000010101011110011011110111110101011110011011110111110101011110011011110111110101011110011011110111110101011110011011110 3
b1111 0
1$
1)
#1300000
0$
0)
b101 %
#1305000
b10000001 /
b11110000000010101011110011011110111110101011110011011110111110101011110011011110111110101011110011011110111110101011110011011110 3
1$
1)
#1310000
0$
0)
b111 %
b1 #
b1 ,
#1315000
11
1.
12
b10000011 /
b1 0
1$
1)
#1320000
0$
0)
b1001 %
b11111111111 #
b11111111111 ,
#1325000
01
0.
02
b1 /
1$
1)
#1330000
0$
0)
b1011 %
b1 "
b1 +
#1335000
b11 /
b11110000000010101011110011011110111110101011110011011110111110101011110011011110111110101011110011011110111110101011110011011101 3
b1111 0
1$
1)
#1340000
0$
0)
b1101 %
b11111111111 "
b11111111111 +
#1345000
b101 /
b11110000000010101011110011011110111110101011110011011110111110101011110011011110111110101011110011011110111110101011110011011101 3
1$
1)
#1350000
0$
0)
b1111 %
b1 "
b1 +
b1 #
b1 ,
#1355000
b111 /
b11110000000010101011110011011110111110101011110011011110111110101011110011011110111110101011110011011110111110101011110011001101 3
b1 0
1$
1)
#1360000
0$
0)
b10001 %
b11111111111 "
b11111111111 +
b11111111111 #
b11111111111 ,
#1365000
b1001 /
b11110000000010101011110011011110111110101011110011011110111110101011110011011110111110101011110011011110111110101011110011001101 3
b1111 0
1$
1)
#1370000
0$
0)
b10011 %
#1375000
b1011 /
b11110000000010101011110011011110111110101011110011011110111110101011110011011110111110101011110011011110111110101011111111001101 3
1$
1)
#1380000
0$
0)
b10101 %
b1 #
b1 ,
#1385000
b1101 /
b11110000000010101011110011011110111110101011110011011110111110101011110011011110111110101011110011011110111110101011101111001101 3
b1 0
1$
1)
#1390000
0$
0)
b10111 %
#1395000
b1111 /
b11110000000010101011110011011110111110101011110011011110111110101011110011011110111110101011110011011110111110101010101111001101 3
1$
1)
#1400000
0$
0)
b11001 %
#1405000
b10001 /
b11110000000010101011110011011110111110101011110011011110111110101011110011011110111110101011110011011110111110101010101111001101 3
1$
1)
#1410000
0$
0)
b11011 %
b11111111111 #
b11111111111 ,
#1415000
b10011 /
b11110000000010101011110011011110111110101011110011011110111110101011110011011110111110101011110011011110111110111010101111001101 3
b1111 0
1$
1)
#1420000
0$
0)
b11101 %
#1425000
b10101 /
b11110000000010101011110011011110111110101011110011011110111110101011110011011110111110101011110011011110111111111010101111001101 3
1$
1)
#1430000
0$
0)
b11111 %
b1 #
b1 ,
#1435000
b10111 /
b11110000000010101011110011011110111110101011110011011110111110101011110011011110111110101011110011011110111011111010101111001101 3
b1 0
1$
1)
#1440000
0$
0)
b100001 %
b11111111111 #
b11111111111 ,
#1445000
b11001 /
b11110000000010101011110011011110111110101011110011011110111110101011110011011110111110101011110011011110111011111010101111001101 3
b1111 0
1$
1)
#1450000
0$
0)
b100011 %
b1 "
b1 +
#1455000
b11011 /
b11110000000010101011110011011110111110101011110011011110111110101011110011011110111110101011110011011101111011111010101111001101 3
1$
1)
#1460000
0$
0)
b100101 %
b11111111111 "
b11111111111 +
#1465000
b11101 /
b11110000000010101011110011011110111110101011110011011110111110101011110011011110111110101011110011011101111011111010101111001101 3
1$
1)
#1470000
0$
0)
b100111 %
b1 "
b1 +
b1 #
b1 ,
#1475000
b11111 /
b11110000000010101011110011011110111110101011110011011110111110101011110011011110111110101011110011001101111011111010101111001101 3
b1 0
1$
1)
#1480000
0$
0)
b101001 %
b11111111111 "
b11111111111 +
b11111111111 #
b11111111111 ,
#1485000
b100001 /
b11110000000010101011110011011110111110101011110011011110111110101011110011011110111110101011110011001101111011111010101111001101 3
b1111 0
1$
1)
#1490000
0$
0)
b101011 %
#1495000
b100011 /
b11110000000010101011110011011110111110101011110011011110111110101011110011011110111110101011111111001101111011111010101111001101 3
1$
1)
#1500000
0$
0)
b101101 %
b1 #
b1 ,
#1505000
b100101 /
b11110000000010101011110011011110111110101011110011011110111110101011110011011110111110101011101111001101111011111010101111001101 3
b1 0
1$
1)
#1510000
0$
0)
b101111 %
#1515000
b100111 /
b11110000000010101011110011011110111110101011110011011110111110101011110011011110111110101010101111001101111011111010101111001101 3
1$
1)
#1520000
0$
0)
b110001 %
#1525000
b101001 /
b11110000000010101011110011011110111110101011110011011110111110101011110011011110111110101010101111001101111011111010101111001101 3
1$
1)
#1530000
0$
0)
b110011 %
b11111111111 #
b11111111111 ,
#1535000
b101011 /
b11110000000010101011110011011110111110101011110011011110111110101011110011011110111110111010101111001101111011111010101111001101 3
b1111 0
1$
1)
#1540000
0$
0)
b110101 %
#1545000
b101101 /
b11110000000010101011110011011110111110101011110011011110111110101011110011011110111111111010101111001101111011111010101111001101 3
1$
1)
#1550000
0$
0)
b110111 %
b1 #
b1 ,
