FFT/fix_pointer/fft.v


module fft(
           input             clk,rst,
           input [10:0]      ar,
           input [10:0]      ai,
           input             valid_i,
           output reg [10:0] xr,
           output reg [10:0] xi,
           output [10:0] test
           );
   reg [10:0]                ar_reg [0:63];
   reg [10:0]                ai_reg [0:63];
   reg [31:0]                wr;
   reg [31:0]                wi;
   reg [10:0]                xr_tmp,xi_tmp;                            
   reg [6:0]                 input_cnt, output_cnt, m, mh, j, i, k;
   reg                       start_flg, output_flg, m_loop_flg,i_loop_flg,j_loop_flg;

   assign test = ar_reg[1];
   
   
   always@(posedge clk or negedge rst)
     begin
        if(!rst) begin
           xr <= 0;
           xi <= 0;
           input_cnt <= 0;
           output_cnt <= 0;
           output_flg <= 0;
           
           m <= 0;
           j <= 0;
           start_flg <= 0;
           m_loop_flg <= 0;
           i_loop_flg <= 0;
           j_loop_flg <= 0;           
           
        end

        else begin
              if(start_flg) begin //FFT
                 if(!i_loop_flg) begin
                    m <= m >> 1;
                    if(!m) begin
                       start_flg <= 0;
                       output_flg <= 1;
                       
                       //演算終了
                    end
                    else begin
                       mh <= m >> 1;
                       i_loop_flg <= 1;
                    end
                 end
                 else begin
                    if(!j_loop_flg) begin
                       i <= i + 1;
                       if(i >= mh) begin
                          i <= 0;
                          i_loop_flg <= 0; 
                       end                       
                       else begin
                          wr <= (m >> 5) * i;
                          wi <= (m >> 5) * i;
                          j <= i;
                          k <= j + mh;
                          j_loop_flg <= 1;                        
                       end
                    end
                    else begin
                       j <= j + m;
                       k <= j + mh;

                       if(j >= 64) begin
                          j <= 0;
                          k <= mh;
                          j_loop_flg <= 0;
                       end
                       if (k < 64) begin
                          xr_tmp <= ar_reg[j] -ar_reg[k];
                          xi_tmp <= ai_reg[j] -ai_reg[k];
                          ar_reg[k] <= (wr * xr- wi * xi) >>15;
                          ai_reg[k] <= (wr * xi- wi * xr) >>15;
                       end
                    end // else: !if(!j_loop_flg)
                 end // else: !if(!i_loop_flg)
              end // if (start_flg)

              else if(output_flg) begin
                 xr[output_cnt] <= ar_reg[output_cnt];
                 xi[output_cnt] <= ai_reg[output_cnt];
                 output_cnt <= output_cnt + 1;

                 if(output_cnt >= 64) begin
                    output_flg <= 0;
                    output_cnt <= 0;
                 end
              end
              else if(valid_i) begin
                 ar_reg[input_cnt] <= ar;
                 ai_reg[input_cnt] <= ai;
                 input_cnt <= input_cnt + 1;
                 if(input_cnt >= 64) begin
                    start_flg <= 1;
                    input_cnt <= 0;
                    m <= 64;
                    mh <= 32;
                    i <= 0;
                    i_loop_flg <= 1;
                    j <= 0;
                    j_loop_flg <= 1;
                    
                 end   
              end // if (valid_i)
           
           
           else begin


           end // else: !if(valid_i)

        end // else: !if(!rst)
     end // always@ (posedge clk)
   


   
   
   
   
endmodule // encode_fix_point

FFT/fix_pointer/test_fft.v

module test_fft;
   reg [10:0]  xr,xi;
   
   reg         clk,rst;
   reg         valid;
   reg [6:0]   cnt;
   reg [10:0]  ar;
   reg [10:0]  ai;
   
   
   initial begin rst=1;
      #1 rst=0;
      #2 rst=1;
      #30000 $finish;

   end
   initial
     begin
        $dumpvars;
        $dumpfile("stm.vcd");
        #0
          begin
             clk <= 0;
             valid <= 0;
             ai <= 0;
             ar <= 0;
          end
     end

   always #5         clk <= ~clk;

   initial begin
      
      #50
        valid <= 1;
      #650
        valid <= 0;
      
   end // initial begin
   
   fft fft_module(.clk(clk), .rst(rst), .valid_i(valid), .ar(ar), .ai(ai));
   
   
endmodule

FFT/fix_pointer/dump.vcd
$date
	Thu Dec 12 15:56:21 2013
$end
$version
	Icarus Verilog
$end
$timescale
	1s
$end
$scope module test_fft $end
$var reg 11 ! ai [10:0] $end
$var reg 11 " ar [10:0] $end
$var reg 1 # clk $end
$var reg 1 $ rst $end
$var reg 1 % valid $end
$scope module fft_module $end
$var wire 11 & ai [10:0] $end
$var wire 11 ' ar [10:0] $end
$var wire 1 ( clk $end
$var wire 1 ) rst $end
$var wire 11 * test [10:0] $end
$var wire 1 + valid_i $end
$var reg 7 , i [6:0] $end
$var reg 1 - i_loop_flg $end
$var reg 7 . input_cnt [6:0] $end
$var reg 7 / j [6:0] $end
$var reg 1 0 j_loop_flg $end
$var reg 7 1 k [6:0] $end
$var reg 7 2 m [6:0] $end
$var reg 1 3 m_loop_flg $end
$var reg 7 4 mh [6:0] $end
$var reg 7 5 output_cnt [6:0] $end
$var reg 1 6 output_flg $end
$var reg 1 7 start_flg $end
$var reg 32 8 wi [31:0] $end
$var reg 32 9 wr [31:0] $end
$var reg 11 : xi [10:0] $end
$var reg 11 ; xi_tmp [10:0] $end
$var reg 11 < xr [10:0] $end
$var reg 11 = xr_tmp [10:0] $end
$upscope $end
$upscope $end
$enddefinitions $end
#0
$dumpvars
bx =
bx <
bx ;
bx :
bx 9
bx 8
x7
x6
bx 5
bx 4
x3
bx 2
bx 1
x0
bx /
bx .
x-
bx ,
0+
bz *
1)
0(
b0 '
b0 &
0%
1$
0#
b0 "
b0 !
$end
#1
00
0-
03
07
b0 /
b0 2
06
b0 5
b0 .
b0 :
b0 <
0$
0)
#3
1$
1)
#5
1#
1(
#10
0#
0(
#15
1#
1(
#20
0#
0(
#25
1#
1(
#30
0#
0(
#35
1#
1(
#40
0#
0(
#45
1#
1(
#50
0#
0(
1%
1+
#55
b1 .
1#
1(
#60
0#
0(
#65
b10 .
b0 *
1#
1(
#70
0#
0(
#75
b11 .
1#
1(
#80
0#
0(
#85
b100 .
1#
1(
#90
0#
0(
#95
b101 .
1#
1(
#100
0#
0(
#105
b110 .
1#
1(
#110
0#
0(
#115
b111 .
1#
1(
#120
0#
0(
#125
b1000 .
1#
1(
#130
0#
0(
#135
b1001 .
1#
1(
#140
0#
0(
#145
b1010 .
1#
1(
#150
0#
0(
#155
b1011 .
1#
1(
#160
0#
0(
#165
b1100 .
1#
1(
#170
0#
0(
#175
b1101 .
1#
1(
#180
0#
0(
#185
b1110 .
1#
1(
#190
0#
0(
#195
b1111 .
1#
1(
#200
0#
0(
#205
b10000 .
1#
1(
#210
0#
0(
#215
b10001 .
1#
1(
#220
0#
0(
#225
b10010 .
1#
1(
#230
0#
0(
#235
b10011 .
1#
1(
#240
0#
0(
#245
b10100 .
1#
1(
#250
0#
0(
#255
b10101 .
1#
1(
#260
0#
0(
#265
b10110 .
1#
1(
#270
0#
0(
#275
b10111 .
1#
1(
#280
0#
0(
#285
b11000 .
1#
1(
#290
0#
0(
#295
b11001 .
1#
1(
#300
0#
0(
#305
b11010 .
1#
1(
#310
0#
0(
#315
b11011 .
1#
1(
#320
0#
0(
#325
b11100 .
1#
1(
#330
0#
0(
#335
b11101 .
1#
1(
#340
0#
0(
#345
b11110 .
1#
1(
#350
0#
0(
#355
b11111 .
1#
1(
#360
0#
0(
#365
b100000 .
1#
1(
#370
0#
0(
#375
b100001 .
1#
1(
#380
0#
0(
#385
b100010 .
1#
1(
#390
0#
0(
#395
b100011 .
1#
1(
#400
0#
0(
#405
b100100 .
1#
1(
#410
0#
0(
#415
b100101 .
1#
1(
#420
0#
0(
#425
b100110 .
1#
1(
#430
0#
0(
#435
b100111 .
1#
1(
#440
0#
0(
#445
b101000 .
1#
1(
#450
0#
0(
#455
b101001 .
1#
1(
#460
0#
0(
#465
b101010 .
1#
1(
#470
0#
0(
#475
b101011 .
1#
1(
#480
0#
0(
#485
b101100 .
1#
1(
#490
0#
0(
#495
b101101 .
1#
1(
#500
0#
0(
#505
b101110 .
1#
1(
#510
0#
0(
#515
b101111 .
1#
1(
#520
0#
0(
#525
b110000 .
1#
1(
#530
0#
0(
#535
b110001 .
1#
1(
#540
0#
0(
#545
b110010 .
1#
1(
#550
0#
0(
#555
b110011 .
1#
1(
#560
0#
0(
#565
b110100 .
1#
1(
#570
0#
0(
#575
b110101 .
1#
1(
#580
0#
0(
#585
b110110 .
1#
1(
#590
0#
0(
#595
b110111 .
1#
1(
#600
0#
0(
#605
b111000 .
1#
1(
#610
0#
0(
#615
b111001 .
1#
1(
#620
0#
0(
#625
b111010 .
1#
1(
#630
0#
0(
#635
b111011 .
1#
1(
#640
0#
0(
#645
b111100 .
1#
1(
#650
0#
0(
#655
b111101 .
1#
1(
#660
0#
0(
#665
b111110 .
1#
1(
#670
0#
0(
#675
b111111 .
1#
1(
#680
0#
0(
#685
b1000000 .
1#
1(
#690
0#
0(
#695
10
1-
b0 ,
b100000 4
b1000000 2
17
b0 .
1#
1(
#700
0#
0(
0%
0+
#705
b100000 1
b1000000 /
1#
1(
#710
0#
0(
#715
00
b100000 1
b0 /
1#
1(
#720
0#
0(
#725
10
b0 8
b0 9
b1 ,
1#
1(
#730
0#
0(
#735
b1000000 /
1#
1(
#740
0#
0(
#745
00
b100000 1
b0 /
1#
1(
#750
0#
0(
#755
10
b1 /
b10 8
b10 9
b10 ,
1#
1(
#760
0#
0(
#765
b0 ;
b0 =
b100001 1
b1000001 /
1#
1(
#770
0#
0(
#775
bx ;
bx =
00
b100000 1
b0 /
1#
1(
#780
0#
0(
#785
10
b10 /
b100 8
b100 9
b11 ,
1#
1(
#790
0#
0(
#795
b0 ;
b0 =
b100010 1
b1000010 /
1#
1(
#800
0#
0(
#805
bx ;
bx =
00
b100000 1
b0 /
1#
1(
#810
0#
0(
#815
10
b11 /
b110 8
b110 9
b100 ,
1#
1(
#820
0#
0(
#825
b0 ;
b0 =
b100011 1
b1000011 /
1#
1(
#830
0#
0(
#835
bx ;
bx =
00
b100000 1
b0 /
1#
1(
#840
0#
0(
#845
10
b100 /
b1000 8
b1000 9
b101 ,
1#
1(
#850
0#
0(
#855
b0 ;
b0 =
b100100 1
b1000100 /
1#
1(
#860
0#
0(
#865
bx ;
bx =
00
b100000 1
b0 /
1#
1(
#870
0#
0(
#875
10
b101 /
b1010 8
b1010 9
b110 ,
1#
1(
#880
0#
0(
#885
b0 ;
b0 =
b100101 1
b1000101 /
1#
1(
#890
0#
0(
#895
bx ;
bx =
00
b100000 1
b0 /
1#
1(
#900
0#
0(
#905
10
b110 /
b1100 8
b1100 9
b111 ,
1#
1(
#910
0#
0(
#915
b0 ;
b0 =
b100110 1
b1000110 /
1#
1(
#920
0#
0(
#925
bx ;
bx =
00
b100000 1
b0 /
1#
1(
#930
0#
0(
#935
10
b111 /
b1110 8
b1110 9
b1000 ,
1#
1(
#940
0#
0(
#945
b0 ;
b0 =
b100111 1
b1000111 /
1#
1(
#950
0#
0(
#955
bx ;
bx =
00
b100000 1
b0 /
1#
1(
#960
0#
0(
#965
10
b1000 /
b10000 8
b10000 9
b1001 ,
1#
1(
#970
0#
0(
#975
b0 ;
b0 =
b101000 1
b1001000 /
1#
1(
#980
0#
0(
#985
bx ;
bx =
00
b100000 1
b0 /
1#
1(
#990
0#
0(
#995
10
b1001 /
b10010 8
b10010 9
b1010 ,
1#
1(
#1000
0#
0(
#1005
b0 ;
b0 =
b101001 1
b1001001 /
1#
1(
#1010
0#
0(
#1015
bx ;
bx =
00
b100000 1
b0 /
1#
1(
#1020
0#
0(
#1025
10
b1010 /
b10100 8
b10100 9
b1011 ,
1#
1(
#1030
0#
0(
#1035
b0 ;
b0 =
b101010 1
b1001010 /
1#
1(
#1040
0#
0(
#1045
bx ;
bx =
00
b100000 1
b0 /
1#
1(
#1050
0#
0(
#1055
10
b1011 /
b10110 8
b10110 9
b1100 ,
1#
1(
#1060
0#
0(
#1065
b0 ;
b0 =
b101011 1
b1001011 /
1#
1(
#1070
0#
0(
#1075
bx ;
bx =
00
b100000 1
b0 /
1#
1(
#1080
0#
0(
#1085
10
b1100 /
b11000 8
b11000 9
b1101 ,
1#
1(
#1090
0#
0(
#1095
b0 ;
b0 =
b101100 1
b1001100 /
1#
1(
#1100
0#
0(
#1105
bx ;
bx =
00
b100000 1
b0 /
1#
1(
#1110
0#
0(
#1115
10
b1101 /
b11010 8
b11010 9
b1110 ,
1#
1(
#1120
0#
0(
#1125
b0 ;
b0 =
b101101 1
b1001101 /
1#
1(
#1130
0#
0(
#1135
bx ;
bx =
00
b100000 1
b0 /
1#
1(
#1140
0#
0(
#1145
10
b1110 /
b11100 8
b11100 9
b1111 ,
1#
1(
#1150
0#
0(
#1155
b0 ;
b0 =
b101110 1
b1001110 /
1#
1(
#1160
0#
0(
#1165
bx ;
bx =
00
b100000 1
b0 /
1#
1(
#1170
0#
0(
#1175
10
b1111 /
b11110 8
b11110 9
b10000 ,
1#
1(
#1180
0#
0(
#1185
b0 ;
b0 =
b101111 1
b1001111 /
1#
1(
#1190
0#
0(
#1195
bx ;
bx =
00
b100000 1
b0 /
1#
1(
#1200
0#
0(
#1205
10
b10000 /
b100000 8
b100000 9
b10001 ,
1#
1(
#1210
0#
0(
#1215
b0 ;
b0 =
b110000 1
b1010000 /
1#
1(
#1220
0#
0(
#1225
bx ;
bx =
00
b100000 1
b0 /
1#
1(
#1230
0#
0(
#1235
10
b10001 /
b100010 8
b100010 9
b10010 ,
1#
1(
#1240
0#
0(
#1245
b0 ;
b0 =
b110001 1
b1010001 /
1#
1(
#1250
0#
0(
#1255
bx ;
bx =
00
b100000 1
b0 /
1#
1(
#1260
0#
0(
#1265
10
b10010 /
b100100 8
b100100 9
b10011 ,
1#
1(
#1270
0#
0(
#1275
b0 ;
b0 =
b110010 1
b1010010 /
1#
1(
#1280
0#
0(
#1285
bx ;
bx =
00
b100000 1
b0 /
1#
1(
#1290
0#
0(
#1295
10
b10011 /
b100110 8
b100110 9
b10100 ,
1#
1(
#1300
0#
0(
#1305
b0 ;
b0 =
b110011 1
b1010011 /
1#
1(
#1310
0#
0(
#1315
bx ;
bx =
00
b100000 1
b0 /
1#
1(
#1320
0#
0(
#1325
10
b10100 /
b101000 8
b101000 9
b10101 ,
1#
1(
#1330
0#
0(
#1335
b0 ;
b0 =
b110100 1
b1010100 /
1#
1(
#1340
0#
0(
#1345
bx ;
bx =
00
b100000 1
b0 /
1#
1(
#1350
0#
0(
#1355
10
b10101 /
b101010 8
b101010 9
b10110 ,
1#
1(
#1360
0#
0(
#1365
b0 ;
b0 =
b110101 1
b1010101 /
1#
1(
#1370
0#
0(
#1375
bx ;
bx =
00
b100000 1
b0 /
1#
1(
#1380
0#
0(
#1385
10
b10110 /
b101100 8
b101100 9
b10111 ,
1#
1(
#1390
0#
0(
#1395
b0 ;
b0 =
b110110 1
b1010110 /
1#
1(
#1400
0#
0(
#1405
bx ;
bx =
00
b100000 1
b0 /
1#
1(
#1410
0#
0(
#1415
10
b10111 /
b101110 8
b101110 9
b11000 ,
1#
1(
#1420
0#
0(
#1425
b0 ;
b0 =
b110111 1
b1010111 /
1#
1(
#1430
0#
0(
#1435
bx ;
bx =
00
b100000 1
b0 /
1#
1(
#1440
0#
0(
#1445
10
b11000 /
b110000 8
b110000 9
b11001 ,
1#
1(
#1450
0#
0(
#1455
b0 ;
b0 =
b111000 1
b1011000 /
1#
1(
#1460
0#
0(
#1465
bx ;
bx =
00
b100000 1
b0 /
1#
1(
#1470
0#
0(
#1475
10
b11001 /
b110010 8
b110010 9
b11010 ,
1#
1(
#1480
0#
0(
#1485
b0 ;
b0 =
b111001 1
b1011001 /
1#
1(
#1490
0#
0(
#1495
bx ;
bx =
00
b100000 1
b0 /
1#
1(
#1500
0#
0(
#1505
10
b11010 /
b110100 8
b110100 9
b11011 ,
1#
1(
#1510
0#
0(
#1515
b0 ;
b0 =
b111010 1
b1011010 /
1#
1(
#1520
0#
0(
#1525
bx ;
bx =
00
b100000 1
b0 /
1#
1(
#1530
0#
0(
#1535
10
b11011 /
b110110 8
b110110 9
b11100 ,
1#
1(
#1540
0#
0(
#1545
b0 ;
b0 =
b111011 1
b1011011 /
1#
1(
#1550
0#
0(
#1555
bx ;
bx =
00
b100000 1
b0 /
1#
1(
#1560
0#
0(
#1565
10
b11100 /
b111000 8
b111000 9
b11101 ,
1#
1(
#1570
0#
0(
#1575
b0 ;
b0 =
b111100 1
b1011100 /
1#
1(
#1580
0#
0(
#1585
bx ;
bx =
00
b100000 1
b0 /
1#
1(
#1590
0#
0(
#1595
10
b11101 /
b111010 8
b111010 9
b11110 ,
1#
1(
#1600
0#
0(
#1605
b0 ;
b0 =
b111101 1
b1011101 /
1#
1(
#1610
0#
0(
#1615
bx ;
bx =
00
b100000 1
b0 /
1#
1(
#1620
0#
0(
#1625
10
b11110 /
b111100 8
b111100 9
b11111 ,
1#
1(
#1630
0#
0(
#1635
b0 ;
b0 =
b111110 1
b1011110 /
1#
1(
#1640
0#
0(
#1645
bx ;
bx =
00
b100000 1
b0 /
1#
1(
#1650
0#
0(
#1655
10
b11111 /
b111110 8
b111110 9
b100000 ,
1#
1(
#1660
0#
0(
#1665
b0 ;
b0 =
b111111 1
b1011111 /
1#
1(
#1670
0#
0(
#1675
bx ;
bx =
00
b100000 1
b0 /
1#
1(
#1680
0#
0(
#1685
0-
b0 ,
1#
1(
#1690
0#
0(
#1695
1-
b100000 2
1#
1(
#1700
0#
0(
#1705
10
b0 8
b0 9
b1 ,
1#
1(
#1710
0#
0(
#1715
b0 ;
b0 =
b100000 /
1#
1(
#1720
0#
0(
#1725
b1000000 1
b1000000 /
1#
1(
#1730
0#
0(
#1735
00
b100000 1
b0 /
1#
1(
#1740
0#
0(
#1745
10
b1 /
b1 8
b1 9
b10 ,
1#
1(
#1750
0#
0(
#1755
b100001 1
b100001 /
1#
1(
#1760
0#
0(
#1765
b1000001 1
b1000001 /
1#
1(
#1770
0#
0(
#1775
00
b100000 1
b0 /
1#
1(
#1780
0#
0(
#1785
10
b10 /
b10 8
b10 9
b11 ,
1#
1(
#1790
0#
0(
#1795
b100010 1
b100010 /
1#
1(
#1800
0#
0(
#1805
b1000010 1
b1000010 /
1#
1(
#1810
0#
0(
#1815
00
b100000 1
b0 /
1#
1(
#1820
0#
0(
#1825
10
b11 /
b11 8
b11 9
b100 ,
1#
1(
#1830
0#
0(
#1835
b100011 1
b100011 /
1#
1(
#1840
0#
0(
#1845
b1000011 1
b1000011 /
1#
1(
#1850
0#
0(
#1855
00
b100000 1
b0 /
1#
1(
#1860
0#
0(
#1865
10
b100 /
b100 8
b100 9
b101 ,
1#
1(
#1870
0#
0(
#1875
b100100 1
b100100 /
1#
1(
#1880
0#
0(
#1885
b1000100 1
b1000100 /
1#
1(
#1890
0#
0(
#1895
00
b100000 1
b0 /
1#
1(
#1900
0#
0(
#1905
10
b101 /
b101 8
b101 9
b110 ,
1#
1(
#1910
0#
0(
#1915
b100101 1
b100101 /
1#
1(
#1920
0#
0(
#1925
b1000101 1
b1000101 /
1#
1(
#1930
0#
0(
#1935
00
b100000 1
b0 /
1#
1(
#1940
0#
0(
#1945
10
b110 /
b110 8
b110 9
b111 ,
1#
1(
#1950
0#
0(
#1955
b100110 1
b100110 /
1#
1(
#1960
0#
0(
#1965
b1000110 1
b1000110 /
1#
1(
#1970
0#
0(
#1975
00
b100000 1
b0 /
1#
1(
#1980
0#
0(
#1985
10
b111 /
b111 8
b111 9
b1000 ,
1#
1(
#1990
0#
0(
#1995
b100111 1
b100111 /
1#
1(
#2000
0#
0(
#2005
b1000111 1
b1000111 /
1#
1(
#2010
0#
0(
#2015
00
b100000 1
b0 /
1#
1(
#2020
0#
0(
#2025
10
b1000 /
b1000 8
b1000 9
b1001 ,
1#
1(
#2030
0#
0(
#2035
b101000 1
b101000 /
1#
1(
#2040
0#
0(
#2045
b1001000 1
b1001000 /
1#
1(
#2050
0#
0(
#2055
00
b100000 1
b0 /
1#
1(
#2060
0#
0(
#2065
10
b1001 /
b1001 8
b1001 9
b1010 ,
1#
1(
#2070
0#
0(
#2075
b101001 1
b101001 /
1#
1(
#2080
0#
0(
#2085
b1001001 1
b1001001 /
1#
1(
#2090
0#
0(
#2095
00
b100000 1
b0 /
1#
1(
#2100
0#
0(
#2105
10
b1010 /
b1010 8
b1010 9
b1011 ,
1#
1(
#2110
0#
0(
#2115
b101010 1
b101010 /
1#
1(
#2120
0#
0(
#2125
b1001010 1
b1001010 /
1#
1(
#2130
0#
0(
#2135
00
b100000 1
b0 /
1#
1(
#2140
0#
0(
#2145
10
b1011 /
b1011 8
b1011 9
b1100 ,
1#
1(
#2150
0#
0(
#2155
b101011 1
b101011 /
1#
1(
#2160
0#
0(
#2165
b1001011 1
b1001011 /
1#
1(
#2170
0#
0(
#2175
00
b100000 1
b0 /
1#
1(
#2180
0#
0(
#2185
10
b1100 /
b1100 8
b1100 9
b1101 ,
1#
1(
#2190
0#
0(
#2195
b101100 1
b101100 /
1#
1(
#2200
0#
0(
#2205
b1001100 1
b1001100 /
1#
1(
#2210
0#
0(
#2215
00
b100000 1
b0 /
1#
1(
#2220
0#
0(
#2225
10
b1101 /
b1101 8
b1101 9
b1110 ,
1#
1(
#2230
0#
0(
#2235
b101101 1
b101101 /
1#
1(
#2240
0#
0(
#2245
b1001101 1
b1001101 /
1#
1(
#2250
0#
0(
#2255
00
b100000 1
b0 /
1#
1(
#2260
0#
0(
#2265
10
b1110 /
b1110 8
b1110 9
b1111 ,
1#
1(
#2270
0#
0(
#2275
b101110 1
b101110 /
1#
1(
#2280
0#
0(
#2285
b1001110 1
b1001110 /
1#
1(
#2290
0#
0(
#2295
00
b100000 1
b0 /
1#
1(
#2300
0#
0(
#2305
10
b1111 /
b1111 8
b1111 9
b10000 ,
1#
1(
#2310
0#
0(
#2315
b101111 1
b101111 /
1#
1(
#2320
0#
0(
#2325
b1001111 1
b1001111 /
1#
1(
#2330
0#
0(
#2335
00
b100000 1
b0 /
1#
1(
#2340
0#
0(
#2345
10
b10000 /
b10000 8
b10000 9
b10001 ,
1#
1(
#2350
0#
0(
#2355
b110000 1
b110000 /
1#
1(
#2360
0#
0(
#2365
b1010000 1
b1010000 /
1#
1(
#2370
0#
0(
#2375
00
b100000 1
b0 /
1#
1(
#2380
0#
0(
#2385
10
b10001 /
b10001 8
b10001 9
b10010 ,
1#
1(
#2390
0#
0(
#2395
b110001 1
b110001 /
1#
1(
#2400
0#
0(
#2405
b1010001 1
b1010001 /
1#
1(
#2410
0#
0(
#2415
00
b100000 1
b0 /
1#
1(
#2420
0#
0(
#2425
10
b10010 /
b10010 8
b10010 9
b10011 ,
1#
1(
#2430
0#
0(
#2435
b110010 1
b110010 /
1#
1(
#2440
0#
0(
#2445
b1010010 1
b1010010 /
1#
1(
#2450
0#
0(
#2455
00
b100000 1
b0 /
1#
1(
#2460
0#
0(
#2465
10
b10011 /
b10011 8
b10011 9
b10100 ,
1#
1(
#2470
0#
0(
#2475
b110011 1
b110011 /
1#
1(
#2480
0#
0(
#2485
b1010011 1
b1010011 /
1#
1(
#2490
0#
0(
#2495
00
b100000 1
b0 /
1#
1(
#2500
0#
0(
#2505
10
b10100 /
b10100 8
b10100 9
b10101 ,
1#
1(
#2510
0#
0(
#2515
b110100 1
b110100 /
1#
1(
#2520
0#
0(
#2525
b1010100 1
b1010100 /
1#
1(
#2530
0#
0(
#2535
00
b100000 1
b0 /
1#
1(
#2540
0#
0(
#2545
10
b10101 /
b10101 8
b10101 9
b10110 ,
1#
1(
#2550
0#
0(
#2555
b110101 1
b110101 /
1#
1(
#2560
0#
0(
#2565
b1010101 1
b1010101 /
1#
1(
#2570
0#
0(
#2575
00
b100000 1
b0 /
1#
1(
#2580
0#
0(
#2585
10
b10110 /
b10110 8
b10110 9
b10111 ,
1#
1(
#2590
0#
0(
#2595
b110110 1
b110110 /
1#
1(
#2600
0#
0(
#2605
b1010110 1
b1010110 /
1#
1(
#2610
0#
0(
#2615
00
b100000 1
b0 /
1#
1(
#2620
0#
0(
#2625
10
b10111 /
b10111 8
b10111 9
b11000 ,
1#
1(
#2630
0#
0(
#2635
b110111 1
b110111 /
1#
1(
#2640
0#
0(
#2645
b1010111 1
b1010111 /
1#
1(
#2650
0#
0(
#2655
00
b100000 1
b0 /
1#
1(
#2660
0#
0(
#2665
10
b11000 /
b11000 8
b11000 9
b11001 ,
1#
1(
#2670
0#
0(
#2675
b111000 1
b111000 /
1#
1(
#2680
0#
0(
#2685
b1011000 1
b1011000 /
1#
1(
#2690
0#
0(
#2695
00
b100000 1
b0 /
1#
1(
#2700
0#
0(
#2705
10
b11001 /
b11001 8
b11001 9
b11010 ,
1#
1(
#2710
0#
0(
#2715
b111001 1
b111001 /
1#
1(
#2720
0#
0(
#2725
b1011001 1
b1011001 /
1#
1(
#2730
0#
0(
#2735
00
b100000 1
b0 /
1#
1(
#2740
0#
0(
#2745
10
b11010 /
b11010 8
b11010 9
b11011 ,
1#
1(
#2750
0#
0(
#2755
b111010 1
b111010 /
1#
1(
#2760
0#
0(
#2765
b1011010 1
b1011010 /
1#
1(
#2770
0#
0(
#2775
00
b100000 1
b0 /
1#
1(
#2780
0#
0(
#2785
10
b11011 /
b11011 8
b11011 9
b11100 ,
1#
1(
#2790
0#
0(
#2795
b111011 1
b111011 /
1#
1(
#2800
0#
0(
#2805
b1011011 1
b1011011 /
1#
1(
#2810
0#
0(
#2815
00
b100000 1
b0 /
1#
1(
#2820
0#
0(
#2825
10
b11100 /
b11100 8
b11100 9
b11101 ,
1#
1(
#2830
0#
0(
#2835
b111100 1
b111100 /
1#
1(
#2840
0#
0(
#2845
b1011100 1
b1011100 /
1#
1(
#2850
0#
0(
#2855
00
b100000 1
b0 /
1#
1(
#2860
0#
0(
#2865
10
b11101 /
b11101 8
b11101 9
b11110 ,
1#
1(
#2870
0#
0(
#2875
b111101 1
b111101 /
1#
1(
#2880
0#
0(
#2885
b1011101 1
b1011101 /
1#
1(
#2890
0#
0(
#2895
00
b100000 1
b0 /
1#
1(
#2900
0#
0(
#2905
10
b11110 /
b11110 8
b11110 9
b11111 ,
1#
1(
#2910
0#
0(
#2915
b111110 1
b111110 /
1#
1(
#2920
0#
0(
#2925
b1011110 1
b1011110 /
1#
1(
#2930
0#
0(
#2935
00
b100000 1
b0 /
1#
1(
#2940
0#
0(
#2945
10
b11111 /
b11111 8
b11111 9
b100000 ,
1#
1(
#2950
0#
0(
#2955
b111111 1
b111111 /
1#
1(
#2960
0#
0(
#2965
b1011111 1
b1011111 /
1#
1(
#2970
0#
0(
#2975
00
b100000 1
b0 /
1#
1(
#2980
0#
0(
#2985
0-
b0 ,
1#
1(
#2990
0#
0(
#2995
1-
b10000 4
b10000 2
1#
1(
#3000
0#
0(
#3005
10
b10000 1
b0 8
b0 9
b1 ,
1#
1(
#3010
0#
0(
#3015
b10000 /
1#
1(
#3020
0#
0(
#3025
b100000 1
b100000 /
1#
1(
#3030
0#
0(
#3035
b110000 1
b110000 /
1#
1(
#3040
0#
0(
#3045
b1000000 1
b1000000 /
1#
1(
#3050
0#
0(
#3055
00
b10000 1
b0 /
1#
1(
#3060
0#
0(
#3065
10
b1 /
b10 ,
1#
1(
#3070
0#
0(
#3075
b10001 1
b10001 /
1#
1(
#3080
0#
0(
#3085
b100001 1
b100001 /
1#
1(
#3090
0#
0(
#3095
b110001 1
b110001 /
1#
1(
#3100
0#
0(
#3105
b1000001 1
b1000001 /
1#
1(
#3110
0#
0(
#3115
00
b10000 1
b0 /
1#
1(
#3120
0#
0(
#3125
10
b10 /
b11 ,
1#
1(
#3130
0#
0(
#3135
b10010 1
b10010 /
1#
1(
#3140
0#
0(
#3145
b100010 1
b100010 /
1#
1(
#3150
0#
0(
#3155
b110010 1
b110010 /
1#
1(
#3160
0#
0(
#3165
b1000010 1
b1000010 /
1#
1(
#3170
0#
0(
#3175
00
b10000 1
b0 /
1#
1(
#3180
0#
0(
#3185
10
b11 /
b100 ,
1#
1(
#3190
0#
0(
#3195
b10011 1
b10011 /
1#
1(
#3200
0#
0(
#3205
b100011 1
b100011 /
1#
1(
#3210
0#
0(
#3215
b110011 1
b110011 /
1#
1(
#3220
0#
0(
#3225
b1000011 1
b1000011 /
1#
1(
#3230
0#
0(
#3235
00
b10000 1
b0 /
1#
1(
#3240
0#
0(
#3245
10
b100 /
b101 ,
1#
1(
#3250
0#
0(
#3255
b10100 1
b10100 /
1#
1(
#3260
0#
0(
#3265
b100100 1
b100100 /
1#
1(
#3270
0#
0(
#3275
b110100 1
b110100 /
1#
1(
#3280
0#
0(
#3285
b1000100 1
b1000100 /
1#
1(
#3290
0#
0(
#3295
00
b10000 1
b0 /
1#
1(
#3300
0#
0(
#3305
10
b101 /
b110 ,
1#
1(
#3310
0#
0(
#3315
b10101 1
b10101 /
1#
1(
#3320
0#
0(
#3325
b100101 1
b100101 /
1#
1(
#3330
0#
0(
#3335
b110101 1
b110101 /
1#
1(
#3340
0#
0(
#3345
b1000101 1
b1000101 /
1#
1(
#3350
0#
0(
#3355
00
b10000 1
b0 /
1#
1(
#3360
0#
0(
#3365
10
b110 /
b111 ,
1#
1(
#3370
0#
0(
#3375
b10110 1
b10110 /
1#
1(
#3380
0#
0(
#3385
b100110 1
b100110 /
1#
1(
#3390
0#
0(
#3395
b110110 1
b110110 /
1#
1(
#3400
0#
0(
#3405
b1000110 1
b1000110 /
1#
1(
#3410
0#
0(
#3415
00
b10000 1
b0 /
1#
1(
#3420
0#
0(
#3425
10
b111 /
b1000 ,
1#
1(
#3430
0#
0(
#3435
b10111 1
b10111 /
1#
1(
#3440
0#
0(
#3445
b100111 1
b100111 /
1#
1(
#3450
0#
0(
#3455
b110111 1
b110111 /
1#
1(
#3460
0#
0(
#3465
b1000111 1
b1000111 /
1#
1(
#3470
0#
0(
#3475
00
b10000 1
b0 /
1#
1(
#3480
0#
0(
#3485
10
b1000 /
b1001 ,
1#
1(
#3490
0#
0(
#3495
b11000 1
b11000 /
1#
1(
#3500
0#
0(
#3505
b101000 1
b101000 /
1#
1(
#3510
0#
0(
#3515
b111000 1
b111000 /
1#
1(
#3520
0#
0(
#3525
b1001000 1
b1001000 /
1#
1(
#3530
0#
0(
#3535
00
b10000 1
b0 /
1#
1(
