BCD/lcd_top/lcd_control.v

module lcd_control
  (
   input        CLK,
   input        RST,

   output       update,
   output       lcd_row, 
   output [3:0] lcd_col,
   output [7:0] lcd_char,
   output       lcd_we,

   input        lcd_busy,

   input        valid_i,
   input        start_update,
   input [7:0]  char
   );

`define SW 4
   reg [79:0]   char_reg;
   reg          getchar_from_num2char_flg, wait_getchar_from_num2char;
   
   parameter s_wait_init = `SW'd0;
   parameter s_0         = `SW'd1;
   parameter s_1         = `SW'd2;
   parameter s_2         = `SW'd3;
   parameter s_3         = `SW'd4;
   parameter s_4         = `SW'd5;
   parameter s_5         = `SW'd6;
   parameter s_6         = `SW'd7;
   parameter s_7         = `SW'd8;
   parameter s_8         = `SW'd9;
   parameter s_9         = `SW'd10;
   parameter s_update    = `SW'd11;
   parameter s_idle      = `SW'd12;

   reg [`SW-1:0] state; 
   reg [4:0]     s,getchar_from_num2char_state;
`undef SW

   
   assign lcd_char = 
					 state == s_0?  char_reg[7:0] : 
                     state == s_1?  char_reg[15:8] : 
                     state == s_2?  char_reg[23:16] : 
                     state == s_3?  char_reg[31:24] : 
                     state == s_4?  char_reg[39:32] : 
                     state == s_5?  char_reg[47:40] : 
                     state == s_6?  char_reg[55:48] : 
                     state == s_7?  char_reg[63:56] : 
                     state == s_8?  char_reg[71:64] : 
                     state == s_9?  char_reg[79:72] :
                     3'h0;
   
   assign lcd_we   = state != s_wait_init && state != s_idle && state != s_update;
   assign lcd_row  = 1;
   //!(state == s_h
   //|| state == s_e
   //|| state == s_l1
   //|| state == s_l2
   //|| state == s_o1);
   
   assign update = state == s_update;
   
   assign lcd_col = 
                    state == s_0?  4'd0 : 
                    state == s_1?  4'd1 : 
                    state == s_2?  4'd2 : 
                    state == s_3?  4'd3 : 
                    state == s_4?  4'd4 : 
                    state == s_5?  4'd5 : 
                    state == s_6?  4'd6 : 
                    state == s_7?  4'd7 : 
                    state == s_8?  4'd8 : 
                    state == s_9?  4'd9 :
                    3'h0;                     
   
   always @(posedge CLK or negedge RST)
     if (!RST) begin
        state <= s_wait_init;
        getchar_from_num2char_flg <= 0;
        wait_getchar_from_num2char <= 0; 
        char_reg <= 0;
        
        s <= 0;
     end else begin
        case (state)
          s_wait_init: 
            if (!lcd_busy)
              state <= s_idle;

          s_idle:
            if (start_update)
              state <= s_0;

          s_0:        
            state <= s_1;
          s_1:
            state <= s_2;
          s_2:
            state <= s_3;
          s_3:
            state <= s_4;
          s_4:
            state <= s_5;
          s_5:
            state <= s_6;
          s_6:
            state <= s_7;
          s_7:
            state <= s_8;
          s_8:
            state <= s_9;
          s_9:
            state <= s_update;
          s_update:
            if (!lcd_busy)
              state <= s_idle;		  
          default: ;
          
        endcase
		
        
		if(getchar_from_num2char_flg == 1)
          begin
             if(valid_i == 1)
               begin
				  if(getchar_from_num2char_state == 4'd0)   char_reg[7:0]    <= char; 
 				  if(getchar_from_num2char_state == 4'd1)   char_reg[15:8]   <= char; 
 				  if(getchar_from_num2char_state == 4'd2)   char_reg[23:16]  <= char; 
 				  if(getchar_from_num2char_state == 4'd3)   char_reg[31:24]  <= char; 
 				  if(getchar_from_num2char_state == 4'd4)   char_reg[39:32]  <= char; 
 				  if(getchar_from_num2char_state == 4'd5)   char_reg[47:40]  <= char; 
 				  if(getchar_from_num2char_state == 4'd6)   char_reg[55:48]  <= char; 
 				  if(getchar_from_num2char_state == 4'd7)   char_reg[63:56]  <= char; 
 				  if(getchar_from_num2char_state == 4'd8)   char_reg[71:64]  <= char; 
 				  if(getchar_from_num2char_state == 4'd9)   char_reg[79:72]  <= char;    
				  getchar_from_num2char_state <= getchar_from_num2char_state + 1;
               end
             else
               begin
                  getchar_from_num2char_flg <= 0;
				  getchar_from_num2char_state <= 0;
               end
          end
        else if(start_update == 1)
          begin
			 getchar_from_num2char_state <= 0; 
             if(valid_i == 1)
               wait_getchar_from_num2char <= 0;
             else
               getchar_from_num2char_flg <= 1;
          end
        
        if(wait_getchar_from_num2char == 1)
          begin
             if(valid_i == 0)
               begin
                  getchar_from_num2char_flg <= 1;
                  wait_getchar_from_num2char <= 0;                 
               end
          end
        
     end

endmodule

BCD/num2char/num2char.v
`define BWW 6
`define BW  32
`define DW  10
`define DWW 4
`define DWB 40



module num2char
  (
   input        CLK,
   input        RST,

   input        start_update,
   input [31:0] error_rate,

   output [7:0] char,
   output       valid_o
   );

   reg [`BWW:0] state;
   reg [`BW+`DWB-1:0] AllReg;
   reg [`DWB-1:0]     char_reg;

   reg [7:0]          dispchar;
   reg                char_ready;
   reg [7:0]          cnt;
   reg                valid_out, disp_start;

   wire [`BW+`DWB:0]  tempReg;

   assign tempReg = {AllReg[`BW+`DWB-2:0],1'b0};
   assign char = dispchar;
   assign valid_o = valid_out;


   always@(posedge CLK or negedge RST)
     begin
        if(!RST)
          begin
             state <= 0;
             char_ready <= 0;
             valid_out <= 0;

          end
        else
          begin
             if(state == 0)
               begin
                  if(start_update == 1)
                    begin
                       cnt <= 40;
                       state <= 1;
                       AllReg <= {`DWB'b0, error_rate};
                    end
               end
             else if(state < (`BW))
               begin
                  AllReg <= {onedigit(tempReg), tempReg[`BW-1:0]};
                  state <= state +1;
               end
             else if(state == (`BW))
               begin
                  char_reg <= tempReg[`BW+`DWB-1:`BW];
                  state <= state +1;
                  char_ready <= 1;
               end
             else if(char_ready == 1)
               begin
                  state <= 0;
                  char_ready <= 0;
                  disp_start <= 1;
               end
             if (disp_start == 1)
               begin
                  valid_out <= 1;
                  dispchar <= ({char_reg[(cnt-4)+3], char_reg[(cnt-4)+2], char_reg[(cnt-4)+1], char_reg[(cnt-4)]}) +8'h30;
                  cnt <=  cnt - 4;
                  if(cnt == 0)
                    begin
                       cnt <= 40;
                       valid_out <= 0;
                       disp_start <= 0;
                    end
               end
          end
     end

   function [`DWB-1:0] onedigit;
      input  [`BW+`DWB-1:0] in;
      reg [3:0]             t0,t1;
      reg [`DWB-1:0]        a;
      integer               i;

      begin
         a = in[`BW+`DWB-1:`BW];
         onedigit = 0;
         for (i=0; i<`DW; i=i+1)
           begin
              onedigit =onedigit>>4;
              t0 = a[3:0];
              a = a >> 4;
              t1 = t0 +2'b11;
              if(t1[3] == 1)
                begin
                   onedigit = {t1[3:0], onedigit[`DWB-5:0]};
                end
              else
                begin
                   onedigit = {t0[3:0], onedigit[`DWB-5:0]};
                end
           end
      end
   endfunction

endmodule // num2char

BCD/lcd_top/lcd_ber_top.v

module lcd_ber_top
  (
   input        CLK,
   input        RST,

   output       update,
   output       lcd_row, 
   output [3:0] lcd_col,
   output [7:0] lcd_char,
   output       lcd_we,

   input        lcd_busy,
   input        start,

   input        valid_i,
   input [7:0]  sent_data,
   input [7:0]  recv_data,
   input [3:0]  number_of_bits 
   );

   wire         ber_valid_o;
   reg [31:0]  error_rate;

   wire         start_update;
   wire [7:0]   char;
   wire         n2c_valid_o;

   assign start_update = start;

   /*test code*/
   always@(negedge !RST)
     begin
        error_rate <= 32'd123456789;
     end
   /*Finish test code*/
   
 /*  ber ber_inst
     (
      .CLK(CLK),
      .RST(RST),

      .valid_i(valid_i),
      .sent_data(sent_data),
      .recv_data(recv_data),
      .number_of_bits(number_of_bits),

      .valid_o(ber_valid_o),
      .error_rate(error_rate)
      );
*/
   num2char num2char_inst
     (
      .CLK(CLK),
      .RST(RST),

      .start_update(start_update),
      .error_rate(error_rate),

      .char(char),
      .valid_o(n2c_valid_o)
      );

   lcd_control lcd_control_inst
     (
      .CLK(CLK),
      .RST(RST),

      .start_update(start_update),
      .lcd_row(lcd_row), 
      .lcd_col(lcd_col),
      .lcd_char(lcd_char),
      .lcd_we(lcd_we),

      .lcd_busy(lcd_busy),

      .valid_i(n2c_valid_o),
      .update(update),
      .char(char)
      );
   
endmodule // lcd_test

BCD/HelloWorld/test_lcd.v

module test_lcd_control;

   reg clk,rst,start_update, busy;
   reg [7:0] char;
   reg       valid;
   
   initial begin rst=1;
      #10 rst=0;
      #10 rst=1;
      #3000 $finish;

   end
   initial
     begin
        $dumpvars;
        $dumpfile("stm.vcd");
        #0
        busy <= 0;      
        start_update <= 0;
        clk=0;
     end

   always #10 clk <= ~clk;
   always #120 busy <= ~busy;
   always #120 start_update <= ~start_update;
   
   
   initial begin
           
        #50
          start_update <= 1;
        #60
          valid <= 1;
        #70
          start_update <= 0;
          char <=31;
        #80
          char <=32;
        #90 
          char <=33;
        #100
          valid <= 0;
        
        
        
     end // initial begin
   
   lcd_ber_top top_inst(.CLK(clk), .RST(rst), .lcd_busy(busy), .start(start_update));
   
   
endmodule

BCD/lcd_top/dump.vcd
$date
	Fri Dec  6 12:09:41 2013
$end
$version
	Icarus Verilog
$end
$timescale
	1s
$end
$scope module test_lcd_control $end
$var reg 1 ! busy $end
$var reg 8 " char [7:0] $end
$var reg 1 # clk $end
$var reg 1 $ rst $end
$var reg 1 % start_update $end
$var reg 1 & valid $end
$scope module top_inst $end
$var wire 1 ' CLK $end
$var wire 1 ( RST $end
$var wire 8 ) char [7:0] $end
$var wire 1 * lcd_busy $end
$var wire 8 + lcd_char [7:0] $end
$var wire 4 , lcd_col [3:0] $end
$var wire 1 - lcd_row $end
$var wire 1 . lcd_we $end
$var wire 1 / n2c_valid_o $end
$var wire 4 0 number_of_bits [3:0] $end
$var wire 8 1 recv_data [7:0] $end
$var wire 8 2 sent_data [7:0] $end
$var wire 1 3 start $end
$var wire 1 4 start_update $end
$var wire 1 5 update $end
$var wire 1 6 valid_i $end
$var reg 32 7 error_rate [31:0] $end
$scope module num2char_inst $end
$var wire 1 ' CLK $end
$var wire 1 ( RST $end
$var wire 8 8 char [7:0] $end
$var wire 32 9 error_rate [31:0] $end
$var wire 1 4 start_update $end
$var wire 73 : tempReg [72:0] $end
$var wire 1 / valid_o $end
$var reg 72 ; AllReg [71:0] $end
$var reg 1 < char_ready $end
$var reg 40 = char_reg [39:0] $end
$var reg 8 > cnt [7:0] $end
$var reg 1 ? disp_start $end
$var reg 8 @ dispchar [7:0] $end
$var reg 7 A state [6:0] $end
$var reg 1 B valid_out $end
$scope function onedigit $end
$var reg 40 C a [39:0] $end
$var integer 32 D i [31:0] $end
$var reg 72 E in [71:0] $end
$var reg 40 F onedigit [39:0] $end
$var reg 4 G t0 [3:0] $end
$var reg 4 H t1 [3:0] $end
$upscope $end
$upscope $end
$scope module lcd_control_inst $end
$var wire 1 ' CLK $end
$var wire 1 ( RST $end
$var wire 8 I char [7:0] $end
$var wire 1 * lcd_busy $end
$var wire 8 J lcd_char [7:0] $end
$var wire 4 K lcd_col [3:0] $end
$var wire 1 - lcd_row $end
$var wire 1 . lcd_we $end
$var wire 1 4 start_update $end
$var wire 1 5 update $end
$var wire 1 / valid_i $end
$var reg 80 L char_reg [79:0] $end
$var reg 1 M getchar_from_num2char_flg $end
$var reg 5 N getchar_from_num2char_state [4:0] $end
$var reg 5 O s [4:0] $end
$var reg 4 P state [3:0] $end
$var reg 1 Q wait_getchar_from_num2char $end
$upscope $end
$upscope $end
$upscope $end
$enddefinitions $end
#0
$dumpvars
xQ
bx P
bx O
bx N
xM
bx L
bx K
bx J
bx I
bx H
bx G
bx F
bx E
bx D
bx C
xB
bx A
bx @
x?
bx >
bx =
x<
bx ;
b0xxxxxxxxxxxxxxxxxxxxxxxxxxxxxxxxxxxxxxxxxxxxxxxxxxxxxxxxxxxxxxxxxxxxxxx0 :
b111010110111100110100010101 9
bx 8
b111010110111100110100010101 7
z6
x5
04
03
bz 2
bz 1
bz 0
x/
x.
1-
bx ,
bx +
0*
bx )
1(
0'
x&
0%
1$
0#
bx "
0!
$end
#10
0.
b0 +
b0 J
b0 ,
b0 K
0B
0/
0<
b0 A
b0 O
b0 L
0Q
0M
b0 P
05
1#
1'
0$
0(
#20
0#
0'
1$
1(
#30
b1100 P
1#
1'
#40
0#
0'
#50
1.
b1110101101111001101000101010 :
1M
b0 N
b1 P
b111010110111100110100010101 ;
b1 A
b101000 >
1#
1'
1%
14
13
#60
0#
0'
#70
b11101011011110011010001010100 :
b1 ,
b1 K
b10 A
b1110101101111001101000101010 ;
0M
b10 P
b11 H
b0 G
b1010 D
b0 F
b0 C
b1110101101111001101000101010 E
1#
1'
#80
0#
0'
#90
b10 ,
b10 K
b111010110111100110100010101000 :
1M
b11 P
b11 A
b11101011011110011010001010100 ;
b1010 D
b11101011011110011010001010100 E
1#
1'
#100
0#
0'
#110
b11 ,
b11 K
b1110101101111001101000101010000 :
b100 A
b111010110111100110100010101000 ;
0M
b100 P
b1010 D
b111010110111100110100010101000 E
1#
1'
1&
#120
0#
0'
0%
04
03
1!
1*
#130
b100 ,
b100 K
b11101011011110011010001010100000 :
b101 P
b101 A
b1110101101111001101000101010000 ;
b1010 D
b1110101101111001101000101010000 E
1#
1'
#140
0#
0'
#150
b101 ,
b101 K
b111010110111100110100010101000000 :
b110 A
b11101011011110011010001010100000 ;
b110 P
b1010 D
b11101011011110011010001010100000 E
1#
1'
#160
0#
0'
#170
b110 ,
b110 K
b1110101101111001101000101010000000 :
b111 P
b111 A
b111010110111100110100010101000000 ;
b1 F
b11 H
b0 G
b1010 D
b0 C
b111010110111100110100010101000000 E
1#
1'
#180
0#
0'
b11111 "
#190
b111 ,
b111 K
b11101011011110011010001010100000000 :
b1000 A
b1110101101111001101000101010000000 ;
b1000 P
b11 H
b0 G
b1010 D
b11 F
b0 C
b1110101101111001101000101010000000 E
1#
1'
#200
0#
0'
#210
b1000 ,
b1000 K
b1010010110111100110100010101000000000 :
b1001 P
b1001 A
b101001011011110011010001010100000000 ;
b11 H
b0 G
b1010 D
b1010 F
b0 C
b11101011011110011010001010100000000 E
1#
1'
#220
0#
0'
#230
b1001 ,
b1001 K
b10100101101111001101000101010000000000 :
b1010 A
b1010010110111100110100010101000000000 ;
b1010 P
b11 H
b0 G
b1010 D
b10100 F
b0 C
b1010010110111100110100010101000000000 E
1#
1'
#240
0#
0'
1%
14
13
0!
0*
#250
b0 ,
b0 K
0.
b101100011011110011010001010100000000000 :
1M
b1011 P
15
b1011 A
b10110001101111001101000101010000000000 ;
b11 H
b0 G
b1010 D
b101100 F
b0 C
b10100101101111001101000101010000000000 E
1#
1'
#260
0#
0'
b100000 "
#270
b10001011110111100110100010101000000000000 :
0.
b1100 A
b1000101111011110011010001010100000000000 ;
0M
b1100 P
05
b11 H
b0 G
b1010 D
b10001011 F
b0 C
b101100011011110011010001010100000000000 E
1#
1'
#280
0#
0'
#290
1.
b100011010101111001101000101010000000000000 :
1M
b1 P
b1101 A
b10001101010111100110100010101000000000000 ;
b11 H
b0 G
b1010 D
b100011010 F
b0 C
b10001011110111100110100010101000000000000 E
1#
1'
#300
0#
0'
#310
b1000111000011110011010001010100000000000000 :
b1 ,
b1 K
b1110 A
b100011100001111001101000101010000000000000 ;
0M
b10 P
b11 H
b0 G
b1010 D
b1000111000 F
b0 C
b100011010101111001101000101010000000000000 E
1#
1'
#320
0#
0'
#330
b10 ,
b10 K
b10010100000111100110100010101000000000000000 :
1M
b11 P
b1111 A
b1001010000011110011010001010100000000000000 ;
b11 H
b0 G
b1010 D
b10010100000 F
b0 C
b1000111000011110011010001010100000000000000 E
1#
1'
#340
0#
0'
#350
b11 ,
b11 K
b110001000001111001101000101010000000000000000 :
b10000 A
b11000100000111100110100010101000000000000000 ;
0M
b100 P
b11 H
b0 G
b1010 D
b110001000001 F
b0 C
b10010100000111100110100010101000000000000000 E
1#
1'
b100001 "
#360
0#
0'
0%
04
03
1!
1*
#370
b100 ,
b100 K
b1101110110011110011010001010100000000000000000 :
b101 P
b10001 A
b110111011001111001101000101010000000000000000 ;
b11 H
b0 G
b1010 D
b1101110110011 F
b0 C
b110001000001111001101000101010000000000000000 E
1#
1'
#380
0#
0'
#390
b101 ,
b101 K
b11101010011010100110100010101000000000000000000 :
b10010 A
b1110101001101010011010001010100000000000000000 ;
b110 P
b11 H
b0 G
b1010 D
b11101010011010 F
b0 C
b1101110110011110011010001010100000000000000000 E
1#
1'
#400
0#
0'
#410
b110 ,
b110 K
b1010100000111000001101000101010000000000000000000 :
b111 P
b10011 A
b101010000011100000110100010101000000000000000000 ;
b11 H
b0 G
b1010 D
b1010100000111000 F
b0 C
b11101010011010100110100010101000000000000000000 E
1#
1'
#420
0#
0'
#430
b111 ,
b111 K
b11000000010100000011010001010100000000000000000000 :
b10100 A
b1100000001010000001101000101010000000000000000000 ;
b1000 P
b11 H
b0 G
b1010 D
b11000000010100000 F
b0 C
b1010100000111000001101000101010000000000000000000 E
1#
1'
#440
0#
0'
#450
b1000 ,
b1000 K
b110000000101000000110100010101000000000000000000000 :
b1001 P
b10101 A
b11000000010100000011010001010100000000000000000000 ;
b11 H
b0 G
b1010 D
b110000000101000000 F
b0 C
b11000000010100000011010001010100000000000000000000 E
1#
1'
0&
#460
0#
0'
#470
b1001 ,
b1001 K
b10010000001010110001101000101010000000000000000000000 :
b10110 A
b1001000000101011000110100010101000000000000000000000 ;
b1010 P
b11 H
b0 G
b1010 D
b10010000001010110001 F
b0 C
b110000000101000000110100010101000000000000000000000 E
1#
1'
#480
0#
0'
1%
14
13
0!
0*
#490
b0 ,
b0 K
0.
b100100000100010010011010001010100000000000000000000000 :
1M
b1011 P
15
b10111 A
b10010000010001001001101000101010000000000000000000000 ;
b11 H
b0 G
b1010 D
b100100000100010010011 F
b0 C
b10010000001010110001101000101010000000000000000000000 E
1#
1'
#500
0#
0'
#510
b1001000001000100101001100010101000000000000000000000000 :
0.
b11000 A
b100100000100010010100110001010100000000000000000000000 ;
0M
b1100 P
05
b11 H
b0 G
b1010 D
b1001000001000100101001 F
b0 C
b100100000100010010011010001010100000000000000000000000 E
1#
1'
#520
0#
0'
#530
1.
b10010110010001010000011000101010000000000000000000000000 :
1M
b1 P
b11001 A
b1001011001000101000001100010101000000000000000000000000 ;
b11 H
b0 G
b1010 D
b10010110010001010000011 F
b0 C
b1001000001000100101001100010101000000000000000000000000 E
1#
1'
#540
0#
0'
#550
b110010010100100000001001001010100000000000000000000000000 :
b1 ,
b1 K
b11010 A
b11001001010010000000100100101010000000000000000000000000 ;
0M
b10 P
b11 H
b0 G
b1010 D
b110010010100100000001001 F
b0 C
b10010110010001010000011000101010000000000000000000000000 E
1#
1'
#560
0#
0'
#570
b10 ,
b10 K
b1110000101100000000010010010101000000000000000000000000000 :
1M
b11 P
b11011 A
b111000010110000000001001001010100000000000000000000000000 ;
b11 H
b0 G
b1010 D
b1110000101100000000010010 F
b0 C
b110010010100100000001001001010100000000000000000000000000 E
1#
1'
#580
0#
0'
#590
b11 ,
b11 K
b11101110001011000000100100101010000000000000000000000000000 :
b11100 A
b1110111000101100000010010010101000000000000000000000000000 ;
0M
b100 P
b11 H
b0 G
b1010 D
b11101110001011000000100100 F
b0 C
b1110000101100000000010010010101000000000000000000000000000 E
1#
1'
#600
0#
0'
0%
04
03
1!
1*
#610
b100 ,
b100 K
b1010101000011001000001001100010100000000000000000000000000000 :
b101 P
b11101 A
b101010100001100100000100110001010000000000000000000000000000 ;
b11 H
b0 G
b1010 D
b1010101000011001000001001100 F
b0 C
b11101110001011000000100100101010000000000000000000000000000 E
1#
1'
#620
0#
0'
#630
b101 ,
b101 K
b11000010000110010000011001011101000000000000000000000000000000 :
b11110 A
b1100001000011001000001100101110100000000000000000000000000000 ;
b110 P
b11 H
b0 G
b1010 D
b11000010000110010000011001011 F
b0 C
b1010101000011001000001001100010100000000000000000000000000000 E
1#
1'
#640
0#
0'
#650
b110 ,
b110 K
b110000101110010100000111001010010000000000000000000000000000000 :
b111 P
b11111 A
b11000010111001010000011100101001000000000000000000000000000000 ;
b11 H
b0 G
b1010 D
b110000101110010100000111001010 F
b0 C
b11000010000110010000011001011101000000000000000000000000000000 E
1#
1'
#660
0#
0'
#670
b111 ,
b111 K
b10010001101000101011001111000100100000000000000000000000000000000 :
b100000 A
b1001000110100010101100111100010010000000000000000000000000000000 ;
b1000 P
b11 H
b0 G
b1010 D
b10010001101000101011001111000100 F
b0 C
b110000101110010100000111001010010000000000000000000000000000000 E
1#
1'
#680
0#
0'
#690
b1000 ,
b1000 K
b1001 P
1<
b100001 A
b100100011010001010110011110001001 =
1#
1'
#700
0#
0'
#710
b1001 ,
b1001 K
1?
0<
b0 A
b1010 P
1#
1'
#720
0#
0'
1%
14
13
0!
0*
#730
b0 ,
b0 K
0.
b1110101101111001101000101010 :
1M
b1011 P
15
b100100 >
b110000 @
b110000 )
b110000 8
b110000 I
1B
1/
b111010110111100110100010101 ;
b1 A
1#
1'
#740
0#
0'
#750
b11101011011110011010001010100 :
0.
b100000 >
b110001 @
b110001 )
b110001 8
b110001 I
b10 A
b1110101101111001101000101010 ;
b1 N
b110000 L
b1100 P
05
b1010 D
b0 F
b1110101101111001101000101010 E
1#
1'
#760
0#
0'
#770
1.
b110000 +
b110000 J
b111010110111100110100010101000 :
b10 N
b11000100110000 L
b1 P
b11100 >
b110010 @
b110010 )
b110010 8
b110010 I
b11 A
b11101011011110011010001010100 ;
b1010 D
b11101011011110011010001010100 E
1#
1'
#780
0#
0'
#790
b1110101101111001101000101010000 :
b110001 +
b110001 J
b1 ,
b1 K
b11000 >
b110011 @
b110011 )
b110011 8
b110011 I
b100 A
b111010110111100110100010101000 ;
b11 N
b1100100011000100110000 L
b10 P
b1010 D
b111010110111100110100010101000 E
1#
1'
#800
0#
0'
#810
b110010 +
b110010 J
b10 ,
b10 K
b11101011011110011010001010100000 :
b100 N
b110011001100100011000100110000 L
b11 P
b10100 >
b110100 @
b110100 )
b110100 8
b110100 I
b101 A
b1110101101111001101000101010000 ;
b1010 D
b1110101101111001101000101010000 E
1#
1'
#820
0#
0'
#830
b110011 +
b110011 J
b11 ,
b11 K
b111010110111100110100010101000000 :
b10000 >
b110101 @
b110101 )
b110101 8
b110101 I
b110 A
b11101011011110011010001010100000 ;
b101 N
b11010000110011001100100011000100110000 L
b100 P
b1010 D
b11101011011110011010001010100000 E
1#
1'
#840
0#
0'
0%
04
03
1!
1*
#850
b110100 +
b110100 J
b100 ,
b100 K
b1110101101111001101000101010000000 :
b110 N
b1101010011010000110011001100100011000100110000 L
b101 P
b1100 >
b110110 @
b110110 )
b110110 8
b110110 I
b111 A
b111010110111100110100010101000000 ;
b1 F
b11 H
b0 G
b1010 D
b0 C
b111010110111100110100010101000000 E
1#
1'
#860
0#
0'
#870
b110101 +
b110101 J
b101 ,
b101 K
b11101011011110011010001010100000000 :
b1000 >
b110111 @
b110111 )
b110111 8
b110111 I
b1000 A
b1110101101111001101000101010000000 ;
b111 N
b110110001101010011010000110011001100100011000100110000 L
b110 P
b11 H
b0 G
b1010 D
b11 F
b0 C
b1110101101111001101000101010000000 E
1#
1'
#880
0#
0'
#890
b110110 +
b110110 J
b110 ,
b110 K
b1010010110111100110100010101000000000 :
b1000 N
b11011100110110001101010011010000110011001100100011000100110000 L
b111 P
b100 >
b111000 @
b111000 )
b111000 8
b111000 I
b1001 A
b101001011011110011010001010100000000 ;
b11 H
b0 G
b1010 D
b1010 F
b0 C
b11101011011110011010001010100000000 E
1#
1'
#900
0#
0'
#910
b110111 +
b110111 J
b111 ,
b111 K
b10100101101111001101000101010000000000 :
b0 >
b111001 @
b111001 )
b111001 8
b111001 I
b1010 A
b1010010110111100110100010101000000000 ;
b1001 N
b1110000011011100110110001101010011010000110011001100100011000100110000 L
b1000 P
b11 H
b0 G
b1010 D
b10100 F
b0 C
b1010010110111100110100010101000000000 E
1#
1'
#920
0#
0'
#930
b111000 +
b111000 J
b1000 ,
b1000 K
b101100011011110011010001010100000000000 :
b1010 N
b111001001110000011011100110110001101010011010000110011001100100011000100110000 L
b1001 P
0?
0B
0/
b101000 >
bx @
bx )
bx 8
bx I
b1011 A
b10110001101111001101000101010000000000 ;
b11 H
b0 G
b1010 D
b101100 F
b0 C
b10100101101111001101000101010000000000 E
1#
1'
#940
0#
0'
#950
b111001 +
b111001 J
b1001 ,
b1001 K
b10001011110111100110100010101000000000000 :
b1100 A
b1000101111011110011010001010100000000000 ;
b0 N
0M
b1010 P
b11 H
b0 G
b1010 D
b10001011 F
b0 C
b101100011011110011010001010100000000000 E
1#
1'
#960
0#
0'
1%
14
13
0!
0*
#970
b0 +
b0 J
b0 ,
b0 K
0.
b100011010101111001101000101010000000000000 :
1M
b1011 P
15
b1101 A
b10001101010111100110100010101000000000000 ;
b11 H
b0 G
b1010 D
b100011010 F
b0 C
b10001011110111100110100010101000000000000 E
1#
1'
#980
0#
0'
#990
b1000111000011110011010001010100000000000000 :
0.
b1110 A
b100011100001111001101000101010000000000000 ;
0M
b1100 P
05
b11 H
b0 G
b1010 D
b1000111000 F
b0 C
b100011010101111001101000101010000000000000 E
1#
1'
#1000
0#
0'
#1010
1.
b110000 +
b110000 J
b10010100000111100110100010101000000000000000 :
1M
b1 P
b1111 A
b1001010000011110011010001010100000000000000 ;
b11 H
b0 G
b1010 D
b10010100000 F
b0 C
b1000111000011110011010001010100000000000000 E
1#
1'
#1020
0#
0'
#1030
b110001000001111001101000101010000000000000000 :
b110001 +
b110001 J
b1 ,
b1 K
b10000 A
b11000100000111100110100010101000000000000000 ;
0M
b10 P
b11 H
b0 G
b1010 D
b110001000001 F
b0 C
b10010100000111100110100010101000000000000000 E
1#
1'
#1040
0#
0'
#1050
b110010 +
b110010 J
b10 ,
b10 K
b1101110110011110011010001010100000000000000000 :
1M
b11 P
b10001 A
b110111011001111001101000101010000000000000000 ;
b11 H
b0 G
b1010 D
b1101110110011 F
b0 C
b110001000001111001101000101010000000000000000 E
1#
1'
#1060
0#
0'
#1070
b110011 +
b110011 J
b11 ,
b11 K
b11101010011010100110100010101000000000000000000 :
b10010 A
b1110101001101010011010001010100000000000000000 ;
0M
b100 P
b11 H
b0 G
b1010 D
b11101010011010 F
b0 C
b1101110110011110011010001010100000000000000000 E
1#
1'
#1080
0#
0'
0%
04
03
1!
1*
#1090
b110100 +
b110100 J
b100 ,
b100 K
b1010100000111000001101000101010000000000000000000 :
b101 P
b10011 A
b101010000011100000110100010101000000000000000000 ;
b11 H
b0 G
b1010 D
b1010100000111000 F
b0 C
b11101010011010100110100010101000000000000000000 E
1#
1'
#1100
0#
0'
#1110
b110101 +
b110101 J
b101 ,
b101 K
b11000000010100000011010001010100000000000000000000 :
b10100 A
b1100000001010000001101000101010000000000000000000 ;
b110 P
b11 H
b0 G
b1010 D
b11000000010100000 F
b0 C
b1010100000111000001101000101010000000000000000000 E
1#
1'
#1120
0#
0'
#1130
b110110 +
b110110 J
b110 ,
b110 K
b110000000101000000110100010101000000000000000000000 :
b111 P
b10101 A
b11000000010100000011010001010100000000000000000000 ;
b11 H
b0 G
b1010 D
b110000000101000000 F
b0 C
b11000000010100000011010001010100000000000000000000 E
1#
1'
#1140
0#
0'
#1150
b110111 +
b110111 J
b111 ,
b111 K
b10010000001010110001101000101010000000000000000000000 :
b10110 A
b1001000000101011000110100010101000000000000000000000 ;
b1000 P
b11 H
b0 G
b1010 D
b10010000001010110001 F
b0 C
b110000000101000000110100010101000000000000000000000 E
1#
1'
#1160
0#
0'
#1170
b111000 +
b111000 J
b1000 ,
b1000 K
b100100000100010010011010001010100000000000000000000000 :
b1001 P
b10111 A
b10010000010001001001101000101010000000000000000000000 ;
b11 H
b0 G
b1010 D
b100100000100010010011 F
b0 C
b10010000001010110001101000101010000000000000000000000 E
1#
1'
#1180
0#
0'
#1190
b111001 +
b111001 J
b1001 ,
b1001 K
b1001000001000100101001100010101000000000000000000000000 :
b11000 A
b100100000100010010100110001010100000000000000000000000 ;
b1010 P
b11 H
b0 G
b1010 D
b1001000001000100101001 F
b0 C
b100100000100010010011010001010100000000000000000000000 E
1#
1'
#1200
0#
0'
1%
14
13
0!
0*
#1210
b0 +
b0 J
b0 ,
b0 K
0.
b10010110010001010000011000101010000000000000000000000000 :
1M
b1011 P
15
b11001 A
b1001011001000101000001100010101000000000000000000000000 ;
b11 H
b0 G
b1010 D
b10010110010001010000011 F
b0 C
b1001000001000100101001100010101000000000000000000000000 E
1#
1'
#1220
0#
0'
#1230
b110010010100100000001001001010100000000000000000000000000 :
0.
b11010 A
b11001001010010000000100100101010000000000000000000000000 ;
0M
b1100 P
05
b11 H
b0 G
b1010 D
b110010010100100000001001 F
b0 C
b10010110010001010000011000101010000000000000000000000000 E
1#
1'
#1240
0#
0'
#1250
1.
b110000 +
b110000 J
b1110000101100000000010010010101000000000000000000000000000 :
1M
b1 P
b11011 A
b111000010110000000001001001010100000000000000000000000000 ;
b11 H
b0 G
b1010 D
b1110000101100000000010010 F
b0 C
b110010010100100000001001001010100000000000000000000000000 E
1#
1'
#1260
0#
0'
#1270
b11101110001011000000100100101010000000000000000000000000000 :
b110001 +
b110001 J
b1 ,
b1 K
b11100 A
b1110111000101100000010010010101000000000000000000000000000 ;
0M
b10 P
b11 H
b0 G
b1010 D
b11101110001011000000100100 F
b0 C
b1110000101100000000010010010101000000000000000000000000000 E
1#
1'
#1280
0#
0'
#1290
b110010 +
b110010 J
b10 ,
b10 K
b1010101000011001000001001100010100000000000000000000000000000 :
1M
b11 P
b11101 A
b101010100001100100000100110001010000000000000000000000000000 ;
b11 H
b0 G
b1010 D
b1010101000011001000001001100 F
b0 C
b11101110001011000000100100101010000000000000000000000000000 E
1#
1'
#1300
0#
0'
#1310
b110011 +
b110011 J
b11 ,
b11 K
b11000010000110010000011001011101000000000000000000000000000000 :
b11110 A
b1100001000011001000001100101110100000000000000000000000000000 ;
0M
b100 P
b11 H
b0 G
b1010 D
b11000010000110010000011001011 F
b0 C
b1010101000011001000001001100010100000000000000000000000000000 E
1#
1'
#1320
0#
0'
0%
04
03
1!
1*
