PM/iqmap_16qam/iqmap_16qam.v
`timescale 1ns / 1ps

module iqmap_16qam(
                  input                    CLK,
                  input                    RST,
                  input                    ce,
                  input                    valid_i,
                  input [127:0]            reader_data,
                  output reg signed [10:0] xr,
                  output reg signed [10:0] xi,
                  output reg               valid_o,
                  output                   valid_raw,
                  output reg               reader_en,
                  output reg [3:0]         raw
                  );
   
   assign valid_raw = valid_o;
   
   reg [127:0]                             reader_data_reg;
   reg [8:0]                               cnt;
   reg                                     start_output_flg;
   reg [3:0]                               bits_r, bits_i;
                               
   
   always@(posedge CLK)
	 begin
		if(!RST)
		  begin
			 cnt <= 3;
			 reader_data_reg <= 0;
			 valid_o <= 0;
			 raw <= 0;
			 reader_en <= 1;
             start_output_flg <= 0;
             
		  end
		else
		  begin
			 if(valid_i)
			   begin
				  reader_en <= 0;
				  reader_data_reg <= reader_data;
                  bits_r <=  reader_data_reg[0]<<1 | reader_data_reg[2];
                  bits_i <=  reader_data_reg[1]<<1 | reader_data_reg[3];


				  cnt <= 3;
                  start_output_flg <= 1;                 
			   end
			 else
			   begin
                  if(start_output_flg)
                    begin
                       bits_r <=  reader_data_reg[cnt-3]<<1 | reader_data_reg[cnt-1];
				       case(bits_r)
                         3'h0: xr <= 3;
                         3'h1: xr <= 1;
                         3'h3: xr <= -1;
                         3'h2: xr <= 3;
                       endcase 
                       
                       bits_i <=  reader_data_reg[cnt-2]<<1 | reader_data_reg[cnt];
				       case(bits_i)
                         3'h0: xi <= 3;
                         3'h1: xi <= 1;
                         3'h3: xi <= -1;
                         3'h2: xi <= 3;
                       endcase 
                       
                       valid_o <= 1;
                       
                         
				       cnt <= cnt + 4;
				       if(cnt >= 128)
					     begin
                            start_output_flg <= 0;
					        valid_o <= 0;
					        reader_en <= 1;
                            cnt <= 3;
                            
					     end
			        end // if (start_output)
               end
		  end
	 end


endmodule

PM/iqmap_16qam/test_iqmap_16qam.v

module test_iqmap_16qam;
   reg [127:0] reader_data;
   reg reader_en;
   reg clk,rst,start_update, busy;
   reg       valid,raw;
   
   initial begin rst=1;
      #10 rst=0;
      #10 rst=1;
      #3000 $finish;

   end
   initial
     begin
        $dumpvars;
        $dumpfile("stm.vcd");
        #0
        clk <= 0;
	    reader_data <= 128'habcdefabcdefabcdefabcdefabcdef;
        valid <= 0;
        
     end

   always #10 clk <= ~clk;
   
   
   initial begin
           
        #50
          valid <= 1;
        #60
          valid <= 0;        
     end // initial begin
   
   iqmap_16qam qam(.CLK(clk), .RST(rst), .reader_data(reader_data), .valid_i(valid),.ce(ce));
   
   
endmodule

PM/iqmap_16qam/dump.vcd
$date
	Tue Dec 10 15:48:03 2013
$end
$version
	Icarus Verilog
$end
$timescale
	1ps
$end
$scope module test_iqmap_16qam $end
$var wire 1 ! ce $end
$var reg 1 " clk $end
$var reg 128 # reader_data [127:0] $end
$var reg 1 $ rst $end
$var reg 1 % valid $end
$scope module qam $end
$var wire 1 & CLK $end
$var wire 1 ' RST $end
$var wire 1 ! ce $end
$var wire 128 ( reader_data [127:0] $end
$var wire 1 ) valid_i $end
$var wire 1 * valid_raw $end
$var reg 4 + bits_i [3:0] $end
$var reg 4 , bits_r [3:0] $end
$var reg 9 - cnt [8:0] $end
$var reg 4 . raw [3:0] $end
$var reg 128 / reader_data_reg [127:0] $end
$var reg 1 0 reader_en $end
$var reg 1 1 start_output_flg $end
$var reg 1 2 valid_o $end
$var reg 11 3 xi [10:0] $end
$var reg 11 4 xr [10:0] $end
$upscope $end
$upscope $end
$enddefinitions $end
#0
$dumpvars
bx 4
bx 3
x2
x1
x0
bx /
bx .
bx -
bx ,
bx +
x*
0)
b101010111100110111101111101010111100110111101111101010111100110111101111101010111100110111101111101010111100110111101111 (
1'
0&
0%
1$
b101010111100110111101111101010111100110111101111101010111100110111101111101010111100110111101111101010111100110111101111 #
0"
z!
$end
#10000
01
10
b0 .
02
0*
b0 /
b11 -
1"
1&
0$
0'
#20000
0"
0&
1$
1'
#30000
1"
1&
#40000
0"
0&
#50000
11
b0 +
b0 ,
b101010111100110111101111101010111100110111101111101010111100110111101111101010111100110111101111101010111100110111101111 /
00
1"
1&
1%
1)
#60000
0"
0&
#70000
b11 +
b11 ,
1"
1&
#80000
0"
0&
#90000
1"
1&
#100000
0"
0&
#110000
b111 -
12
1*
b11111111111 3
b11111111111 4
1"
1&
0%
0)
#120000
0"
0&
#130000
b1011 -
b1 ,
1"
1&
#140000
0"
0&
#150000
b1111 -
b1 +
b1 4
b11 ,
1"
1&
#160000
0"
0&
#170000
b10011 -
b1 3
b11111111111 4
b1 ,
1"
1&
#180000
0"
0&
#190000
b10111 -
b11 +
b1 4
b10 ,
1"
1&
#200000
0"
0&
#210000
b11011 -
b11111111111 3
b11 4
b0 ,
1"
1&
#220000
0"
0&
#230000
b11111 -
b11 ,
1"
1&
#240000
0"
0&
#250000
b100011 -
b11111111111 4
b1 ,
1"
1&
#260000
0"
0&
#270000
b100111 -
b1 +
b1 4
b11 ,
1"
1&
#280000
0"
0&
#290000
b101011 -
b1 3
b11111111111 4
b1 ,
1"
1&
#300000
0"
0&
#310000
b101111 -
b11 +
b1 4
b10 ,
1"
1&
#320000
0"
0&
#330000
b110011 -
b11111111111 3
b11 4
b0 ,
1"
1&
#340000
0"
0&
#350000
b110111 -
b11 ,
1"
1&
#360000
0"
0&
#370000
b111011 -
b11111111111 4
b1 ,
1"
1&
#380000
0"
0&
#390000
b111111 -
b1 +
b1 4
b11 ,
1"
1&
#400000
0"
0&
#410000
b1000011 -
b1 3
b11111111111 4
b1 ,
1"
1&
#420000
0"
0&
#430000
b1000111 -
b11 +
b1 4
b10 ,
1"
1&
#440000
0"
0&
#450000
b1001011 -
b11111111111 3
b11 4
b0 ,
1"
1&
#460000
0"
0&
#470000
b1001111 -
b11 ,
1"
1&
#480000
0"
0&
#490000
b1010011 -
b11111111111 4
b1 ,
1"
1&
#500000
0"
0&
#510000
b1010111 -
b1 +
b1 4
b11 ,
1"
1&
#520000
0"
0&
#530000
b1011011 -
b1 3
b11111111111 4
b1 ,
1"
1&
#540000
0"
0&
#550000
b1011111 -
b11 +
b1 4
b10 ,
1"
1&
#560000
0"
0&
#570000
b1100011 -
b11111111111 3
b11 4
b0 ,
1"
1&
#580000
0"
0&
#590000
b1100111 -
b11 ,
1"
1&
#600000
0"
0&
#610000
b1101011 -
b11111111111 4
b1 ,
1"
1&
#620000
0"
0&
#630000
b1101111 -
b1 +
b1 4
b11 ,
1"
1&
#640000
0"
0&
#650000
b1110011 -
b1 3
b11111111111 4
b1 ,
1"
1&
#660000
0"
0&
#670000
b1110111 -
b11 +
b1 4
b10 ,
1"
1&
#680000
0"
0&
#690000
b1111011 -
b11111111111 3
b11 4
b0 ,
1"
1&
#700000
0"
0&
#710000
b1111111 -
b0 +
1"
1&
#720000
0"
0&
#730000
b10000011 -
b11 3
1"
1&
#740000
0"
0&
#750000
10
02
0*
01
b11 -
b0xx +
b0xx ,
1"
1&
