BCD/num2char/num2char.v
`define BWW 6
`define BW  32
`define DW  10
`define DWW 4
`define DWB 40



module num2char
  (
   input        CLK,
   input        RST,

   input        start_update,
   input [31:0] error_rate,

   output [7:0] char,
   output       valid_o
   );

   reg [`BWW:0] state;
   reg [`BW+`DWB-1:0] AllReg;
   reg [`DWB-1:0]     char_reg;

   reg [7:0]          dispchar;
   reg                char_ready;
   reg [7:0]          cnt;
   reg                valid_out, disp_start;

   wire [`BW+`DWB:0]  tempReg;

   assign tempReg = {AllReg[`BW+`DWB-2:0],1'b0};
   assign char = dispchar;
   assign valid_o = valid_out;


   always@(posedge CLK or negedge RST)
     begin
        if(!RST)
          begin
             state <= 0;
             char_ready <= 0;
             valid_out <= 0;

          end
        else
          begin
             if(state == 0)
               begin
                  if(start_update == 1)
                    begin
                       cnt <= 40;
                       state <= 1;
                       AllReg <= {`DWB'b0, error_rate};
                    end
               end
             else if(state < (`BW))
               begin
                  AllReg <= {onedigit(tempReg), tempReg[`BW-1:0]};
                  state <= state +1;
               end
             else if(state == (`BW))
               begin
                  char_reg <= tempReg[`BW+`DWB-1:`BW];
                  state <= state +1;
                  char_ready <= 1;
               end
             else if(char_ready == 1)
               begin
                  state <= 0;
                  char_ready <= 0;
                  disp_start <= 1;
               end
             if (disp_start == 1)
               begin
                  valid_out <= 1;
                  dispchar <= ({char_reg[(cnt-4)+3], char_reg[(cnt-4)+2], char_reg[(cnt-4)+1], char_reg[(cnt-4)]}) +8'h30;
                  cnt <=  cnt - 4;
                  if(cnt == 0)
                    begin
                       cnt <= 40;
                       valid_out <= 0;
                       disp_start <= 0;
                    end
               end
          end
     end

   function [`DWB-1:0] onedigit;
      input  [`BW+`DWB-1:0] in;
      reg [3:0]             t0,t1;
      reg [`DWB-1:0]        a;
      integer               i;

      begin
         a = in[`BW+`DWB-1:`BW];
         onedigit = 0;
         for (i=0; i<`DW; i=i+1)
           begin
              onedigit =onedigit>>4;
              t0 = a[3:0];
              a = a >> 4;
              t1 = t0 +2'b11;
              if(t1[3] == 1)
                begin
                   onedigit = {t1[3:0], onedigit[`DWB-5:0]};
                end
              else
                begin
                   onedigit = {t0[3:0], onedigit[`DWB-5:0]};
                end
           end
      end
   endfunction

endmodule // num2char

BCD/num2char/test_num2char.v

module test_num2char;

   reg clk,rst,start_update;
   reg [31:0] error_rate;
   wire[7:0]  char;
   wire       valid;

   initial begin rst=1;
      #10 rst=0;
      #10 rst=1;
      #3000 $finish;

   end
   initial
     begin
        $dumpvars;
        $dumpfile("stm.vcd");

        #0 
          start_update <= 0;
          error_rate <= 2136;
        
        clk=0;
        #10
          start_update <= 1;
        forever #10 clk=~clk;
        
     end
   num2char num2char_inst(.CLK(clk),.RST(rst),.start_update(start_update), .error_rate(error_rate),.char(char), .valid_o(valid));

endmodule

BCD/num2char/dump.vcd
$date
	Tue Dec 10 12:23:36 2013
$end
$version
	Icarus Verilog
$end
$timescale
	1s
$end
$scope module test_num2char $end
$var wire 8 ! char [7:0] $end
$var wire 1 " valid $end
$var reg 1 # clk $end
$var reg 32 $ error_rate [31:0] $end
$var reg 1 % rst $end
$var reg 1 & start_update $end
$scope module num2char_inst $end
$var wire 1 ' CLK $end
$var wire 1 ( RST $end
$var wire 8 ) char [7:0] $end
$var wire 32 * error_rate [31:0] $end
$var wire 1 + start_update $end
$var wire 73 , tempReg [72:0] $end
$var wire 1 " valid_o $end
$var reg 72 - AllReg [71:0] $end
$var reg 1 . char_ready $end
$var reg 40 / char_reg [39:0] $end
$var reg 8 0 cnt [7:0] $end
$var reg 1 1 disp_start $end
$var reg 8 2 dispchar [7:0] $end
$var reg 7 3 state [6:0] $end
$var reg 1 4 valid_out $end
$scope function onedigit $end
$var reg 40 5 a [39:0] $end
$var integer 32 6 i [31:0] $end
$var reg 72 7 in [71:0] $end
$var reg 40 8 onedigit [39:0] $end
$var reg 4 9 t0 [3:0] $end
$var reg 4 : t1 [3:0] $end
$upscope $end
$upscope $end
$upscope $end
$enddefinitions $end
#0
$dumpvars
bx :
bx 9
bx 8
bx 7
bx 6
bx 5
x4
bx 3
bx 2
x1
bx 0
bx /
x.
bx -
b0xxxxxxxxxxxxxxxxxxxxxxxxxxxxxxxxxxxxxxxxxxxxxxxxxxxxxxxxxxxxxxxxxxxxxxx0 ,
0+
b100001011000 *
bx )
1(
0'
0&
1%
b100001011000 $
0#
x"
bx !
$end
#10
04
0"
0.
b0 3
1&
1+
0%
0(
#20
b1000010110000 ,
b100001011000 -
b1 3
b101000 0
1#
1'
1%
1(
#30
0#
0'
#40
b10000101100000 ,
b10 3
b1000010110000 -
b11 :
b0 9
b1010 6
b0 8
b0 5
b1000010110000 7
1#
1'
#50
0#
0'
#60
b100001011000000 ,
b11 3
b10000101100000 -
b1010 6
b10000101100000 7
1#
1'
#70
0#
0'
#80
b1000010110000000 ,
b100 3
b100001011000000 -
b1010 6
b100001011000000 7
1#
1'
#90
0#
0'
#100
b10000101100000000 ,
b101 3
b1000010110000000 -
b1010 6
b1000010110000000 7
1#
1'
#110
0#
0'
#120
b100001011000000000 ,
b110 3
b10000101100000000 -
b1010 6
b10000101100000000 7
1#
1'
#130
0#
0'
#140
b1000010110000000000 ,
b111 3
b100001011000000000 -
b1010 6
b100001011000000000 7
1#
1'
#150
0#
0'
#160
b10000101100000000000 ,
b1000 3
b1000010110000000000 -
b1010 6
b1000010110000000000 7
1#
1'
#170
0#
0'
#180
b100001011000000000000 ,
b1001 3
b10000101100000000000 -
b1010 6
b10000101100000000000 7
1#
1'
#190
0#
0'
#200
b1000010110000000000000 ,
b1010 3
b100001011000000000000 -
b1010 6
b100001011000000000000 7
1#
1'
#210
0#
0'
#220
b10000101100000000000000 ,
b1011 3
b1000010110000000000000 -
b1010 6
b1000010110000000000000 7
1#
1'
#230
0#
0'
#240
b100001011000000000000000 ,
b1100 3
b10000101100000000000000 -
b1010 6
b10000101100000000000000 7
1#
1'
#250
0#
0'
#260
b1000010110000000000000000 ,
b1101 3
b100001011000000000000000 -
b1010 6
b100001011000000000000000 7
1#
1'
#270
0#
0'
#280
b10000101100000000000000000 ,
b1110 3
b1000010110000000000000000 -
b1010 6
b1000010110000000000000000 7
1#
1'
#290
0#
0'
#300
b100001011000000000000000000 ,
b1111 3
b10000101100000000000000000 -
b1010 6
b10000101100000000000000000 7
1#
1'
#310
0#
0'
#320
b1000010110000000000000000000 ,
b10000 3
b100001011000000000000000000 -
b1010 6
b100001011000000000000000000 7
1#
1'
#330
0#
0'
#340
b10000101100000000000000000000 ,
b10001 3
b1000010110000000000000000000 -
b1010 6
b1000010110000000000000000000 7
1#
1'
#350
0#
0'
#360
b100001011000000000000000000000 ,
b10010 3
b10000101100000000000000000000 -
b1010 6
b10000101100000000000000000000 7
1#
1'
#370
0#
0'
#380
b1000010110000000000000000000000 ,
b10011 3
b100001011000000000000000000000 -
b1010 6
b100001011000000000000000000000 7
1#
1'
#390
0#
0'
#400
b10000101100000000000000000000000 ,
b10100 3
b1000010110000000000000000000000 -
b1010 6
b1000010110000000000000000000000 7
1#
1'
#410
0#
0'
#420
b100001011000000000000000000000000 ,
b10101 3
b10000101100000000000000000000000 -
b1010 6
b10000101100000000000000000000000 7
1#
1'
#430
0#
0'
#440
b1000010110000000000000000000000000 ,
b10110 3
b100001011000000000000000000000000 -
b1 8
b11 :
b0 9
b1010 6
b0 5
b100001011000000000000000000000000 7
1#
1'
#450
0#
0'
#460
b10000101100000000000000000000000000 ,
b10111 3
b1000010110000000000000000000000000 -
b11 :
b0 9
b1010 6
b10 8
b0 5
b1000010110000000000000000000000000 7
1#
1'
#470
0#
0'
#480
b100001011000000000000000000000000000 ,
b11000 3
b10000101100000000000000000000000000 -
b11 :
b0 9
b1010 6
b100 8
b0 5
b10000101100000000000000000000000000 7
1#
1'
#490
0#
0'
#500
b1011010110000000000000000000000000000 ,
b11001 3
b101101011000000000000000000000000000 -
b11 :
b0 9
b1010 6
b1011 8
b0 5
b100001011000000000000000000000000000 7
1#
1'
#510
0#
0'
#520
b11001101100000000000000000000000000000 ,
b11010 3
b1100110110000000000000000000000000000 -
b11 :
b0 9
b1010 6
b11001 8
b0 5
b1011010110000000000000000000000000000 7
1#
1'
#530
0#
0'
#540
b110011011000000000000000000000000000000 ,
b11011 3
b11001101100000000000000000000000000000 -
b11 :
b0 9
b1010 6
b110011 8
b0 5
b11001101100000000000000000000000000000 7
1#
1'
#550
0#
0'
#560
b10011001110000000000000000000000000000000 ,
b11100 3
b1001100111000000000000000000000000000000 -
b11 :
b0 9
b1010 6
b10011001 8
b0 5
b110011011000000000000000000000000000000 7
1#
1'
#570
0#
0'
#580
b100110011100000000000000000000000000000000 ,
b11101 3
b10011001110000000000000000000000000000000 -
b11 :
b0 9
b1010 6
b100110011 8
b0 5
b10011001110000000000000000000000000000000 7
1#
1'
#590
0#
0'
#600
b1010011010000000000000000000000000000000000 ,
b11110 3
b101001101000000000000000000000000000000000 -
b11 :
b0 9
b1010 6
b1010011010 8
b0 5
b100110011100000000000000000000000000000000 7
1#
1'
#610
0#
0'
#620
b100000110100000000000000000000000000000000000 ,
b11111 3
b10000011010000000000000000000000000000000000 -
b11 :
b0 9
b1010 6
b100000110100 8
b0 5
b1010011010000000000000000000000000000000000 7
1#
1'
#630
0#
0'
#640
b1000010011011000000000000000000000000000000000 ,
b100000 3
b100001001101100000000000000000000000000000000 -
b11 :
b0 9
b1010 6
b1000010011011 8
b0 5
b100000110100000000000000000000000000000000000 7
1#
1'
#650
0#
0'
#660
1.
b100001 3
b10000100110110 /
1#
1'
#670
0#
0'
#680
11
0.
b0 3
1#
1'
#690
0#
0'
#700
b1000010110000 ,
b100100 0
b110000 2
b110000 !
b110000 )
14
1"
b100001011000 -
b1 3
1#
1'
#710
0#
0'
#720
b10000101100000 ,
b100000 0
b10 3
b1000010110000 -
b1010 6
b0 8
b1000010110000 7
1#
1'
#730
0#
0'
#740
b100001011000000 ,
b11100 0
b11 3
b10000101100000 -
b1010 6
b10000101100000 7
1#
1'
#750
0#
0'
#760
b1000010110000000 ,
b11000 0
b100 3
b100001011000000 -
b1010 6
b100001011000000 7
1#
1'
#770
0#
0'
#780
b10000101100000000 ,
b10100 0
b101 3
b1000010110000000 -
b1010 6
b1000010110000000 7
1#
1'
#790
0#
0'
#800
b100001011000000000 ,
b10000 0
b110 3
b10000101100000000 -
b1010 6
b10000101100000000 7
1#
1'
#810
0#
0'
#820
b1000010110000000000 ,
b1100 0
b110010 2
b110010 !
b110010 )
b111 3
b100001011000000000 -
b1010 6
b100001011000000000 7
1#
1'
#830
0#
0'
#840
b10000101100000000000 ,
b1000 0
b110001 2
b110001 !
b110001 )
b1000 3
b1000010110000000000 -
b1010 6
b1000010110000000000 7
1#
1'
#850
0#
0'
#860
b100001011000000000000 ,
b100 0
b110011 2
b110011 !
b110011 )
b1001 3
b10000101100000000000 -
b1010 6
b10000101100000000000 7
1#
1'
#870
0#
0'
#880
b1000010110000000000000 ,
b0 0
b110110 2
b110110 !
b110110 )
b1010 3
b100001011000000000000 -
b1010 6
b100001011000000000000 7
1#
1'
#890
0#
0'
#900
b10000101100000000000000 ,
01
04
0"
b101000 0
bx 2
bx !
bx )
b1011 3
b1000010110000000000000 -
b1010 6
b1000010110000000000000 7
1#
1'
#910
0#
0'
#920
b100001011000000000000000 ,
b1100 3
b10000101100000000000000 -
b1010 6
b10000101100000000000000 7
1#
1'
#930
0#
0'
#940
b1000010110000000000000000 ,
b1101 3
b100001011000000000000000 -
b1010 6
b100001011000000000000000 7
1#
1'
#950
0#
0'
#960
b10000101100000000000000000 ,
b1110 3
b1000010110000000000000000 -
b1010 6
b1000010110000000000000000 7
1#
1'
#970
0#
0'
#980
b100001011000000000000000000 ,
b1111 3
b10000101100000000000000000 -
b1010 6
b10000101100000000000000000 7
1#
1'
#990
0#
0'
#1000
b1000010110000000000000000000 ,
b10000 3
b100001011000000000000000000 -
b1010 6
b100001011000000000000000000 7
1#
1'
#1010
0#
0'
#1020
b10000101100000000000000000000 ,
b10001 3
b1000010110000000000000000000 -
b1010 6
b1000010110000000000000000000 7
1#
1'
#1030
0#
0'
#1040
b100001011000000000000000000000 ,
b10010 3
b10000101100000000000000000000 -
b1010 6
b10000101100000000000000000000 7
1#
1'
#1050
0#
0'
#1060
b1000010110000000000000000000000 ,
b10011 3
b100001011000000000000000000000 -
b1010 6
b100001011000000000000000000000 7
1#
1'
#1070
0#
0'
#1080
b10000101100000000000000000000000 ,
b10100 3
b1000010110000000000000000000000 -
b1010 6
b1000010110000000000000000000000 7
1#
1'
#1090
0#
0'
#1100
b100001011000000000000000000000000 ,
b10101 3
b10000101100000000000000000000000 -
b1010 6
b10000101100000000000000000000000 7
1#
1'
#1110
0#
0'
#1120
b1000010110000000000000000000000000 ,
b10110 3
b100001011000000000000000000000000 -
b1 8
b11 :
b0 9
b1010 6
b0 5
b100001011000000000000000000000000 7
1#
1'
#1130
0#
0'
#1140
b10000101100000000000000000000000000 ,
b10111 3
b1000010110000000000000000000000000 -
b11 :
b0 9
b1010 6
b10 8
b0 5
b1000010110000000000000000000000000 7
1#
1'
#1150
0#
0'
#1160
b100001011000000000000000000000000000 ,
b11000 3
b10000101100000000000000000000000000 -
b11 :
b0 9
b1010 6
b100 8
b0 5
b10000101100000000000000000000000000 7
1#
1'
#1170
0#
0'
#1180
b1011010110000000000000000000000000000 ,
b11001 3
b101101011000000000000000000000000000 -
b11 :
b0 9
b1010 6
b1011 8
b0 5
b100001011000000000000000000000000000 7
1#
1'
#1190
0#
0'
#1200
b11001101100000000000000000000000000000 ,
b11010 3
b1100110110000000000000000000000000000 -
b11 :
b0 9
b1010 6
b11001 8
b0 5
b1011010110000000000000000000000000000 7
1#
1'
#1210
0#
0'
#1220
b110011011000000000000000000000000000000 ,
b11011 3
b11001101100000000000000000000000000000 -
b11 :
b0 9
b1010 6
b110011 8
b0 5
b11001101100000000000000000000000000000 7
1#
1'
#1230
0#
0'
#1240
b10011001110000000000000000000000000000000 ,
b11100 3
b1001100111000000000000000000000000000000 -
b11 :
b0 9
b1010 6
b10011001 8
b0 5
b110011011000000000000000000000000000000 7
1#
1'
#1250
0#
0'
#1260
b100110011100000000000000000000000000000000 ,
b11101 3
b10011001110000000000000000000000000000000 -
b11 :
b0 9
b1010 6
b100110011 8
b0 5
b10011001110000000000000000000000000000000 7
1#
1'
#1270
0#
0'
#1280
b1010011010000000000000000000000000000000000 ,
b11110 3
b101001101000000000000000000000000000000000 -
b11 :
b0 9
b1010 6
b1010011010 8
b0 5
b100110011100000000000000000000000000000000 7
1#
1'
#1290
0#
0'
#1300
b100000110100000000000000000000000000000000000 ,
b11111 3
b10000011010000000000000000000000000000000000 -
b11 :
b0 9
b1010 6
b100000110100 8
b0 5
b1010011010000000000000000000000000000000000 7
1#
1'
#1310
0#
0'
#1320
b1000010011011000000000000000000000000000000000 ,
b100000 3
b100001001101100000000000000000000000000000000 -
b11 :
b0 9
b1010 6
b1000010011011 8
b0 5
b100000110100000000000000000000000000000000000 7
1#
1'
#1330
0#
0'
#1340
1.
b100001 3
1#
1'
#1350
0#
0'
#1360
11
0.
b0 3
1#
1'
#1370
0#
0'
#1380
b1000010110000 ,
b100100 0
b110000 2
b110000 !
b110000 )
14
1"
b100001011000 -
b1 3
1#
1'
#1390
0#
0'
#1400
b10000101100000 ,
b100000 0
b10 3
b1000010110000 -
b1010 6
b0 8
b1000010110000 7
1#
1'
#1410
0#
0'
#1420
b100001011000000 ,
b11100 0
b11 3
b10000101100000 -
b1010 6
b10000101100000 7
1#
1'
#1430
0#
0'
#1440
b1000010110000000 ,
b11000 0
b100 3
b100001011000000 -
b1010 6
b100001011000000 7
1#
1'
#1450
0#
0'
#1460
b10000101100000000 ,
b10100 0
b101 3
b1000010110000000 -
b1010 6
b1000010110000000 7
1#
1'
#1470
0#
0'
#1480
b100001011000000000 ,
b10000 0
b110 3
b10000101100000000 -
b1010 6
b10000101100000000 7
1#
1'
#1490
0#
0'
#1500
b1000010110000000000 ,
b1100 0
b110010 2
b110010 !
b110010 )
b111 3
b100001011000000000 -
b1010 6
b100001011000000000 7
1#
1'
#1510
0#
0'
#1520
b10000101100000000000 ,
b1000 0
b110001 2
b110001 !
b110001 )
b1000 3
b1000010110000000000 -
b1010 6
b1000010110000000000 7
1#
1'
#1530
0#
0'
#1540
b100001011000000000000 ,
b100 0
b110011 2
b110011 !
b110011 )
b1001 3
b10000101100000000000 -
b1010 6
b10000101100000000000 7
1#
1'
#1550
0#
0'
#1560
b1000010110000000000000 ,
b0 0
b110110 2
b110110 !
b110110 )
b1010 3
b100001011000000000000 -
b1010 6
b100001011000000000000 7
1#
1'
#1570
0#
0'
#1580
b10000101100000000000000 ,
01
04
0"
b101000 0
bx 2
bx !
bx )
b1011 3
b1000010110000000000000 -
b1010 6
b1000010110000000000000 7
1#
1'
#1590
0#
0'
#1600
b100001011000000000000000 ,
b1100 3
b10000101100000000000000 -
b1010 6
b10000101100000000000000 7
1#
1'
#1610
0#
0'
#1620
b1000010110000000000000000 ,
b1101 3
b100001011000000000000000 -
b1010 6
b100001011000000000000000 7
1#
1'
#1630
0#
0'
#1640
b10000101100000000000000000 ,
b1110 3
b1000010110000000000000000 -
b1010 6
b1000010110000000000000000 7
1#
1'
#1650
0#
0'
#1660
b100001011000000000000000000 ,
b1111 3
b10000101100000000000000000 -
b1010 6
b10000101100000000000000000 7
1#
1'
#1670
0#
0'
#1680
b1000010110000000000000000000 ,
b10000 3
b100001011000000000000000000 -
b1010 6
b100001011000000000000000000 7
1#
1'
#1690
0#
0'
#1700
b10000101100000000000000000000 ,
b10001 3
b1000010110000000000000000000 -
b1010 6
b1000010110000000000000000000 7
1#
1'
#1710
0#
0'
#1720
b100001011000000000000000000000 ,
b10010 3
b10000101100000000000000000000 -
b1010 6
b10000101100000000000000000000 7
1#
1'
#1730
0#
0'
#1740
b1000010110000000000000000000000 ,
b10011 3
b100001011000000000000000000000 -
b1010 6
b100001011000000000000000000000 7
1#
1'
#1750
0#
0'
#1760
b10000101100000000000000000000000 ,
b10100 3
b1000010110000000000000000000000 -
b1010 6
b1000010110000000000000000000000 7
1#
1'
#1770
0#
0'
#1780
b100001011000000000000000000000000 ,
b10101 3
b10000101100000000000000000000000 -
b1010 6
b10000101100000000000000000000000 7
1#
1'
#1790
0#
0'
#1800
b1000010110000000000000000000000000 ,
b10110 3
b100001011000000000000000000000000 -
b1 8
b11 :
b0 9
b1010 6
b0 5
b100001011000000000000000000000000 7
1#
1'
#1810
0#
0'
#1820
b10000101100000000000000000000000000 ,
b10111 3
b1000010110000000000000000000000000 -
b11 :
b0 9
b1010 6
b10 8
b0 5
b1000010110000000000000000000000000 7
1#
1'
#1830
0#
0'
#1840
b100001011000000000000000000000000000 ,
b11000 3
b10000101100000000000000000000000000 -
b11 :
b0 9
b1010 6
b100 8
b0 5
b10000101100000000000000000000000000 7
1#
1'
#1850
0#
0'
#1860
b1011010110000000000000000000000000000 ,
b11001 3
b101101011000000000000000000000000000 -
b11 :
b0 9
b1010 6
b1011 8
b0 5
b100001011000000000000000000000000000 7
1#
1'
#1870
0#
0'
#1880
b11001101100000000000000000000000000000 ,
b11010 3
b1100110110000000000000000000000000000 -
b11 :
b0 9
b1010 6
b11001 8
b0 5
b1011010110000000000000000000000000000 7
1#
1'
#1890
0#
0'
#1900
b110011011000000000000000000000000000000 ,
b11011 3
b11001101100000000000000000000000000000 -
b11 :
b0 9
b1010 6
b110011 8
b0 5
b11001101100000000000000000000000000000 7
1#
1'
#1910
0#
0'
#1920
b10011001110000000000000000000000000000000 ,
b11100 3
b1001100111000000000000000000000000000000 -
b11 :
b0 9
b1010 6
b10011001 8
b0 5
b110011011000000000000000000000000000000 7
1#
1'
#1930
0#
0'
#1940
b100110011100000000000000000000000000000000 ,
b11101 3
b10011001110000000000000000000000000000000 -
b11 :
b0 9
b1010 6
b100110011 8
b0 5
b10011001110000000000000000000000000000000 7
1#
1'
#1950
0#
0'
#1960
b1010011010000000000000000000000000000000000 ,
b11110 3
b101001101000000000000000000000000000000000 -
b11 :
b0 9
b1010 6
b1010011010 8
b0 5
b100110011100000000000000000000000000000000 7
1#
1'
#1970
0#
0'
#1980
b100000110100000000000000000000000000000000000 ,
b11111 3
b10000011010000000000000000000000000000000000 -
b11 :
b0 9
b1010 6
b100000110100 8
b0 5
b1010011010000000000000000000000000000000000 7
1#
1'
#1990
0#
0'
#2000
b1000010011011000000000000000000000000000000000 ,
b100000 3
b100001001101100000000000000000000000000000000 -
b11 :
b0 9
b1010 6
b1000010011011 8
b0 5
b100000110100000000000000000000000000000000000 7
1#
1'
#2010
0#
0'
#2020
1.
b100001 3
1#
1'
#2030
0#
0'
#2040
11
0.
b0 3
1#
1'
#2050
0#
0'
#2060
b1000010110000 ,
b100100 0
b110000 2
b110000 !
b110000 )
14
1"
b100001011000 -
b1 3
1#
1'
#2070
0#
0'
#2080
b10000101100000 ,
b100000 0
b10 3
b1000010110000 -
b1010 6
b0 8
b1000010110000 7
1#
1'
#2090
0#
0'
#2100
b100001011000000 ,
b11100 0
b11 3
b10000101100000 -
b1010 6
b10000101100000 7
1#
1'
#2110
0#
0'
#2120
b1000010110000000 ,
b11000 0
b100 3
b100001011000000 -
b1010 6
b100001011000000 7
1#
1'
#2130
0#
0'
#2140
b10000101100000000 ,
b10100 0
b101 3
b1000010110000000 -
b1010 6
b1000010110000000 7
1#
1'
#2150
0#
0'
#2160
b100001011000000000 ,
b10000 0
b110 3
b10000101100000000 -
b1010 6
b10000101100000000 7
1#
1'
#2170
0#
0'
#2180
b1000010110000000000 ,
b1100 0
b110010 2
b110010 !
b110010 )
b111 3
b100001011000000000 -
b1010 6
b100001011000000000 7
1#
1'
#2190
0#
0'
#2200
b10000101100000000000 ,
b1000 0
b110001 2
b110001 !
b110001 )
b1000 3
b1000010110000000000 -
b1010 6
b1000010110000000000 7
1#
1'
#2210
0#
0'
#2220
b100001011000000000000 ,
b100 0
b110011 2
b110011 !
b110011 )
b1001 3
b10000101100000000000 -
b1010 6
b10000101100000000000 7
1#
1'
#2230
0#
0'
#2240
b1000010110000000000000 ,
b0 0
b110110 2
b110110 !
b110110 )
b1010 3
b100001011000000000000 -
b1010 6
b100001011000000000000 7
1#
1'
#2250
0#
0'
#2260
b10000101100000000000000 ,
01
04
0"
b101000 0
bx 2
bx !
bx )
b1011 3
b1000010110000000000000 -
b1010 6
b1000010110000000000000 7
1#
1'
#2270
0#
0'
#2280
b100001011000000000000000 ,
b1100 3
b10000101100000000000000 -
b1010 6
b10000101100000000000000 7
1#
1'
#2290
0#
0'
#2300
b1000010110000000000000000 ,
b1101 3
b100001011000000000000000 -
b1010 6
b100001011000000000000000 7
1#
1'
#2310
0#
0'
#2320
b10000101100000000000000000 ,
b1110 3
b1000010110000000000000000 -
b1010 6
b1000010110000000000000000 7
1#
1'
#2330
0#
0'
#2340
b100001011000000000000000000 ,
b1111 3
b10000101100000000000000000 -
b1010 6
b10000101100000000000000000 7
1#
1'
#2350
0#
0'
#2360
b1000010110000000000000000000 ,
b10000 3
b100001011000000000000000000 -
b1010 6
b100001011000000000000000000 7
1#
1'
#2370
0#
0'
#2380
b10000101100000000000000000000 ,
b10001 3
b1000010110000000000000000000 -
b1010 6
b1000010110000000000000000000 7
1#
1'
#2390
0#
0'
#2400
b100001011000000000000000000000 ,
b10010 3
b10000101100000000000000000000 -
b1010 6
b10000101100000000000000000000 7
1#
1'
#2410
0#
0'
#2420
b1000010110000000000000000000000 ,
b10011 3
b100001011000000000000000000000 -
b1010 6
b100001011000000000000000000000 7
1#
1'
#2430
0#
0'
#2440
b10000101100000000000000000000000 ,
b10100 3
b1000010110000000000000000000000 -
b1010 6
b1000010110000000000000000000000 7
1#
1'
#2450
0#
0'
#2460
b100001011000000000000000000000000 ,
b10101 3
b10000101100000000000000000000000 -
b1010 6
b10000101100000000000000000000000 7
1#
1'
#2470
0#
0'
#2480
b1000010110000000000000000000000000 ,
b10110 3
b100001011000000000000000000000000 -
b1 8
b11 :
b0 9
b1010 6
b0 5
b100001011000000000000000000000000 7
1#
1'
#2490
0#
0'
#2500
b10000101100000000000000000000000000 ,
b10111 3
b1000010110000000000000000000000000 -
b11 :
b0 9
b1010 6
b10 8
b0 5
b1000010110000000000000000000000000 7
1#
1'
#2510
0#
0'
#2520
b100001011000000000000000000000000000 ,
b11000 3
b10000101100000000000000000000000000 -
b11 :
b0 9
b1010 6
b100 8
b0 5
b10000101100000000000000000000000000 7
1#
1'
#2530
0#
0'
#2540
b1011010110000000000000000000000000000 ,
b11001 3
b101101011000000000000000000000000000 -
b11 :
b0 9
b1010 6
b1011 8
b0 5
b100001011000000000000000000000000000 7
1#
1'
#2550
0#
0'
#2560
b11001101100000000000000000000000000000 ,
b11010 3
b1100110110000000000000000000000000000 -
b11 :
b0 9
b1010 6
b11001 8
b0 5
b1011010110000000000000000000000000000 7
1#
1'
#2570
0#
0'
#2580
b110011011000000000000000000000000000000 ,
b11011 3
b11001101100000000000000000000000000000 -
b11 :
b0 9
b1010 6
b110011 8
b0 5
b11001101100000000000000000000000000000 7
1#
1'
#2590
0#
0'
#2600
b10011001110000000000000000000000000000000 ,
b11100 3
b1001100111000000000000000000000000000000 -
b11 :
b0 9
b1010 6
b10011001 8
b0 5
b110011011000000000000000000000000000000 7
1#
1'
#2610
0#
0'
#2620
b100110011100000000000000000000000000000000 ,
b11101 3
b10011001110000000000000000000000000000000 -
b11 :
b0 9
b1010 6
b100110011 8
b0 5
b10011001110000000000000000000000000000000 7
1#
1'
#2630
0#
0'
#2640
b1010011010000000000000000000000000000000000 ,
b11110 3
b101001101000000000000000000000000000000000 -
b11 :
b0 9
b1010 6
b1010011010 8
b0 5
b100110011100000000000000000000000000000000 7
1#
1'
#2650
0#
0'
#2660
b100000110100000000000000000000000000000000000 ,
b11111 3
b10000011010000000000000000000000000000000000 -
b11 :
b0 9
b1010 6
b100000110100 8
b0 5
b1010011010000000000000000000000000000000000 7
1#
1'
#2670
0#
0'
#2680
b1000010011011000000000000000000000000000000000 ,
b100000 3
b100001001101100000000000000000000000000000000 -
b11 :
b0 9
b1010 6
b1000010011011 8
b0 5
b100000110100000000000000000000000000000000000 7
1#
1'
#2690
0#
0'
#2700
1.
b100001 3
1#
1'
#2710
0#
0'
#2720
11
0.
b0 3
1#
1'
#2730
0#
0'
#2740
b1000010110000 ,
b100100 0
b110000 2
b110000 !
b110000 )
14
1"
b100001011000 -
b1 3
1#
1'
#2750
0#
0'
#2760
b10000101100000 ,
b100000 0
b10 3
b1000010110000 -
b1010 6
b0 8
b1000010110000 7
1#
1'
#2770
0#
0'
#2780
b100001011000000 ,
b11100 0
b11 3
b10000101100000 -
b1010 6
b10000101100000 7
1#
1'
#2790
0#
0'
#2800
b1000010110000000 ,
b11000 0
b100 3
b100001011000000 -
b1010 6
b100001011000000 7
1#
1'
#2810
0#
0'
#2820
b10000101100000000 ,
b10100 0
b101 3
b1000010110000000 -
b1010 6
b1000010110000000 7
1#
1'
#2830
0#
0'
#2840
b100001011000000000 ,
b10000 0
b110 3
b10000101100000000 -
b1010 6
b10000101100000000 7
1#
1'
#2850
0#
0'
#2860
b1000010110000000000 ,
b1100 0
b110010 2
b110010 !
b110010 )
b111 3
b100001011000000000 -
b1010 6
b100001011000000000 7
1#
1'
#2870
0#
0'
#2880
b10000101100000000000 ,
b1000 0
b110001 2
b110001 !
b110001 )
b1000 3
b1000010110000000000 -
b1010 6
b1000010110000000000 7
1#
1'
#2890
0#
0'
#2900
b100001011000000000000 ,
b100 0
b110011 2
b110011 !
b110011 )
b1001 3
b10000101100000000000 -
b1010 6
b10000101100000000000 7
1#
1'
#2910
0#
0'
#2920
b1000010110000000000000 ,
b0 0
b110110 2
b110110 !
b110110 )
b1010 3
b100001011000000000000 -
b1010 6
b100001011000000000000 7
1#
1'
#2930
0#
0'
#2940
b10000101100000000000000 ,
01
04
0"
b101000 0
bx 2
bx !
bx )
b1011 3
b1000010110000000000000 -
b1010 6
b1000010110000000000000 7
1#
1'
#2950
0#
0'
#2960
b100001011000000000000000 ,
b1100 3
b10000101100000000000000 -
b1010 6
b10000101100000000000000 7
1#
1'
#2970
0#
0'
#2980
b1000010110000000000000000 ,
b1101 3
b100001011000000000000000 -
b1010 6
b100001011000000000000000 7
1#
1'
#2990
0#
0'
#3000
b10000101100000000000000000 ,
b1110 3
b1000010110000000000000000 -
b1010 6
b1000010110000000000000000 7
1#
1'
#3010
0#
0'
#3020
b100001011000000000000000000 ,
b1111 3
b10000101100000000000000000 -
b1010 6
b10000101100000000000000000 7
1#
1'
