BCD/lcd_top/lcd_control.v

module lcd_control
  (
   input        CLK,
   input        RST,

   output       update,
   output       lcd_row, 
   output [3:0] lcd_col,
   output [7:0] lcd_char,
   output       lcd_we,

   input        lcd_busy,

   input        valid_i,
   input        start_update,
   input [7:0]  char
   );

`define SW 4
   reg [79:0]   char_reg;
   reg          getchar_from_num2char_flg, wait_getchar_from_num2char;
   
   parameter s_wait_init = `SW'd0;
   parameter s_0         = `SW'd1;
   parameter s_1         = `SW'd2;
   parameter s_2         = `SW'd3;
   parameter s_3         = `SW'd4;
   parameter s_4         = `SW'd5;
   parameter s_5         = `SW'd6;
   parameter s_6         = `SW'd7;
   parameter s_7         = `SW'd8;
   parameter s_8         = `SW'd9;
   parameter s_9         = `SW'd10;
   parameter s_update    = `SW'd11;
   parameter s_idle      = `SW'd12;

   reg [`SW-1:0] state; 
   reg [4:0]     s,getchar_from_num2char_state;
`undef SW

   
   assign lcd_char = 
					 state == s_0?  char_reg[7:0] : 
                     state == s_1?  char_reg[15:8] : 
                     state == s_2?  char_reg[23:16] : 
                     state == s_3?  char_reg[31:24] : 
                     state == s_4?  char_reg[39:32] : 
                     state == s_5?  char_reg[47:40] : 
                     state == s_6?  char_reg[55:48] : 
                     state == s_7?  char_reg[63:56] : 
                     state == s_8?  char_reg[71:64] : 
                     state == s_9?  char_reg[79:72] :
                     3'h0;
   
   assign lcd_we   = state != s_wait_init && state != s_idle && state != s_update;
   assign lcd_row  = 1;
   //!(state == s_h
   //|| state == s_e
   //|| state == s_l1
   //|| state == s_l2
   //|| state == s_o1);
   
   assign update = state == s_update;
   
   assign lcd_col = 
                    state == s_0?  4'd0 : 
                    state == s_1?  4'd1 : 
                    state == s_2?  4'd2 : 
                    state == s_3?  4'd3 : 
                    state == s_4?  4'd4 : 
                    state == s_5?  4'd5 : 
                    state == s_6?  4'd6 : 
                    state == s_7?  4'd7 : 
                    state == s_8?  4'd8 : 
                    state == s_9?  4'd9 :
                    3'h0;                     
   
   always @(posedge CLK or negedge RST)
     if (!RST) begin
        state <= s_wait_init;
        getchar_from_num2char_flg <= 0;
        wait_getchar_from_num2char <= 0; 
        char_reg <= 0;
        
        s <= 0;
     end else begin
        case (state)
          s_wait_init: 
            if (!lcd_busy)
              state <= s_idle;

          s_idle:
            if (start_update)
              state <= s_0;

          s_0:        
            state <= s_1;
          s_1:
            state <= s_2;
          s_2:
            state <= s_3;
          s_3:
            state <= s_4;
          s_4:
            state <= s_5;
          s_5:
            state <= s_6;
          s_6:
            state <= s_7;
          s_7:
            state <= s_8;
          s_8:
            state <= s_9;
          s_9:
            state <= s_update;
          s_update:
            if (!lcd_busy)
              state <= s_idle;		  
          default: ;
          
        endcase
		
        
		if(getchar_from_num2char_flg == 1)
          begin
             if(valid_i == 1)
               begin
				  if(getchar_from_num2char_state == 4'd0)   char_reg[7:0]    <= char; 
 				  if(getchar_from_num2char_state == 4'd1)   char_reg[15:8]   <= char; 
 				  if(getchar_from_num2char_state == 4'd2)   char_reg[23:16]  <= char; 
 				  if(getchar_from_num2char_state == 4'd3)   char_reg[31:24]  <= char; 
 				  if(getchar_from_num2char_state == 4'd4)   char_reg[39:32]  <= char; 
 				  if(getchar_from_num2char_state == 4'd5)   char_reg[47:40]  <= char; 
 				  if(getchar_from_num2char_state == 4'd6)   char_reg[55:48]  <= char; 
 				  if(getchar_from_num2char_state == 4'd7)   char_reg[63:56]  <= char; 
 				  if(getchar_from_num2char_state == 4'd8)   char_reg[71:64]  <= char; 
 				  if(getchar_from_num2char_state == 4'd9)   char_reg[79:72]  <= char;    
				  getchar_from_num2char_state <= getchar_from_num2char_state + 1;
               end
             else
               begin
                  getchar_from_num2char_flg <= 0;
				  getchar_from_num2char_state <= 0;
               end
          end
        else if(start_update == 1)
          begin
			 getchar_from_num2char_state <= 0; 
             if(valid_i == 1)
               wait_getchar_from_num2char <= 0;
             else
               getchar_from_num2char_flg <= 1;
          end
        
        if(wait_getchar_from_num2char == 1)
          begin
             if(valid_i == 0)
               begin
                  getchar_from_num2char_flg <= 1;
                  wait_getchar_from_num2char <= 0;                 
               end
          end
        
     end

endmodule

BCD/num2char/num2char.v
`define BWW 6
`define BW  32
`define DW  10
`define DWW 4
`define DWB 40



module num2char
  (
   input        CLK,
   input        RST,

   input        start_update,
   input [31:0] error_rate,

   output [7:0] char,
   output       valid_o
   );

   reg [`BWW:0] state;
   reg [`BW+`DWB-1:0] AllReg;
   reg [`DWB-1:0]     char_reg;

   reg [7:0]          dispchar;
   reg                char_ready;
   reg [7:0]          cnt;
   reg                valid_out, disp_start;

   wire [`BW+`DWB:0]  tempReg;

   assign tempReg = {AllReg[`BW+`DWB-2:0],1'b0};
   assign char = dispchar;
   assign valid_o = valid_out;


   always@(posedge CLK or negedge RST)
     begin
        if(!RST)
          begin
             state <= 0;
             char_ready <= 0;
             valid_out <= 0;

          end
        else
          begin
             if(state == 0)
               begin
                  if(start_update == 1)
                    begin
                       cnt <= 40;
                       state <= 1;
                       AllReg <= {`DWB'b0, error_rate};
                    end
               end
             else if(state < (`BW))
               begin
                  AllReg <= {onedigit(tempReg), tempReg[`BW-1:0]};
                  state <= state +1;
               end
             else if(state == (`BW))
               begin
                  char_reg <= tempReg[`BW+`DWB-1:`BW];
                  state <= state +1;
                  char_ready <= 1;
               end
             else if(char_ready == 1)
               begin
                  state <= 0;
                  char_ready <= 0;
                  disp_start <= 1;
               end
             if (disp_start == 1)
               begin
                  valid_out <= 1;
                  dispchar <= ({char_reg[(cnt-4)+3], char_reg[(cnt-4)+2], char_reg[(cnt-4)+1], char_reg[(cnt-4)]}) +8'h30;
                  cnt <=  cnt - 4;
                  if(cnt == 0)
                    begin
                       cnt <= 40;
                       valid_out <= 0;
                       disp_start <= 0;
                    end
               end
          end
     end

   function [`DWB-1:0] onedigit;
      input  [`BW+`DWB-1:0] in;
      reg [3:0]             t0,t1;
      reg [`DWB-1:0]        a;
      integer               i;

      begin
         a = in[`BW+`DWB-1:`BW];
         onedigit = 0;
         for (i=0; i<`DW; i=i+1)
           begin
              onedigit =onedigit>>4;
              t0 = a[3:0];
              a = a >> 4;
              t1 = t0 +2'b11;
              if(t1[3] == 1)
                begin
                   onedigit = {t1[3:0], onedigit[`DWB-5:0]};
                end
              else
                begin
                   onedigit = {t0[3:0], onedigit[`DWB-5:0]};
                end
           end
      end
   endfunction

endmodule // num2char

BCD/HelloWorld/lcd_ber_top.v

module lcd_ber_top
  (
   input        CLK,
   input        RST,

   output       update,
   output       lcd_row, 
   output [3:0] lcd_col,
   output [7:0] lcd_char,
   output       lcd_we,

   input        lcd_busy,
   input        start,

   input        valid_i,
   input [7:0]  sent_data,
   input [7:0]  recv_data,
   input [3:0]  number_of_bits 
   );

   wire         ber_valid_o;
   wire [31:0]  error_rate;

   wire         start_update;
   wire [7:0]   char;
   wire         n2c_valid_o;

   assign start_update = start;
 	reg[31:0] error_rate_reg;
	
	assign error_rate = error_rate_reg;
	
	always@(CLK)
		begin
			error_rate_reg <= 32'd123456789;
		end
	
 /*  ber ber_inst
     (
      .CLK(CLK),
      .RST(RST),

      .valid_i(valid_i),
      .sent_data(sent_data),
      .recv_data(recv_data),
      .number_of_bits(number_of_bits),

      .valid_o(ber_valid_o),
      .error_rate(error_rate)
      );
		*/
   num2char num2char_inst
     (
      .CLK(CLK),
      .RST(RST),

      .start_update(start_update),
      .error_rate(error_rate),

      .char(char),
      .valid_o(n2c_valid_o)
      );

   lcd_control lcd_control_inst
     (
      .CLK(CLK),
      .RST(RST),

      .start_update(start_update),
      .lcd_row(lcd_row), 
      .lcd_col(lcd_col),
      .lcd_char(lcd_char),
      .lcd_we(lcd_we),

      .lcd_busy(lcd_busy),

      .valid_i(n2c_valid_o),
      .update(update),
      .char(char)
      );
   
endmodule // lcd_test

BCD/HelloWorld/test_lcd.v

module test_lcd_control;

   reg clk,rst,start_update, busy;
   reg [7:0] char;
   reg       valid;
   
   initial begin rst=1;
      #10 rst=0;
      #10 rst=1;
      #3000 $finish;

   end
   initial
     begin
        $dumpvars;
        $dumpfile("stm.vcd");
        #0
        busy <= 0;      
        start_update <= 0;
        clk=0;
     end

   always #10 clk <= ~clk;
   always #120 busy <= ~busy;
   always #120 start_update <= ~start_update;
   
   
   initial begin
           
        #50
          start_update <= 1;
        #60
          valid <= 1;
        #70
          start_update <= 0;
          char <=31;
        #80
          char <=32;
        #90 
          char <=33;
        #100
          valid <= 0;
        
        
        
     end // initial begin
   
   lcd_ber_top top_inst(.CLK(clk), .RST(rst), .lcd_busy(busy), .start(start_update));
   
   
endmodule

BCD/HelloWorld/dump.vcd
$date
	Mon Dec  9 14:02:19 2013
$end
$version
	Icarus Verilog
$end
$timescale
	1s
$end
$scope module test_lcd_control $end
$var reg 1 ! busy $end
$var reg 8 " char [7:0] $end
$var reg 1 # clk $end
$var reg 1 $ rst $end
$var reg 1 % start_update $end
$var reg 1 & valid $end
$scope module top_inst $end
$var wire 1 ' CLK $end
$var wire 1 ( RST $end
$var wire 8 ) char [7:0] $end
$var wire 32 * error_rate [31:0] $end
$var wire 1 + lcd_busy $end
$var wire 8 , lcd_char [7:0] $end
$var wire 4 - lcd_col [3:0] $end
$var wire 1 . lcd_row $end
$var wire 1 / lcd_we $end
$var wire 1 0 n2c_valid_o $end
$var wire 4 1 number_of_bits [3:0] $end
$var wire 8 2 recv_data [7:0] $end
$var wire 8 3 sent_data [7:0] $end
$var wire 1 4 start $end
$var wire 1 5 start_update $end
$var wire 1 6 update $end
$var wire 1 7 valid_i $end
$var reg 32 8 error_rate_reg [31:0] $end
$scope module num2char_inst $end
$var wire 1 ' CLK $end
$var wire 1 ( RST $end
$var wire 8 9 char [7:0] $end
$var wire 32 : error_rate [31:0] $end
$var wire 1 5 start_update $end
$var wire 73 ; tempReg [72:0] $end
$var wire 1 0 valid_o $end
$var reg 72 < AllReg [71:0] $end
$var reg 1 = char_ready $end
$var reg 40 > char_reg [39:0] $end
$var reg 8 ? cnt [7:0] $end
$var reg 1 @ disp_start $end
$var reg 8 A dispchar [7:0] $end
$var reg 7 B state [6:0] $end
$var reg 1 C valid_out $end
$scope function onedigit $end
$var reg 40 D a [39:0] $end
$var integer 32 E i [31:0] $end
$var reg 72 F in [71:0] $end
$var reg 40 G onedigit [39:0] $end
$var reg 4 H t0 [3:0] $end
$var reg 4 I t1 [3:0] $end
$upscope $end
$upscope $end
$scope module lcd_control_inst $end
$var wire 1 ' CLK $end
$var wire 1 ( RST $end
$var wire 8 J char [7:0] $end
$var wire 1 + lcd_busy $end
$var wire 8 K lcd_char [7:0] $end
$var wire 4 L lcd_col [3:0] $end
$var wire 1 . lcd_row $end
$var wire 1 / lcd_we $end
$var wire 1 5 start_update $end
$var wire 1 6 update $end
$var wire 1 0 valid_i $end
$var reg 80 M char_reg [79:0] $end
$var reg 1 N getchar_from_num2char_flg $end
$var reg 5 O getchar_from_num2char_state [4:0] $end
$var reg 5 P s [4:0] $end
$var reg 4 Q state [3:0] $end
$var reg 1 R wait_getchar_from_num2char $end
$upscope $end
$upscope $end
$upscope $end
$enddefinitions $end
#0
$dumpvars
xR
bx Q
bx P
bx O
xN
bx M
bx L
bx K
bx J
bx I
bx H
bx G
bx F
bx E
bx D
xC
bx B
bx A
x@
bx ?
bx >
x=
bx <
b0xxxxxxxxxxxxxxxxxxxxxxxxxxxxxxxxxxxxxxxxxxxxxxxxxxxxxxxxxxxxxxxxxxxxxxx0 ;
b100100100 :
bx 9
b100100100 8
z7
x6
05
04
bz 3
bz 2
bz 1
x0
x/
1.
bx -
bx ,
0+
b100100100 *
bx )
1(
0'
x&
0%
1$
0#
bx "
0!
$end
#10
0/
b0 ,
b0 K
b0 -
b0 L
0C
00
0=
b0 B
b0 P
b0 M
0R
0N
b0 Q
06
1#
1'
0$
0(
#20
0#
0'
1$
1(
#30
b1100 Q
1#
1'
#40
0#
0'
#50
1/
b1001001000 ;
1N
b0 O
b1 Q
b100100100 <
b1 B
b101000 ?
1#
1'
1%
15
14
#60
0#
0'
#70
b10010010000 ;
b1 -
b1 L
b10 B
b1001001000 <
0N
b10 Q
b11 I
b0 H
b1010 E
b0 G
b0 D
b1001001000 F
1#
1'
#80
0#
0'
#90
b10 -
b10 L
b100100100000 ;
1N
b11 Q
b11 B
b10010010000 <
b1010 E
b10010010000 F
1#
1'
#100
0#
0'
#110
b11 -
b11 L
b1001001000000 ;
b100 B
b100100100000 <
0N
b100 Q
b1010 E
b100100100000 F
1#
1'
1&
#120
0#
0'
0%
05
04
1!
1+
#130
b100 -
b100 L
b10010010000000 ;
b101 Q
b101 B
b1001001000000 <
b1010 E
b1001001000000 F
1#
1'
#140
0#
0'
#150
b101 -
b101 L
b100100100000000 ;
b110 B
b10010010000000 <
b110 Q
b1010 E
b10010010000000 F
1#
1'
#160
0#
0'
#170
b110 -
b110 L
b1001001000000000 ;
b111 Q
b111 B
b100100100000000 <
b1010 E
b100100100000000 F
1#
1'
#180
0#
0'
b11111 "
#190
b111 -
b111 L
b10010010000000000 ;
b1000 B
b1001001000000000 <
b1000 Q
b1010 E
b1001001000000000 F
1#
1'
#200
0#
0'
#210
b1000 -
b1000 L
b100100100000000000 ;
b1001 Q
b1001 B
b10010010000000000 <
b1010 E
b10010010000000000 F
1#
1'
#220
0#
0'
#230
b1001 -
b1001 L
b1001001000000000000 ;
b1010 B
b100100100000000000 <
b1010 Q
b1010 E
b100100100000000000 F
1#
1'
#240
0#
0'
1%
15
14
0!
0+
#250
b0 -
b0 L
0/
b10010010000000000000 ;
1N
b1011 Q
16
b1011 B
b1001001000000000000 <
b1010 E
b1001001000000000000 F
1#
1'
#260
0#
0'
b100000 "
#270
b100100100000000000000 ;
0/
b1100 B
b10010010000000000000 <
0N
b1100 Q
06
b1010 E
b10010010000000000000 F
1#
1'
#280
0#
0'
#290
1/
b1001001000000000000000 ;
1N
b1 Q
b1101 B
b100100100000000000000 <
b1010 E
b100100100000000000000 F
1#
1'
#300
0#
0'
#310
b10010010000000000000000 ;
b1 -
b1 L
b1110 B
b1001001000000000000000 <
0N
b10 Q
b1010 E
b1001001000000000000000 F
1#
1'
#320
0#
0'
#330
b10 -
b10 L
b100100100000000000000000 ;
1N
b11 Q
b1111 B
b10010010000000000000000 <
b1010 E
b10010010000000000000000 F
1#
1'
#340
0#
0'
#350
b11 -
b11 L
b1001001000000000000000000 ;
b10000 B
b100100100000000000000000 <
0N
b100 Q
b1010 E
b100100100000000000000000 F
1#
1'
b100001 "
#360
0#
0'
0%
05
04
1!
1+
#370
b100 -
b100 L
b10010010000000000000000000 ;
b101 Q
b10001 B
b1001001000000000000000000 <
b1010 E
b1001001000000000000000000 F
1#
1'
#380
0#
0'
#390
b101 -
b101 L
b100100100000000000000000000 ;
b10010 B
b10010010000000000000000000 <
b110 Q
b1010 E
b10010010000000000000000000 F
1#
1'
#400
0#
0'
#410
b110 -
b110 L
b1001001000000000000000000000 ;
b111 Q
b10011 B
b100100100000000000000000000 <
b1010 E
b100100100000000000000000000 F
1#
1'
#420
0#
0'
#430
b111 -
b111 L
b10010010000000000000000000000 ;
b10100 B
b1001001000000000000000000000 <
b1000 Q
b1010 E
b1001001000000000000000000000 F
1#
1'
#440
0#
0'
#450
b1000 -
b1000 L
b100100100000000000000000000000 ;
b1001 Q
b10101 B
b10010010000000000000000000000 <
b1010 E
b10010010000000000000000000000 F
1#
1'
0&
#460
0#
0'
#470
b1001 -
b1001 L
b1001001000000000000000000000000 ;
b10110 B
b100100100000000000000000000000 <
b1010 Q
b1010 E
b100100100000000000000000000000 F
1#
1'
#480
0#
0'
1%
15
14
0!
0+
#490
b0 -
b0 L
0/
b10010010000000000000000000000000 ;
1N
b1011 Q
16
b10111 B
b1001001000000000000000000000000 <
b1010 E
b1001001000000000000000000000000 F
1#
1'
#500
0#
0'
#510
b100100100000000000000000000000000 ;
0/
b11000 B
b10010010000000000000000000000000 <
0N
b1100 Q
06
b1010 E
b10010010000000000000000000000000 F
1#
1'
#520
0#
0'
#530
1/
b1001001000000000000000000000000000 ;
1N
b1 Q
b11001 B
b100100100000000000000000000000000 <
b1 G
b11 I
b0 H
b1010 E
b0 D
b100100100000000000000000000000000 F
1#
1'
#540
0#
0'
#550
b10010010000000000000000000000000000 ;
b1 -
b1 L
b11010 B
b1001001000000000000000000000000000 <
0N
b10 Q
b11 I
b0 H
b1010 E
b10 G
b0 D
b1001001000000000000000000000000000 F
1#
1'
#560
0#
0'
#570
b10 -
b10 L
b100100100000000000000000000000000000 ;
1N
b11 Q
b11011 B
b10010010000000000000000000000000000 <
b11 I
b0 H
b1010 E
b100 G
b0 D
b10010010000000000000000000000000000 F
1#
1'
#580
0#
0'
#590
b11 -
b11 L
b1100001000000000000000000000000000000 ;
b11100 B
b110000100000000000000000000000000000 <
0N
b100 Q
b11 I
b0 H
b1010 E
b1100 G
b0 D
b100100100000000000000000000000000000 F
1#
1'
#600
0#
0'
0%
05
04
1!
1+
#610
b100 -
b100 L
b11011010000000000000000000000000000000 ;
b101 Q
b11101 B
b1101101000000000000000000000000000000 <
b11 I
b0 H
b1010 E
b11011 G
b0 D
b1100001000000000000000000000000000000 F
1#
1'
#620
0#
0'
#630
b101 -
b101 L
b111001100000000000000000000000000000000 ;
b11110 B
b11100110000000000000000000000000000000 <
b110 Q
b11 I
b0 H
b1010 E
b111001 G
b0 D
b11011010000000000000000000000000000000 F
1#
1'
#640
0#
0'
#650
b110 -
b110 L
b10100011000000000000000000000000000000000 ;
b111 Q
b11111 B
b1010001100000000000000000000000000000000 <
b11 I
b0 H
b1010 E
b10100011 G
b0 D
b111001100000000000000000000000000000000 F
1#
1'
#660
0#
0'
#670
b111 -
b111 L
b101001001000000000000000000000000000000000 ;
b100000 B
b10100100100000000000000000000000000000000 <
b1000 Q
b11 I
b0 H
b1010 E
b101001001 G
b0 D
b10100011000000000000000000000000000000000 F
1#
1'
#680
0#
0'
#690
b1000 -
b1000 L
b1001 Q
1=
b100001 B
b1010010010 >
1#
1'
#700
0#
0'
#710
b1001 -
b1001 L
1@
0=
b0 B
b1010 Q
1#
1'
#720
0#
0'
1%
15
14
0!
0+
#730
b0 -
b0 L
0/
b1001001000 ;
1N
b1011 Q
16
b100100 ?
b110000 A
b110000 )
b110000 9
b110000 J
1C
10
b100100100 <
b1 B
1#
1'
#740
0#
0'
#750
b10010010000 ;
0/
b100000 ?
b10 B
b1001001000 <
b1 O
b110000 M
b1100 Q
06
b1010 E
b0 G
b1001001000 F
1#
1'
#760
0#
0'
#770
1/
b110000 ,
b110000 K
b100100100000 ;
b10 O
b11000000110000 M
b1 Q
b11100 ?
b11 B
b10010010000 <
b1010 E
b10010010000 F
1#
1'
#780
0#
0'
#790
b1001001000000 ;
b1 -
b1 L
b11000 ?
b100 B
b100100100000 <
b11 O
b1100000011000000110000 M
b10 Q
b1010 E
b100100100000 F
1#
1'
#800
0#
0'
#810
b10 -
b10 L
b10010010000000 ;
b100 O
b110000001100000011000000110000 M
b11 Q
b10100 ?
b101 B
b1001001000000 <
b1010 E
b1001001000000 F
1#
1'
#820
0#
0'
#830
b11 -
b11 L
b100100100000000 ;
b10000 ?
b110 B
b10010010000000 <
b101 O
b11000000110000001100000011000000110000 M
b100 Q
b1010 E
b10010010000000 F
1#
1'
#840
0#
0'
0%
05
04
1!
1+
#850
b100 -
b100 L
b1001001000000000 ;
b110 O
b1100000011000000110000001100000011000000110000 M
b101 Q
b1100 ?
b111 B
b100100100000000 <
b1010 E
b100100100000000 F
1#
1'
#860
0#
0'
#870
b101 -
b101 L
b10010010000000000 ;
b1000 ?
b110010 A
b110010 )
b110010 9
b110010 J
b1000 B
b1001001000000000 <
b111 O
b110000001100000011000000110000001100000011000000110000 M
b110 Q
b1010 E
b1001001000000000 F
1#
1'
#880
0#
0'
#890
b110 -
b110 L
b100100100000000000 ;
b1000 O
b11001000110000001100000011000000110000001100000011000000110000 M
b111 Q
b100 ?
b111001 A
b111001 )
b111001 9
b111001 J
b1001 B
b10010010000000000 <
b1010 E
b10010010000000000 F
1#
1'
#900
0#
0'
#910
b110010 ,
b110010 K
b111 -
b111 L
b1001001000000000000 ;
b0 ?
b110010 A
b110010 )
b110010 9
b110010 J
b1010 B
b100100100000000000 <
b1001 O
b1110010011001000110000001100000011000000110000001100000011000000110000 M
b1000 Q
b1010 E
b100100100000000000 F
1#
1'
#920
0#
0'
#930
b111001 ,
b111001 K
b1000 -
b1000 L
b10010010000000000000 ;
b1010 O
b110010001110010011001000110000001100000011000000110000001100000011000000110000 M
b1001 Q
0@
0C
00
b101000 ?
bx A
bx )
bx 9
bx J
b1011 B
b1001001000000000000 <
b1010 E
b1001001000000000000 F
1#
1'
#940
0#
0'
#950
b110010 ,
b110010 K
b1001 -
b1001 L
b100100100000000000000 ;
b1100 B
b10010010000000000000 <
b0 O
0N
b1010 Q
b1010 E
b10010010000000000000 F
1#
1'
#960
0#
0'
1%
15
14
0!
0+
#970
b0 ,
b0 K
b0 -
b0 L
0/
b1001001000000000000000 ;
1N
b1011 Q
16
b1101 B
b100100100000000000000 <
b1010 E
b100100100000000000000 F
1#
1'
#980
0#
0'
#990
b10010010000000000000000 ;
0/
b1110 B
b1001001000000000000000 <
0N
b1100 Q
06
b1010 E
b1001001000000000000000 F
1#
1'
#1000
0#
0'
#1010
1/
b110000 ,
b110000 K
b100100100000000000000000 ;
1N
b1 Q
b1111 B
b10010010000000000000000 <
b1010 E
b10010010000000000000000 F
1#
1'
#1020
0#
0'
#1030
b1001001000000000000000000 ;
b1 -
b1 L
b10000 B
b100100100000000000000000 <
0N
b10 Q
b1010 E
b100100100000000000000000 F
1#
1'
#1040
0#
0'
#1050
b10 -
b10 L
b10010010000000000000000000 ;
1N
b11 Q
b10001 B
b1001001000000000000000000 <
b1010 E
b1001001000000000000000000 F
1#
1'
#1060
0#
0'
#1070
b11 -
b11 L
b100100100000000000000000000 ;
b10010 B
b10010010000000000000000000 <
0N
b100 Q
b1010 E
b10010010000000000000000000 F
1#
1'
#1080
0#
0'
0%
05
04
1!
1+
#1090
b100 -
b100 L
b1001001000000000000000000000 ;
b101 Q
b10011 B
b100100100000000000000000000 <
b1010 E
b100100100000000000000000000 F
1#
1'
#1100
0#
0'
#1110
b101 -
b101 L
b10010010000000000000000000000 ;
b10100 B
b1001001000000000000000000000 <
b110 Q
b1010 E
b1001001000000000000000000000 F
1#
1'
#1120
0#
0'
#1130
b110 -
b110 L
b100100100000000000000000000000 ;
b111 Q
b10101 B
b10010010000000000000000000000 <
b1010 E
b10010010000000000000000000000 F
1#
1'
#1140
0#
0'
#1150
b110010 ,
b110010 K
b111 -
b111 L
b1001001000000000000000000000000 ;
b10110 B
b100100100000000000000000000000 <
b1000 Q
b1010 E
b100100100000000000000000000000 F
1#
1'
#1160
0#
0'
#1170
b111001 ,
b111001 K
b1000 -
b1000 L
b10010010000000000000000000000000 ;
b1001 Q
b10111 B
b1001001000000000000000000000000 <
b1010 E
b1001001000000000000000000000000 F
1#
1'
#1180
0#
0'
#1190
b110010 ,
b110010 K
b1001 -
b1001 L
b100100100000000000000000000000000 ;
b11000 B
b10010010000000000000000000000000 <
b1010 Q
b1010 E
b10010010000000000000000000000000 F
1#
1'
#1200
0#
0'
1%
15
14
0!
0+
#1210
b0 ,
b0 K
b0 -
b0 L
0/
b1001001000000000000000000000000000 ;
1N
b1011 Q
16
b11001 B
b100100100000000000000000000000000 <
b1 G
b11 I
b0 H
b1010 E
b0 D
b100100100000000000000000000000000 F
1#
1'
#1220
0#
0'
#1230
b10010010000000000000000000000000000 ;
0/
b11010 B
b1001001000000000000000000000000000 <
0N
b1100 Q
06
b11 I
b0 H
b1010 E
b10 G
b0 D
b1001001000000000000000000000000000 F
1#
1'
#1240
0#
0'
#1250
1/
b110000 ,
b110000 K
b100100100000000000000000000000000000 ;
1N
b1 Q
b11011 B
b10010010000000000000000000000000000 <
b11 I
b0 H
b1010 E
b100 G
b0 D
b10010010000000000000000000000000000 F
1#
1'
#1260
0#
0'
#1270
b1100001000000000000000000000000000000 ;
b1 -
b1 L
b11100 B
b110000100000000000000000000000000000 <
0N
b10 Q
b11 I
b0 H
b1010 E
b1100 G
b0 D
b100100100000000000000000000000000000 F
1#
1'
#1280
0#
0'
#1290
b10 -
b10 L
b11011010000000000000000000000000000000 ;
1N
b11 Q
b11101 B
b1101101000000000000000000000000000000 <
b11 I
b0 H
b1010 E
b11011 G
b0 D
b1100001000000000000000000000000000000 F
1#
1'
#1300
0#
0'
#1310
b11 -
b11 L
b111001100000000000000000000000000000000 ;
b11110 B
b11100110000000000000000000000000000000 <
0N
b100 Q
b11 I
b0 H
b1010 E
b111001 G
b0 D
b11011010000000000000000000000000000000 F
1#
1'
#1320
0#
0'
0%
05
04
1!
1+
#1330
b100 -
b100 L
b10100011000000000000000000000000000000000 ;
b101 Q
b11111 B
b1010001100000000000000000000000000000000 <
b11 I
b0 H
b1010 E
b10100011 G
b0 D
b111001100000000000000000000000000000000 F
1#
1'
#1340
0#
0'
#1350
b101 -
b101 L
b101001001000000000000000000000000000000000 ;
b100000 B
b10100100100000000000000000000000000000000 <
b110 Q
b11 I
b0 H
b1010 E
b101001001 G
b0 D
b10100011000000000000000000000000000000000 F
1#
1'
#1360
0#
0'
#1370
b110 -
b110 L
b111 Q
1=
b100001 B
1#
1'
#1380
0#
0'
#1390
b110010 ,
b110010 K
b111 -
b111 L
1@
0=
b0 B
b1000 Q
1#
1'
#1400
0#
0'
#1410
b111001 ,
b111001 K
b1000 -
b1000 L
b1001 Q
b100100 ?
b110000 A
b110000 )
b110000 9
b110000 J
1C
10
1#
1'
#1420
0#
0'
#1430
b110010 ,
b110010 K
b1001 -
b1001 L
b100000 ?
b1010 Q
1#
1'
#1440
0#
0'
1%
15
14
0!
0+
#1450
b0 ,
b0 K
b0 -
b0 L
0/
b1001001000 ;
b1011 Q
16
b100100100 <
b1 B
b11100 ?
1#
1'
#1460
0#
0'
#1470
b10010010000 ;
0/
b11000 ?
b10 B
b1001001000 <
b1100 Q
06
b1010 E
b0 G
b1001001000 F
1#
1'
#1480
0#
0'
#1490
1/
b110000 ,
b110000 K
b100100100000 ;
b1 Q
b10100 ?
b11 B
b10010010000 <
b1010 E
b10010010000 F
1#
1'
#1500
0#
0'
#1510
b1001001000000 ;
b1 -
b1 L
b10000 ?
b100 B
b100100100000 <
b10 Q
b1010 E
b100100100000 F
1#
1'
#1520
0#
0'
#1530
b10 -
b10 L
b10010010000000 ;
b11 Q
b1100 ?
b101 B
b1001001000000 <
b1010 E
b1001001000000 F
1#
1'
#1540
0#
0'
#1550
b11 -
b11 L
b100100100000000 ;
b1000 ?
b110010 A
b110010 )
b110010 9
b110010 J
b110 B
b10010010000000 <
b100 Q
b1010 E
b10010010000000 F
1#
1'
#1560
0#
0'
0%
05
04
1!
1+
#1570
b100 -
b100 L
b1001001000000000 ;
b101 Q
b100 ?
b111001 A
b111001 )
b111001 9
b111001 J
b111 B
b100100100000000 <
b1010 E
b100100100000000 F
1#
1'
#1580
0#
0'
#1590
b101 -
b101 L
b10010010000000000 ;
b0 ?
b110010 A
b110010 )
b110010 9
b110010 J
b1000 B
b1001001000000000 <
b110 Q
b1010 E
b1001001000000000 F
1#
1'
#1600
0#
0'
#1610
b110 -
b110 L
b100100100000000000 ;
b111 Q
0@
0C
00
b101000 ?
bx A
bx )
bx 9
bx J
b1001 B
b10010010000000000 <
b1010 E
b10010010000000000 F
1#
1'
#1620
0#
0'
#1630
b110010 ,
b110010 K
b111 -
b111 L
b1001001000000000000 ;
b1010 B
b100100100000000000 <
b1000 Q
b1010 E
b100100100000000000 F
1#
1'
#1640
0#
0'
#1650
b111001 ,
b111001 K
b1000 -
b1000 L
b10010010000000000000 ;
b1001 Q
b1011 B
b1001001000000000000 <
b1010 E
b1001001000000000000 F
1#
1'
#1660
0#
0'
#1670
b110010 ,
b110010 K
b1001 -
b1001 L
b100100100000000000000 ;
b1100 B
b10010010000000000000 <
b1010 Q
b1010 E
b10010010000000000000 F
1#
1'
#1680
0#
0'
1%
15
14
0!
0+
#1690
b0 ,
b0 K
b0 -
b0 L
0/
b1001001000000000000000 ;
1N
b1011 Q
16
b1101 B
b100100100000000000000 <
b1010 E
b100100100000000000000 F
1#
1'
#1700
0#
0'
#1710
b10010010000000000000000 ;
0/
b1110 B
b1001001000000000000000 <
0N
b1100 Q
06
b1010 E
b1001001000000000000000 F
1#
1'
#1720
0#
0'
#1730
1/
b110000 ,
b110000 K
b100100100000000000000000 ;
1N
b1 Q
b1111 B
b10010010000000000000000 <
b1010 E
b10010010000000000000000 F
1#
1'
#1740
0#
0'
#1750
b1001001000000000000000000 ;
b1 -
b1 L
b10000 B
b100100100000000000000000 <
0N
b10 Q
b1010 E
b100100100000000000000000 F
1#
1'
#1760
0#
0'
#1770
b10 -
b10 L
b10010010000000000000000000 ;
1N
b11 Q
b10001 B
b1001001000000000000000000 <
b1010 E
b1001001000000000000000000 F
1#
1'
#1780
0#
0'
#1790
b11 -
b11 L
b100100100000000000000000000 ;
b10010 B
b10010010000000000000000000 <
0N
b100 Q
b1010 E
b10010010000000000000000000 F
1#
1'
#1800
0#
0'
0%
05
04
1!
1+
#1810
b100 -
b100 L
b1001001000000000000000000000 ;
b101 Q
b10011 B
b100100100000000000000000000 <
b1010 E
b100100100000000000000000000 F
1#
1'
#1820
0#
0'
#1830
b101 -
b101 L
b10010010000000000000000000000 ;
b10100 B
b1001001000000000000000000000 <
b110 Q
b1010 E
b1001001000000000000000000000 F
1#
1'
#1840
0#
0'
#1850
b110 -
b110 L
b100100100000000000000000000000 ;
b111 Q
b10101 B
b10010010000000000000000000000 <
b1010 E
b10010010000000000000000000000 F
1#
1'
#1860
0#
0'
